Workbook

Sheet 0101
D2: PLANILLA DE RECAUDACION DIARIA DE APUESTA Y PREMIOS | M2: 2025
D4: FECHA : | E4: 45931 | G4: RECAUDACION DEL DIA: | I4: 45931
C6: 26 | D6: SALDO DEL DIA ANTERIOR | G6: PREMIOS | H6: 3234613.4
G7: EFECTIVO | H7: 6675360
G8: TOTAL | H8: =H6+H7 -> 9909973.4 | Q8: TICKET ANULADOS | AA8: TICKET PREMIADOS | AL8: TICKET VENDIDOS
C10: MATUTINA | D10: VESPERT. | E10: SIESTA | F10: TARDE | G10: NOCT. | H10: TOTAL | J10: PREMIOS | K10: EFECTIVO | L10: MONEDAS | M10: TOTAL | N10: DIFER. | Q10: M | R10: V | S10: S | T10: T | U10: N | V10: TOTAL | X10: PRES. | Y10: DIFER. | AA10: ANT | AB10: M | AC10: V | AD10: S | AE10: T | AF10: N | AG10: TOTAL | AI10: PRES | AJ10: DIFER. | AL10: M | AM10: V | AN10: S | AO10: T | AP10: N | AQ10: TOTAL | AS10: PRES. | AT10: DIFER.
H11: =SUM(H12:H15) -> 723800
B12: 001 | C12: 163900 | D12: 59400 | E12: 5500 | F12: 46600 | G12: 56800 | H12: =SUM(C12:G12) -> 332200 | I12: 001 | J12: 52500 | K12: 279700 | M12: =SUM(J12:L12) -> 332200 | N12: =H12-M12 -> 0 | Q12: 1 | T12: 3 | V12: =U12+T12+S12+R12+Q12 -> 4 | X12: 0 | Y12: =V12-X12 -> 4 | Z12: V | AA12: 4 | AB12: 1 | AG12: =AF12+AE12+AD12+AC12+AB12+AA12 -> 5 | AI12: 0 | AJ12: =AG12-AI12 -> 5 | AL12: 105 | AM12: 39 | AN12: 4 | AO12: 26 | AP12: 32 | AQ12: =AP12+AO12+AN12+AM12+AL12 -> 206 | AS12: 0 | AT12: =AQ12-AS12 -> 206
B13: 002 | C13: 123600 | D13: 99500 | E13: 5700 | F13: 2600 | G13: 2500 | H13: =SUM(C13:G13) -> 233900 | I13: 002 | J13: 49000 | K13: 184900 | M13: =SUM(J13:L13) -> 233900 | N13: =H13-M13 -> 0 | Q13: 2 | R13: 2 | U13: 1 | V13: =U13+T13+S13+R13+Q13 -> 5 | X13: 0 | Y13: =V13-X13 -> 5 | Z13: L | AA13: 2 | AG13: =AF13+AE13+AD13+AC13+AB13+AA13 -> 2 | AJ13: =AG13-AI13 -> 2 | AL13: 81 | AM13: 77 | AN13: 8 | AO13: 2 | AP13: 2 | AQ13: =AP13+AO13+AN13+AM13+AL13 -> 170 | AS13: 0 | AT13: =AQ13-AS13 -> 170
B14: 003 | C14: 0 | D14: 0 | E14: 39000 | F14: 33750 | G14: 84950 | H14: =SUM(C14:G14) -> 157700 | I14: 003 | K14: 157700 | M14: =SUM(J14:L14) -> 157700 | N14: =H14-M14 -> 0 | V14: =U14+T14+S14+R14+Q14 -> 0 | X14: 0 | Y14: =V14-X14 -> 0 | Z14: M | AG14: =AF14+AE14+AD14+AC14+AB14+AA14 -> 0 | AJ14: =AG14-AI14 -> 0 | AN14: 26 | AO14: 23 | AP14: 49 | AQ14: =AP14+AO14+AN14+AM14+AL14 -> 98 | AS14: 0 | AT14: =AQ14-AS14 -> 98
B15: 004 | H15: =SUM(C15:G15) -> 0 | I15: 004 | J15: 119000 | L15: -119000 | M15: =SUM(J15:L15) -> 0 | N15: =H15-M15 -> 0 | V15: =U15+T15+S15+R15+Q15 -> 0 | X15: 0 | Y15: =V15-X15 -> 0 | AG15: =AF15+AE15+AD15+AC15+AB15+AA15 -> 0 | AJ15: =AG15-AI15 -> 0 | AQ15: =AP15+AO15+AN15+AM15+AL15 -> 0 | AS15: 0 | AT15: =AQ15-AS15 -> 0
B16: 26/001 | C16: 175400 | D16: 129600 | E16: 18200 | F16: 28650 | G16: 86150 | H16: =SUM(C16:G16) -> 438000 | I16: 01 | J16: 219689.47 | K16: 218350 | L16: -39.47 | M16: =SUM(J16:L16) -> 438000 | N16: =H16-M16 -> 0 | Q16: 2 | R16: 1 | T16: 1 | V16: =U16+T16+S16+R16+Q16 -> 4 | X16: 0 | Y16: =V16-X16 -> 4 | Z16: 01 | AA16: 6 | AB16: 1 | AE16: 1 | AG16: =AF16+AE16+AD16+AC16+AB16+AA16 -> 8 | AJ16: =AG16-AI16 -> 8 | AK16: 01 | AL16: 108 | AM16: 103 | AN16: 27 | AO16: 36 | AP16: 68 | AQ16: =AP16+AO16+AN16+AM16+AL16 -> 342 | AS16: 0 | AT16: =AQ16-AS16 -> 342
B17: 26/002 | C17: 361950 | D17: 213750 | E17: 145350 | F17: 148350 | G17: 203350 | H17: =SUM(C17:G17) -> 1072750 | I17: 02 | J17: 442477.78 | K17: 630300 | L17: -27.78 | M17: =SUM(J17:L17) -> 1072750 | N17: =H17-M17 -> 0 | Q17: 3 | R17: 2 | T17: 4 | U17: 1 | V17: =U17+T17+S17+R17+Q17 -> 10 | X17: 0 | Y17: =V17-X17 -> 10 | Z17: 02 | AA17: 16 | AB17: 2 | AC17: 1 | AG17: =AF17+AE17+AD17+AC17+AB17+AA17 -> 19 | AJ17: =AG17-AI17 -> 19 | AK17: 02 | AL17: 228 | AM17: 155 | AN17: 109 | AO17: 125 | AP17: 157 | AQ17: =AP17+AO17+AN17+AM17+AL17 -> 774 | AS17: 0 | AT17: =AQ17-AS17 -> 774
B18: 26/003 | C18: 150500 | D18: 139400 | E18: 85800 | F18: 115600 | G18: 107000 | H18: =SUM(C18:G18) -> 598300 | I18: 03 | J18: 107800 | K18: 490500 | M18: =SUM(J18:L18) -> 598300 | N18: =H18-M18 -> 0 | V18: =U18+T18+S18+R18+Q18 -> 0 | X18: 0 | Y18: =V18-X18 -> 0 | Z18: 03 | AA18: 3 | AB18: 2 | AC18: 1 | AD18: 1 | AE18: 1 | AG18: =AF18+AE18+AD18+AC18+AB18+AA18 -> 8 | AJ18: =AG18-AI18 -> 8 | AK18: 03 | AL18: 105 | AM18: 88 | AN18: 46 | AO18: 56 | AP18: 65 | AQ18: =AP18+AO18+AN18+AM18+AL18 -> 360 | AS18: 0 | AT18: =AQ18-AS18 -> 360
B19: 26/004 | C19: 201950 | D19: 229950 | E19: 60800 | F19: 93900 | G19: 242500 | H19: =SUM(C19:G19) -> 829100 | I19: 04 | J19: 113400 | K19: 711700 | M19: =SUM(J19:L19) -> 825100 | N19: =H19-M19 -> 4000 | V19: =U19+T19+S19+R19+Q19 -> 0 | X19: 0 | Y19: =V19-X19 -> 0 | Z19: 04 | AA19: 2 | AB19: 1 | AC19: 1 | AE19: 2 | AG19: =AF19+AE19+AD19+AC19+AB19+AA19 -> 6 | AJ19: =AG19-AI19 -> 6 | AK19: 04 | AL19: 101 | AM19: 122 | AN19: 45 | AO19: 63 | AP19: 122 | AQ19: =AP19+AO19+AN19+AM19+AL19 -> 453 | AS19: 0 | AT19: =AQ19-AS19 -> 453
B20: 26/005 | C20: 111500 | D20: 120700 | E20: 39100 | F20: 70850 | G20: 105050 | H20: =SUM(C20:G20) -> 447200 | I20: 05 | J20: 258078.95 | K20: 189100 | M20: =SUM(J20:L20) -> 447178.95 | N20: =H20-M20 -> 21.05 | Q20: 1 | U20: 1 | V20: =U20+T20+S20+R20+Q20 -> 2 | X20: 0 | Y20: =V20-X20 -> 2 | Z20: 05 | AA20: 3 | AB20: 1 | AC20: 2 | AE20: 2 | AG20: =AF20+AE20+AD20+AC20+AB20+AA20 -> 8 | AJ20: =AG20-AI20 -> 8 | AK20: 05 | AL20: 56 | AM20: 77 | AN20: 32 | AO20: 48 | AP20: 59 | AQ20: =AP20+AO20+AN20+AM20+AL20 -> 272 | AS20: 0 | AT20: =AQ20-AS20 -> 272
B21: 26/006 | C21: 185600 | D21: 159850 | E21: 69150 | F21: 98350 | G21: 229500 | H21: =SUM(C21:G21) -> 742450 | I21: 06 | J21: 682500 | K21: 60000 | L21: -50 | M21: =SUM(J21:L21) -> 742450 | N21: =H21-M21 -> 0 | Q21: 4 | R21: 2 | S21: 1 | T21: 2 | V21: =U21+T21+S21+R21+Q21 -> 9 | X21: 0 | Y21: =V21-X21 -> 9 | Z21: 06 | AA21: 12 | AB21: 4 | AC21: 3 | AE21: 1 | AG21: =AF21+AE21+AD21+AC21+AB21+AA21 -> 20 | AJ21: =AG21-AI21 -> 20 | AK21: 06 | AL21: 119 | AM21: 121 | AN21: 67 | AO21: 75 | AP21: 141 | AQ21: =AP21+AO21+AN21+AM21+AL21 -> 523 | AS21: 0 | AT21: =AQ21-AS21 -> 523
B22: 26/007 | C22: 236950 | D22: 183950 | E22: 100500 | F22: 130600 | G22: 242950 | H22: =SUM(C22:G22) -> 894950 | I22: 07 | J22: 373100 | K22: 521900 | L22: -50 | M22: =SUM(J22:L22) -> 894950 | N22: =H22-M22 -> 0 | V22: =U22+T22+S22+R22+Q22 -> 0 | X22: 0 | Y22: =V22-X22 -> 0 | Z22: 07 | AA22: 7 | AB22: 4 | AC22: 1 | AG22: =AF22+AE22+AD22+AC22+AB22+AA22 -> 12 | AJ22: =AG22-AI22 -> 12 | AK22: 07 | AL22: 125 | AM22: 141 | AN22: 68 | AO22: 87 | AP22: 154 | AQ22: =AP22+AO22+AN22+AM22+AL22 -> 575 | AS22: 0 | AT22: =AQ22-AS22 -> 575
B23: 26/008 | C23: 43000 | D23: 40800 | E23: 2900 | F23: 28200 | G23: 102800 | H23: =SUM(C23:G23) -> 217700 | I23: 08 | K23: 217700 | M23: =SUM(J23:L23) -> 217700 | N23: =H23-M23 -> 0 | Q23: 1 | R23: 1 | U23: 1 | V23: =U23+T23+S23+R23+Q23 -> 3 | X23: 0 | Y23: =V23-X23 -> 3 | Z23: 08 | AG23: =AF23+AE23+AD23+AC23+AB23+AA23 -> 0 | AJ23: =AG23-AI23 -> 0 | AK23: 08 | AL23: 36 | AM23: 29 | AN23: 4 | AO23: 24 | AP23: 39 | AQ23: =AP23+AO23+AN23+AM23+AL23 -> 132 | AS23: 0 | AT23: =AQ23-AS23 -> 132
B24: 26/009 | C24: 99700 | D24: 127900 | E24: 19800 | F24: 32700 | G24: 87200 | H24: =SUM(C24:G24) -> 367300 | I24: 09 | J24: 86100 | K24: 281200 | M24: =SUM(J24:L24) -> 367300 | N24: =H24-M24 -> 0 | Q24: 2 | R24: 2 | V24: =U24+T24+S24+R24+Q24 -> 4 | X24: 0 | Y24: =V24-X24 -> 4 | Z24: 09 | AA24: 4 | AC24: 4 | AG24: =AF24+AE24+AD24+AC24+AB24+AA24 -> 8 | AJ24: =AG24-AI24 -> 8 | AK24: 09 | AL24: 54 | AM24: 87 | AN24: 20 | AO24: 34 | AP24: 58 | AQ24: =AP24+AO24+AN24+AM24+AL24 -> 253 | AS24: 0 | AT24: =AQ24-AS24 -> 253
B25: 26/010 | H25: =SUM(C25:G25) -> 0 | I25: 10 | M25: =SUM(J25:L25) -> 0 | N25: =H25-M25 -> 0 | V25: =U25+T25+S25+R25+Q25 -> 0 | X25: 0 | Y25: =V25-X25 -> 0 | Z25: 10 | AG25: =AF25+AE25+AD25+AC25+AB25+AA25 -> 0 | AJ25: =AG25-AI25 -> 0 | AK25: 10 | AQ25: =AP25+AO25+AN25+AM25+AL25 -> 0 | AS25: 0 | AT25: =AQ25-AS25 -> 0
B26: 26/011 | C26: 83800 | D26: 107100 | E26: 46050 | F26: 50900 | G26: 74300 | H26: =SUM(C26:G26) -> 362150 | I26: 11 | J26: 25200 | K26: 337000 | L26: -50 | M26: =SUM(J26:L26) -> 362150 | N26: =H26-M26 -> 0 | R26: 1 | S26: 1 | T26: 1 | V26: =U26+T26+S26+R26+Q26 -> 3 | X26: 0 | Y26: =V26-X26 -> 3 | Z26: 11 | AB26: 2 | AC26: 1 | AG26: =AF26+AE26+AD26+AC26+AB26+AA26 -> 3 | AJ26: =AG26-AI26 -> 3 | AK26: 11 | AL26: 66 | AM26: 105 | AN26: 39 | AO26: 48 | AP26: 69 | AQ26: =AP26+AO26+AN26+AM26+AL26 -> 327 | AS26: 0 | AT26: =AQ26-AS26 -> 327
B27: 26/012 | C27: 137600 | D27: 116250 | E27: 84800 | F27: 85200 | G27: 148150 | H27: =SUM(C27:G27) -> 572000 | I27: 12 | J27: 291375 | K27: 280650 | L27: -25 | M27: =SUM(J27:L27) -> 572000 | N27: =H27-M27 -> 0 | R27: 1 | S27: 1 | T27: 1 | V27: =U27+T27+S27+R27+Q27 -> 3 | X27: 0 | Y27: =V27-X27 -> 3 | Z27: 12 | AA27: 5 | AB27: 3 | AC27: 1 | AD27: 1 | AG27: =AF27+AE27+AD27+AC27+AB27+AA27 -> 10 | AJ27: =AG27-AI27 -> 10 | AK27: 12 | AL27: 91 | AM27: 71 | AN27: 62 | AO27: 72 | AP27: 109 | AQ27: =AP27+AO27+AN27+AM27+AL27 -> 405 | AS27: 0 | AT27: =AQ27-AS27 -> 405
B28: 26/013 | C28: 169600 | D28: 200000 | E28: 139800 | F28: 117100 | G28: 199150 | H28: =SUM(C28:G28) -> 825650 | I28: 13 | J28: 262150 | K28: 563500 | M28: =SUM(J28:L28) -> 825650 | N28: =H28-M28 -> 0 | S28: 1 | T28: 1 | V28: =U28+T28+S28+R28+Q28 -> 2 | X28: 0 | Y28: =V28-X28 -> 2 | Z28: 13 | AA28: 5 | AB28: 2 | AC28: 1 | AG28: =AF28+AE28+AD28+AC28+AB28+AA28 -> 8 | AJ28: =AG28-AI28 -> 8 | AK28: 13 | AL28: 104 | AM28: 98 | AN28: 70 | AO28: 61 | AP28: 101 | AQ28: =AP28+AO28+AN28+AM28+AL28 -> 434 | AS28: 0 | AT28: =AQ28-AS28 -> 434
B29: 26/014 | C29: 129500 | D29: 92700 | E29: 21400 | F29: 39500 | G29: 56000 | H29: =SUM(C29:G29) -> 339100 | I29: 14 | J29: 490000 | L29: -150900 | M29: =SUM(J29:L29) -> 339100 | N29: =H29-M29 -> 0 | Q29: 1 | T29: 2 | V29: =U29+T29+S29+R29+Q29 -> 3 | X29: 0 | Y29: =V29-X29 -> 3 | Z29: 14 | AA29: 5 | AB29: 1 | AC29: 1 | AG29: =AF29+AE29+AD29+AC29+AB29+AA29 -> 7 | AJ29: =AG29-AI29 -> 7 | AK29: 14 | AL29: 106 | AM29: 54 | AN29: 16 | AO29: 24 | AP29: 43 | AQ29: =AP29+AO29+AN29+AM29+AL29 -> 243 | AS29: 0 | AT29: =AQ29-AS29 -> 243
B30: 26/015 | H30: =SUM(C30:G30) -> 0 | I30: 15 | M30: =SUM(J30:L30) -> 0 | N30: =H30-M30 -> 0 | V30: =U30+T30+S30+R30+Q30 -> 0 | X30: 0 | Y30: =V30-X30 -> 0 | Z30: 15 | AG30: =AF30+AE30+AD30+AC30+AB30+AA30 -> 0 | AJ30: =AG30-AI30 -> 0 | AK30: 15 | AQ30: =AP30+AO30+AN30+AM30+AL30 -> 0 | AS30: 0 | AT30: =AQ30-AS30 -> 0
B31: 26/016 | C31: 171300 | D31: 147900 | E31: 58500 | F31: 112100 | G31: 115900 | H31: =SUM(C31:G31) -> 605700 | I31: 16 | J31: 1348200 | L31: -742500 | M31: =SUM(J31:L31) -> 605700 | N31: =H31-M31 -> 0 | U31: 1 | V31: =U31+T31+S31+R31+Q31 -> 1 | X31: 0 | Y31: =V31-X31 -> 1 | Z31: 16 | AA31: 8 | AB31: 2 | AC31: 1 | AG31: =AF31+AE31+AD31+AC31+AB31+AA31 -> 11 | AJ31: =AG31-AI31 -> 11 | AK31: 16 | AL31: 112 | AM31: 100 | AN31: 27 | AO31: 56 | AP31: 80 | AQ31: =AP31+AO31+AN31+AM31+AL31 -> 375 | AS31: 0 | AT31: =AQ31-AS31 -> 375
B32: 26/017 | C32: 29300 | D32: 23700 | E32: 15000 | F32: 17800 | G32: 37800 | H32: =SUM(C32:G32) -> 123600 | I32: 17 | K32: 60700 | L32: 62900 | M32: =SUM(J32:L32) -> 123600 | N32: =H32-M32 -> 0 | V32: =U32+T32+S32+R32+Q32 -> 0 | X32: 0 | Y32: =V32-X32 -> 0 | Z32: 17 | AG32: =AF32+AE32+AD32+AC32+AB32+AA32 -> 0 | AJ32: =AG32-AI32 -> 0 | AK32: 17 | AL32: 23 | AM32: 14 | AN32: 10 | AO32: 16 | AP32: 39 | AQ32: =AP32+AO32+AN32+AM32+AL32 -> 102 | AS32: 0 | AT32: =AQ32-AS32 -> 102
B33: 26/018 | H33: =SUM(C33:G33) -> 0 | I33: 18 | M33: =SUM(J33:L33) -> 0 | N33: =H33-M33 -> 0 | V33: =U33+T33+S33+R33+Q33 -> 0 | X33: 0 | Y33: =V33-X33 -> 0 | Z33: 18 | AG33: =AF33+AE33+AD33+AC33+AB33+AA33 -> 0 | AJ33: =AG33-AI33 -> 0 | AK33: 18 | AQ33: =AP33+AO33+AN33+AM33+AL33 -> 0 | AS33: 0 | AT33: =AQ33-AS33 -> 0
B34: 26/019 | H34: =SUM(C34:G34) -> 0 | I34: 19 | M34: =SUM(J34:L34) -> 0 | N34: =H34-M34 -> 0 | V34: =U34+T34+S34+R34+Q34 -> 0 | X34: 0 | Y34: =V34-X34 -> 0 | Z34: 19 | AG34: =AF34+AE34+AD34+AC34+AB34+AA34 -> 0 | AJ34: =AG34-AI34 -> 0 | AK34: 19 | AQ34: =AP34+AO34+AN34+AM34+AL34 -> 0 | AS34: 0 | AT34: =AQ34-AS34 -> 0
C36: =SUM(C12:C34) -> 2575150 | D36: =SUM(D12:D34) -> 2192450 | E36: =SUM(E12:E34) -> 957350 | F36: =SUM(F12:F34) -> 1252750 | G36: =SUM(G12:G34) -> 2182050 | H36: =SUM(H12:H34) -> 9159750 | J36: =SUM(J12:J34) -> 4920571.2 | K36: =SUM(K12:K35) -> 5184900 | L36: =SUM(L13:L34) -> -949742.25 | M36: =SUM(M12:M34) -> 9155728.9 | Q36: TOTAL ANULADAS | U36: =SUM(V12:V34) -> 53 | X36: =SUM(X12:X34) -> 0 | AA36: TOTAL PREMIADAS | AF36: =SUM(AG12:AG34) -> 135 | AI36: =SUM(AI12:AI34) -> 0 | AL36: TOTAL VENDIDAS | AP36: =SUM(AQ12:AQ34) -> 6044 | AS36: =SUM(AS12:AS34) -> 0
B38: DEBEN / SALIDA | J38: PAGAN / ENTRADA
B40: MARTIN GASTOS | D40: 0 | E40: DEPOSITOS | H40: =D41+C72 -> 10002770 | J40: DEUDA DE CAJA s/l/v | L40: 0 | M40: EXCEDENTE | N40: 0
B41: PREMIOS | D41: =J36 -> 4920571.2 | E41: PREST. PALP. | H41: 0 | J41: FALTANTE DE CAJA | L41: 0 | M41: MARTIN | N41: 0
B42: LIBRERIA | D42: 0 | E42: PREST. TELEKINO | H42: 0 | J42: PREST. PALP./ REVISTA | L42: 0 | M42: PREMIOS | N42: 0
B43: LIMPIEZA | D43: 0 | E43: PREST. JGOS. MENORES | H43: 0 | J43: PREST. TELEKINO | L43: 0 | N43: 0
B44: SODA/AGUA | D44: 0 | E44: IMPUESTOS | H44: 0 | J44: PREST. JGOS. MENORES | L44: 0 | N44: 0
B45: GASTOS VARIOS | D45: 0 | E45: OTROS | H45: =SUM(N12:N34) -> 4021.05 | L45: 0 | N45: 0
B47: SUB TOTAL | D47: =D40+D41+D42+D43+D44+D45+H41+H42+H43+H44+H45 -> 4924592.2 | G47: TOTAL | H47: =D47+H40 -> 14927362 | M47: SUB TOTAL | N47: =L40+L41+L42+L43+L44+L45+N40+N41+N42+N43+N44+N45 -> 0
C49: DETALLE RECAUDACION DE CAJA | H49: IMPORTE | J49: FECHA | L49: DETALLE CIERRE DE CAJA
C51: 20000 x | D51: 80 | E51: =20000*D51 -> 1600000 | I51: MAT | L51: 20000 x | M51: 145 | N51: =20000*M51 -> 2900000
C52: 10000 x | D52: 180 | E52: =10000*D52 -> 1800000 | I52: MAT | L52: 10000 x | M52: 128 | N52: =10000*M52 -> 1280000
C53: 2000 x | D53: 332 | E53: =2000*D53 -> 664000 | I53: MAT | L53: 2000 x | M53: 215 | N53: =2000*M53 -> 430000
C54: 1000 x | D54: 193 | E54: =1000*D54 -> 193000 | I54: MAT | L54: 1000 x | M54: 933 | N54: =1000*M54 -> 933000
C55: 500 x | D55: 151 | E55: =500*D55 -> 75500 | I55: MAT | K55: =SUM(H51:H55) -> 0 | L55: 500 x | M55: 107 | N55: =500*M55 -> 53500
C56: 200 x | D56: 68 | E56: =200*D56 -> 13600 | I56: VEP | L56: 200 x | M56: 410 | N56: =200*M56 -> 82000
C57: 100 x | D57: 100 | E57: =100*D57 -> 10000 | I57: VEP | L57: 100 x | M57: 269 | N57: =100*M57 -> 26900
C58: 50 x | D58: 2 | E58: =50*D58 -> 100 | I58: VEP | L58: 50 x | M58: 1789 | N58: =50*M58 -> 89450
C59: 20 x | D59: 0 | E59: =20*D59 -> 0 | I59: VEP | L59: 20 x | M59: 1512 | N59: =20*M59 -> 30240
C60: 10 x | D60: 3 | E60: =10*D60 -> 30 | I60: VEP | K60: =SUM(H56:H60) -> 0 | L60: 10 x | M60: 360 | N60: =10*M60 -> 3600
C61: 5 x | D61: 0 | E61: =5*D61 -> 0 | I61: TAR | L61: 5 x | M61: 0 | N61: =5*M61 -> 0
C62: 2 x | D62: 0 | E62: =2*D62 -> 0 | I62: TAR | L62: 2 x | M62: 0 | N62: =2*M62 -> 0
C63: 1 x | D63: 0 | E63: =1*D63 -> 0 | I63: TAR | L63: 1 x | M63: 0 | N63: =1*M63 -> 0
C64: SUB - TOTAL | E64: =SUM(E51:F63) -> 4356230 | I64: TAR | L64: SUB - TOTAL | N64: =SUM(N51:N63) -> 5828690
I65: TAR | K65: =SUM(H61:H65) -> 0
D66: TOTAL | F66: =D47+E64 -> 9280822.2 | I66: NOC | L66: PREMOS | N66: 119000
I67: NOC | L67: TELEKINOS | N67: 0
D68: DIFERENCIA | F68: =F66-H36 -> 121072.25 | I68: NOC | L68: BOL. S/PREMIOS | N68: 3115613.4
I69: NOC | L69: OTROS | N69: 0
C70: DEPOSITO | I70: NOC | M70: SUB- TOTAL | N70: =SUM(N66:N69) -> 3234613.4
I71: NOC | K71: =SUM(H66:H71) -> 0
C72: 5082198.5
H73: =SUM(H51:H71) -> 0 | M73: TOTAL | N73: =N64+N70 -> 9063303.4
L75: ARQUEO DE CAJA AL CIERRE (COMPOSICION DEL SALDO)
C76: TOTAL DE INGRESO | H76: =H8+H36+N47 -> 19069723 | L76: PREMIOS | N76: =N70 -> 3234613.4
L77: EFECTIVO | N77: =N64 -> 5828690
C78: TOTAL DE EGRESO | H78: =H73+H40+D40+D42+D43+D44+D45+H41+H42+H43+H44+H45 -> 10006791 | L78: TOTAL DE CAJA AL CIERRE | N78: =N70+N64 -> 9063303.4
C80: SALDO DEL DIA | H80: =H76-H78 -> 9062932.7 | L80: DIFERENCIA DE CAJA | N80: =N78-H80 -> 370.75
L81: (+) POSITIVO | M81: (-) NEGATIVO

Sheet 0201
A1: z
D2: PLANILLA DE RECAUDACION DIARIA DE APUESTA Y PREMIOS | M2: ='0101'!M2 -> 2025
D4: FECHA : | E4: 45170 | G4: RECAUDACION DEL DIA: | I4: 45169
C6: 26 | D6: SALDO DEL DIA ANTERIOR | G6: PREMIOS | H6: ='0101'!N76 -> 3234613.4
G7: EFECTIVO | H7: ='0101'!N77 -> 5828690
G8: TOTAL | H8: =H6+H7 -> 9063303.4 | Q8: TICKET ANULADOS | AA8: TICKET PREMIADOS | AL8: TICKET VENDIDOS
C10: MATUTINA | D10: VESPERT. | E10: SIESTA | F10: TARDE | G10: NOCT. | H10: TOTAL | J10: PREMIOS | K10: EFECTIVO | L10: MONEDAS | M10: TOTAL | N10: DIFER. | Q10: M | R10: V | S10: S | T10: T | U10: N | V10: TOTAL | X10: PRES. | Y10: DIFER. | AA10: ANT | AB10: M | AC10: V | AD10: S | AE10: T | AF10: N | AG10: TOTAL | AI10: PRES | AJ10: DIFER. | AL10: M | AM10: V | AN10: S | AO10: T | AP10: N | AQ10: TOTAL | AS10: PRES. | AT10: DIFER.
H11: =SUM(H12:H15) -> 626400
B12: 001 | C12: 91000 | D12: 32700 | E12: 3000 | F12: 27000 | G12: 83700 | H12: =SUM(C12:G12) -> 237400 | I12: 001 | J12: 21000 | K12: 215300 | M12: =SUM(J12:L12) -> 236300 | N12: =H12-M12 -> 1100 | R12: 1 | U12: 4 | V12: =U12+T12+S12+R12+Q12 -> 5 | X12: 0 | Y12: =V12-X12 -> 5 | Z12: V | AA12: 2 | AG12: =AF12+AE12+AD12+AC12+AB12+AA12 -> 2 | AI12: 0 | AJ12: =AG12-AI12 -> 2 | AL12: 58 | AM12: 25 | AN12: 2 | AO12: 24 | AP12: 51 | AQ12: =AP12+AO12+AN12+AM12+AL12 -> 160 | AS12: 0 | AT12: =AQ12-AS12 -> 160
B13: 002 | H13: =SUM(C13:G13) -> 0 | I13: 002 | M13: =SUM(J13:L13) -> 0 | N13: =H13-M13 -> 0 | V13: =U13+T13+S13+R13+Q13 -> 0 | X13: 0 | Y13: =V13-X13 -> 0 | Z13: L | AG13: =AF13+AE13+AD13+AC13+AB13+AA13 -> 0 | AJ13: =AG13-AI13 -> 0 | AQ13: =AP13+AO13+AN13+AM13+AL13 -> 0 | AS13: 0 | AT13: =AQ13-AS13 -> 0
B14: 003 | C14: 86950 | D14: 93800 | E14: 63200 | F14: 51450 | G14: 93600 | H14: =SUM(C14:G14) -> 389000 | I14: 003 | J14: 19600 | K14: 369400 | M14: =SUM(J14:L14) -> 389000 | N14: =H14-M14 -> 0 | U14: 1 | V14: =U14+T14+S14+R14+Q14 -> 1 | X14: 0 | Y14: =V14-X14 -> 1 | Z14: M | AA14: 2 | AG14: =AF14+AE14+AD14+AC14+AB14+AA14 -> 2 | AJ14: =AG14-AI14 -> 2 | AL14: 58 | AM14: 55 | AN14: 34 | AO14: 34 | AP14: 56 | AQ14: =AP14+AO14+AN14+AM14+AL14 -> 237 | AS14: 0 | AT14: =AQ14-AS14 -> 237
B15: 004 | H15: =SUM(C15:G15) -> 0 | I15: 004 | M15: =SUM(J15:L15) -> 0 | N15: =H15-M15 -> 0 | V15: =U15+T15+S15+R15+Q15 -> 0 | X15: 0 | Y15: =V15-X15 -> 0 | AG15: =AF15+AE15+AD15+AC15+AB15+AA15 -> 0 | AJ15: =AG15-AI15 -> 0 | AQ15: =AP15+AO15+AN15+AM15+AL15 -> 0 | AS15: 0 | AT15: =AQ15-AS15 -> 0
B16: 26/001 | C16: 129400 | D16: 33700 | E16: 25500 | F16: 45200 | G16: 85700 | H16: =SUM(C16:G16) -> 319500 | I16: 01 | J16: 1228500 | L16: -909000 | M16: =SUM(J16:L16) -> 319500 | N16: =H16-M16 -> 0 | R16: 1 | V16: =U16+T16+S16+R16+Q16 -> 1 | X16: 0 | Y16: =V16-X16 -> 1 | Z16: 01 | AA16: 1 | AB16: 3 | AG16: =AF16+AE16+AD16+AC16+AB16+AA16 -> 4 | AJ16: =AG16-AI16 -> 4 | AK16: 01 | AL16: 83 | AM16: 36 | AN16: 20 | AO16: 37 | AP16: 52 | AQ16: =AP16+AO16+AN16+AM16+AL16 -> 228 | AS16: 0 | AT16: =AQ16-AS16 -> 228
B17: 26/002 | C17: 246310 | D17: 207250 | E17: 120300 | F17: 161300 | G17: 233100 | H17: =SUM(C17:G17) -> 968260 | I17: 02 | J17: 108150 | K17: 860000 | M17: =SUM(J17:L17) -> 968150 | N17: =H17-M17 -> 110 | V17: =U17+T17+S17+R17+Q17 -> 0 | X17: 0 | Y17: =V17-X17 -> 0 | Z17: 02 | AA17: 7 | AB17: 4 | AC17: 2 | AE17: 1 | AG17: =AF17+AE17+AD17+AC17+AB17+AA17 -> 14 | AJ17: =AG17-AI17 -> 14 | AK17: 02 | AL17: 183 | AM17: 163 | AN17: 101 | AO17: 107 | AP17: 151 | AQ17: =AP17+AO17+AN17+AM17+AL17 -> 705 | AS17: 0 | AT17: =AQ17-AS17 -> 705
B18: 26/003 | C18: 131000 | D18: 147400 | E18: 74800 | F18: 118050 | G18: 158050 | H18: =SUM(C18:G18) -> 629300 | I18: 03 | J18: 227675 | K18: 401630 | L18: -5 | M18: =SUM(J18:L18) -> 629300 | N18: =H18-M18 -> 0 | V18: =U18+T18+S18+R18+Q18 -> 0 | X18: 0 | Y18: =V18-X18 -> 0 | Z18: 03 | AB18: 4 | AC18: 1 | AE18: 3 | AG18: =AF18+AE18+AD18+AC18+AB18+AA18 -> 8 | AJ18: =AG18-AI18 -> 8 | AK18: 03 | AL18: 66 | AM18: 69 | AN18: 40 | AO18: 58 | AP18: 91 | AQ18: =AP18+AO18+AN18+AM18+AL18 -> 324 | AS18: 0 | AT18: =AQ18-AS18 -> 324
B19: 26/004 | C19: 113600 | D19: 81650 | E19: 36850 | F19: 45900 | G19: 163600 | H19: =SUM(C19:G19) -> 441600 | I19: 04 | J19: 312900 | K19: 124700 | M19: =SUM(J19:L19) -> 437600 | N19: =H19-M19 -> 4000 | R19: 1 | U19: 1 | V19: =U19+T19+S19+R19+Q19 -> 2 | X19: 0 | Y19: =V19-X19 -> 2 | Z19: 04 | AA19: 2 | AB19: 1 | AC19: 1 | AD19: 2 | AG19: =AF19+AE19+AD19+AC19+AB19+AA19 -> 6 | AJ19: =AG19-AI19 -> 6 | AK19: 04 | AL19: 65 | AM19: 54 | AN19: 29 | AO19: 31 | AP19: 82 | AQ19: =AP19+AO19+AN19+AM19+AL19 -> 261 | AS19: 0 | AT19: =AQ19-AS19 -> 261
B20: 26/005 | C20: 62800 | D20: 96250 | E20: 35350 | F20: 100800 | G20: 76100 | H20: =SUM(C20:G20) -> 371300 | I20: 05 | J20: 84000 | K20: 287300 | M20: =SUM(J20:L20) -> 371300 | N20: =H20-M20 -> 0 | Q20: 1 | T20: 1 | V20: =U20+T20+S20+R20+Q20 -> 2 | X20: 0 | Y20: =V20-X20 -> 2 | Z20: 05 | AC20: 2 | AG20: =AF20+AE20+AD20+AC20+AB20+AA20 -> 2 | AJ20: =AG20-AI20 -> 2 | AK20: 05 | AL20: 47 | AM20: 55 | AN20: 29 | AO20: 41 | AP20: 43 | AQ20: =AP20+AO20+AN20+AM20+AL20 -> 215 | AS20: 0 | AT20: =AQ20-AS20 -> 215
B21: 26/006 | C21: 170350 | D21: 128200 | E21: 71400 | F21: 108800 | G21: 155550 | H21: =SUM(C21:G21) -> 634300 | I21: 06 | J21: 316750 | K21: 317600 | L21: -50 | M21: =SUM(J21:L21) -> 634300 | N21: =H21-M21 -> 0 | Q21: 1 | R21: 2 | T21: 4 | U21: 1 | V21: =U21+T21+S21+R21+Q21 -> 8 | X21: 0 | Y21: =V21-X21 -> 8 | Z21: 06 | AA21: 6 | AB21: 9 | AC21: 6 | AD21: 1 | AE21: 1 | AG21: =AF21+AE21+AD21+AC21+AB21+AA21 -> 23 | AJ21: =AG21-AI21 -> 23 | AK21: 06 | AL21: 109 | AM21: 96 | AN21: 51 | AO21: 75 | AP21: 108 | AQ21: =AP21+AO21+AN21+AM21+AL21 -> 439 | AS21: 0 | AT21: =AQ21-AS21 -> 439
B22: 26/007 | C22: 157600 | D22: 156300 | E22: 96500 | F22: 161500 | G22: 159550 | H22: =SUM(C22:G22) -> 731450 | I22: 07 | J22: 186900 | K22: 544500 | L22: 50 | M22: =SUM(J22:L22) -> 731450 | N22: =H22-M22 -> 0 | V22: =U22+T22+S22+R22+Q22 -> 0 | X22: 0 | Y22: =V22-X22 -> 0 | Z22: 07 | AA22: 3 | AB22: 1 | AC22: 1 | AD22: 1 | AG22: =AF22+AE22+AD22+AC22+AB22+AA22 -> 6 | AJ22: =AG22-AI22 -> 6 | AK22: 07 | AL22: 81 | AM22: 105 | AN22: 60 | AO22: 93 | AP22: 98 | AQ22: =AP22+AO22+AN22+AM22+AL22 -> 437 | AS22: 0 | AT22: =AQ22-AS22 -> 437
B23: 26/008 | C23: 53900 | D23: 55700 | E23: 4000 | F23: 47500 | G23: 59300 | H23: =SUM(C23:G23) -> 220400 | I23: 08 | J23: 185500 | K23: 34900 | M23: =SUM(J23:L23) -> 220400 | N23: =H23-M23 -> 0 | V23: =U23+T23+S23+R23+Q23 -> 0 | X23: 0 | Y23: =V23-X23 -> 0 | Z23: 08 | AA23: 1 | AB23: 4 | AE23: 2 | AG23: =AF23+AE23+AD23+AC23+AB23+AA23 -> 7 | AJ23: =AG23-AI23 -> 7 | AK23: 08 | AL23: 38 | AM23: 35 | AN23: 5 | AO23: 23 | AP23: 42 | AQ23: =AP23+AO23+AN23+AM23+AL23 -> 143 | AS23: 0 | AT23: =AQ23-AS23 -> 143
B24: 26/009 | C24: 98300 | D24: 73000 | E24: 25800 | F24: 39200 | G24: 136700 | H24: =SUM(C24:G24) -> 373000 | I24: 09 | J24: 51100 | K24: 323900 | L24: -2000 | M24: =SUM(J24:L24) -> 373000 | N24: =H24-M24 -> 0 | Q24: 1 | U24: 3 | V24: =U24+T24+S24+R24+Q24 -> 4 | X24: 0 | Y24: =V24-X24 -> 4 | Z24: 09 | AA24: 3 | AB24: 1 | AG24: =AF24+AE24+AD24+AC24+AB24+AA24 -> 4 | AJ24: =AG24-AI24 -> 4 | AK24: 09 | AL24: 48 | AM24: 51 | AN24: 18 | AO24: 30 | AP24: 71 | AQ24: =AP24+AO24+AN24+AM24+AL24 -> 218 | AS24: 0 | AT24: =AQ24-AS24 -> 218
B25: 26/010 | H25: =SUM(C25:G25) -> 0 | I25: 10 | M25: =SUM(J25:L25) -> 0 | N25: =H25-M25 -> 0 | V25: =U25+T25+S25+R25+Q25 -> 0 | X25: 0 | Y25: =V25-X25 -> 0 | Z25: 10 | AG25: =AF25+AE25+AD25+AC25+AB25+AA25 -> 0 | AJ25: =AG25-AI25 -> 0 | AK25: 10 | AQ25: =AP25+AO25+AN25+AM25+AL25 -> 0 | AS25: 0 | AT25: =AQ25-AS25 -> 0
B26: 26/011 | C26: 71700 | D26: 57100 | E26: 19900 | F26: 31900 | G26: 53600 | H26: =SUM(C26:G26) -> 234200 | I26: 11 | J26: 98700 | K26: 135500 | M26: =SUM(J26:L26) -> 234200 | N26: =H26-M26 -> 0 | Q26: 1 | V26: =U26+T26+S26+R26+Q26 -> 1 | X26: 0 | Y26: =V26-X26 -> 1 | Z26: 11 | AA26: 3 | AB26: 2 | AC26: 1 | AG26: =AF26+AE26+AD26+AC26+AB26+AA26 -> 6 | AJ26: =AG26-AI26 -> 6 | AK26: 11 | AL26: 56 | AM26: 53 | AN26: 20 | AO26: 39 | AP26: 45 | AQ26: =AP26+AO26+AN26+AM26+AL26 -> 213 | AS26: 0 | AT26: =AQ26-AS26 -> 213
B27: 26/012 | C27: 61250 | D27: 75800 | E27: 74850 | F27: 86000 | G27: 110650 | H27: =SUM(C27:G27) -> 408550 | I27: 12 | J27: 240500 | K27: 168050 | M27: =SUM(J27:L27) -> 408550 | N27: =H27-M27 -> 0 | Q27: 1 | R27: 2 | T27: 2 | V27: =U27+T27+S27+R27+Q27 -> 5 | X27: 0 | Y27: =V27-X27 -> 5 | Z27: 12 | AA27: 3 | AB27: 2 | AD27: 1 | AE27: 1 | AG27: =AF27+AE27+AD27+AC27+AB27+AA27 -> 7 | AJ27: =AG27-AI27 -> 7 | AK27: 12 | AL27: 49 | AM27: 61 | AN27: 56 | AO27: 67 | AP27: 102 | AQ27: =AP27+AO27+AN27+AM27+AL27 -> 335 | AS27: 0 | AT27: =AQ27-AS27 -> 335
B28: 26/013 | C28: 159000 | D28: 155700 | E28: 89800 | F28: 109500 | G28: 209600 | H28: =SUM(C28:G28) -> 723600 | I28: 13 | J28: 330750 | K28: 392900 | L28: -50 | M28: =SUM(J28:L28) -> 723600 | N28: =H28-M28 -> 0 | Q28: 2 | S28: 1 | T28: 2 | U28: 1 | V28: =U28+T28+S28+R28+Q28 -> 6 | X28: 0 | Y28: =V28-X28 -> 6 | Z28: 13 | AA28: 1 | AB28: 1 | AD28: 2 | AG28: =AF28+AE28+AD28+AC28+AB28+AA28 -> 4 | AJ28: =AG28-AI28 -> 4 | AK28: 13 | AL28: 103 | AM28: 85 | AN28: 46 | AO28: 39 | AP28: 100 | AQ28: =AP28+AO28+AN28+AM28+AL28 -> 373 | AS28: 0 | AT28: =AQ28-AS28 -> 373
B29: 26/014 | C29: 144400 | D29: 147650 | E29: 41300 | F29: 24300 | G29: 50300 | H29: =SUM(C29:G29) -> 407950 | I29: 14 | J29: 42000 | K29: 366050 | L29: 100 | M29: =SUM(J29:L29) -> 408150 | N29: =H29-M29 -> -200 | R29: 2 | V29: =U29+T29+S29+R29+Q29 -> 2 | X29: 0 | Y29: =V29-X29 -> 2 | Z29: 14 | AB29: 2 | AG29: =AF29+AE29+AD29+AC29+AB29+AA29 -> 2 | AJ29: =AG29-AI29 -> 2 | AK29: 14 | AL29: 87 | AM29: 87 | AN29: 32 | AO29: 18 | AP29: 36 | AQ29: =AP29+AO29+AN29+AM29+AL29 -> 260 | AS29: 0 | AT29: =AQ29-AS29 -> 260
B30: 26/015 | H30: =SUM(C30:G30) -> 0 | I30: 15 | M30: =SUM(J30:L30) -> 0 | N30: =H30-M30 -> 0 | V30: =U30+T30+S30+R30+Q30 -> 0 | X30: 0 | Y30: =V30-X30 -> 0 | Z30: 15 | AG30: =AF30+AE30+AD30+AC30+AB30+AA30 -> 0 | AJ30: =AG30-AI30 -> 0 | AK30: 15 | AQ30: =AP30+AO30+AN30+AM30+AL30 -> 0 | AS30: 0 | AT30: =AQ30-AS30 -> 0
B31: 26/016 | C31: 124900 | D31: 143300 | E31: 52100 | F31: 127900 | G31: 138500 | H31: =SUM(C31:G31) -> 586700 | I31: 16 | J31: 70700 | K31: 515000 | M31: =SUM(J31:L31) -> 585700 | N31: =H31-M31 -> 1000 | T31: 3 | V31: =U31+T31+S31+R31+Q31 -> 3 | X31: 0 | Y31: =V31-X31 -> 3 | Z31: 16 | AD31: 1 | AE31: 1 | AG31: =AF31+AE31+AD31+AC31+AB31+AA31 -> 2 | AJ31: =AG31-AI31 -> 2 | AK31: 16 | AL31: 60 | AM31: 76 | AN31: 27 | AO31: 64 | AP31: 80 | AQ31: =AP31+AO31+AN31+AM31+AL31 -> 307 | AS31: 0 | AT31: =AQ31-AS31 -> 307
B32: 26/017 | C32: 29500 | D32: 43200 | E32: 22600 | F32: 28700 | G32: 45600 | H32: =SUM(C32:G32) -> 169600 | I32: 17 | J32: 42000 | K32: 127600 | M32: =SUM(J32:L32) -> 169600 | N32: =H32-M32 -> 0 | Q32: 2 | V32: =U32+T32+S32+R32+Q32 -> 2 | X32: 0 | Y32: =V32-X32 -> 2 | Z32: 17 | AA32: 1 | AB32: 1 | AC32: 1 | AE32: 1 | AG32: =AF32+AE32+AD32+AC32+AB32+AA32 -> 4 | AJ32: =AG32-AI32 -> 4 | AK32: 17 | AL32: 25 | AM32: 32 | AN32: 18 | AO32: 21 | AP32: 38 | AQ32: =AP32+AO32+AN32+AM32+AL32 -> 134 | AS32: 0 | AT32: =AQ32-AS32 -> 134
B33: 26/018 | H33: =SUM(C33:G33) -> 0 | I33: 18 | M33: =SUM(J33:L33) -> 0 | N33: =H33-M33 -> 0 | V33: =U33+T33+S33+R33+Q33 -> 0 | X33: 0 | Y33: =V33-X33 -> 0 | Z33: 18 | AG33: =AF33+AE33+AD33+AC33+AB33+AA33 -> 0 | AJ33: =AG33-AI33 -> 0 | AK33: 18 | AQ33: =AP33+AO33+AN33+AM33+AL33 -> 0 | AS33: 0 | AT33: =AQ33-AS33 -> 0
B34: 26/019 | H34: =SUM(C34:G34) -> 0 | I34: 19 | M34: =SUM(J34:L34) -> 0 | N34: =H34-M34 -> 0 | V34: =U34+T34+S34+R34+Q34 -> 0 | X34: 0 | Y34: =V34-X34 -> 0 | Z34: 19 | AG34: =AF34+AE34+AD34+AC34+AB34+AA34 -> 0 | AJ34: =AG34-AI34 -> 0 | AK34: 19 | AQ34: =AP34+AO34+AN34+AM34+AL34 -> 0 | AS34: 0 | AT34: =AQ34-AS34 -> 0
C36: =SUM(C12:C34) -> 1931960 | D36: =SUM(D12:D34) -> 1728700 | E36: =SUM(E12:E34) -> 857250 | F36: =SUM(F12:F34) -> 1315000 | G36: =SUM(G12:G34) -> 2013200 | H36: =SUM(H12:H34) -> 7846110 | J36: =SUM(J12:J34) -> 3566725 | K36: =SUM(K12:K35) -> 5184330 | L36: =SUM(L13:L34) -> -910955 | M36: =SUM(M12:M34) -> 7840100 | Q36: TOTAL ANULADAS | U36: =SUM(V12:V34) -> 42 | X36: =SUM(X12:X34) -> 0 | AA36: TOTAL PREMIADAS | AF36: =SUM(AG12:AG34) -> 103 | AI36: =SUM(AI12:AI34) -> 0 | AL36: TOTAL VENDIDAS | AP36: =SUM(AQ12:AQ34) -> 4989 | AS36: =SUM(AS12:AS34) -> 0
B38: DEBEN / SALIDA | J38: PAGAN / ENTRADA
B40: MARTIN GASTOS | D40: 0 | E40: DEPOSITOS | H40: =D41+C72 -> 9159750 | J40: DEUDA DE CAJA s/l/v | L40: 0 | M40: EXCEDENTE | N40: 0
B41: PREMIOS | D41: =J36 -> 3566725 | E41: PREST. PALP. | H41: 0 | J41: FALTANTE DE CAJA | L41: 0 | M41: MARTIN | N41: 0
B42: LIBRERIA | D42: 0 | E42: PREST. TELEKINO | H42: 0 | J42: PREST. PALP./ REVISTA | L42: 0 | M42: PREMIOS | N42: 0
B43: LIMPIEZA | D43: 0 | E43: PREST. JGOS. MENORES | H43: 0 | J43: PREST. TELEKINO | L43: 0 | N43: 0
B44: SODA/AGUA | D44: 0 | E44: IMPUESTOS | H44: 0 | J44: PREST. JGOS. MENORES | L44: 0 | N44: 0
B45: GASTOS VARIOS | D45: 0 | E45: OTROS | H45: =SUM(N12:N34) -> 6010 | L45: 0 | N45: 0
B47: SUB TOTAL | D47: =D40+D41+D42+D43+D44+D45+H41+H42+H43+H44+H45 -> 3572735 | G47: TOTAL | H47: =D47+H40 -> 12732485 | M47: SUB TOTAL | N47: =L40+L41+L42+L43+L44+L45+N40+N41+N42+N43+N44+N45 -> 0
C49: DETALLE RECAUDACION DE CAJA | H49: IMPORTE | J49: FECHA | L49: DETALLE CIERRE DE CAJA
C51: 20000 x | D51: 40 | E51: =20000*D51 -> 800000 | I51: MAT | L51: 20000 x | M51: 86 | N51: =20000*M51 -> 1720000
C52: 10000 x | D52: 247 | E52: =10000*D52 -> 2470000 | I52: MAT | L52: 10000 x | M52: 186 | N52: =10000*M52 -> 1860000
C53: 2000 x | D53: 387 | E53: =2000*D53 -> 774000 | I53: MAT | L53: 2000 x | M53: 0 | N53: =2000*M53 -> 0
C54: 1000 x | D54: 22 | E54: =1000*D54 -> 22000 | I54: MAT | L54: 1000 x | M54: 571 | N54: =1000*M54 -> 571000
C55: 500 x | D55: 186 | E55: =500*D55 -> 93000 | I55: MAT | K55: =SUM(H51:H55) -> 0 | L55: 500 x | M55: 276 | N55: =500*M55 -> 138000
C56: 200 x | D56: 497 | E56: =200*D56 -> 99400 | I56: VEP | L56: 200 x | M56: 906 | N56: =200*M56 -> 181200
C57: 100 x | D57: 153 | E57: =100*D57 -> 15300 | I57: VEP | L57: 100 x | M57: 322 | N57: =100*M57 -> 32200
C58: 50 x | D58: 2 | E58: =50*D58 -> 100 | I58: VEP | L58: 50 x | M58: 1791 | N58: =50*M58 -> 89550
C59: 20 x | D59: 1 | E59: =20*D59 -> 20 | I59: VEP | L59: 20 x | M59: 1512 | N59: =20*M59 -> 30240
C60: 10 x | D60: 1 | E60: =10*D60 -> 10 | I60: VEP | K60: =SUM(H56:H60) -> 0 | L60: 10 x | M60: 360 | N60: =10*M60 -> 3600
C61: 5 x | D61: 0 | E61: =5*D61 -> 0 | I61: TAR | L61: 5 x | M61: 0 | N61: =5*M61 -> 0
C62: 2 x | D62: 0 | E62: =2*D62 -> 0 | I62: TAR | L62: 2 x | M62: 0 | N62: =2*M62 -> 0
C63: 1 x | D63: 0 | E63: =1*D63 -> 0 | I63: TAR | L63: 1 x | M63: 0 | N63: =1*M63 -> 0
C64: SUB - TOTAL | E64: =SUM(E51:F63) -> 4273830 | I64: TAR | L64: SUB - TOTAL | N64: =SUM(N51:N63) -> 4625790
I65: TAR | K65: =SUM(H61:H65) -> 0
D66: TOTAL | F66: =D47+E64 -> 7846565 | I66: NOC | L66: PREMOS | N66: 0
I67: NOC | L67: TELEKINOS | N67: 0
D68: DIFERENCIA | F68: =F66-H36 -> 455 | I68: NOC | L68: BOL. S/PREMIOS | N68: 3115613.4
I69: NOC | L69: OTROS | N69: 0
C70: DEPOSITO | I70: NOC | M70: SUB- TOTAL | N70: =SUM(N66:N69) -> 3115613.4
I71: NOC | K71: =SUM(H66:H71) -> 0
C72: 5593025
H73: =SUM(H51:H71) -> 0 | M73: TOTAL | N73: =N64+N70 -> 7741403.4
L75: ARQUEO DE CAJA AL CIERRE (COMPOSICION DEL SALDO)
C76: TOTAL DE INGRESO | H76: =H8+H36+N47 -> 16909413 | L76: PREMIOS | N76: =N70 -> 3115613.4
L77: EFECTIVO | N77: =N64 -> 4625790
C78: TOTAL DE EGRESO | H78: =H73+H40+D40+D42+D43+D44+D45+H41+H42+H43+H44+H45 -> 9165760 | L78: TOTAL DE CAJA AL CIERRE | N78: =N70+N64 -> 7741403.4
C80: SALDO DEL DIA | H80: =H76-H78 -> 7743653.4 | L80: DIFERENCIA DE CAJA | N80: =N78-H80 -> -2250
L81: (+) POSITIVO | M81: (-) NEGATIVO

Sheet 0301
A1: z
D2: PLANILLA DE RECAUDACION DIARIA DE APUESTA Y PREMIOS | M2: ='0101'!M2 -> 2025
D4: FECHA : | E4: 45170 | G4: RECAUDACION DEL DIA: | I4: 45169
C6: 26 | D6: SALDO DEL DIA ANTERIOR | G6: PREMIOS | H6: ='0201'!N76 -> 3115613.4
G7: EFECTIVO | H7: ='0201'!N77 -> 4625790
G8: TOTAL | H8: =H6+H7 -> 7741403.4 | Q8: TICKET ANULADOS | AA8: TICKET PREMIADOS | AL8: TICKET VENDIDOS
C10: MATUTINA | D10: VESPERT. | E10: SIESTA | F10: TARDE | G10: NOCT. | H10: TOTAL | J10: PREMIOS | K10: EFECTIVO | L10: MONEDAS | M10: TOTAL | N10: DIFER. | Q10: M | R10: V | S10: S | T10: T | U10: N | V10: TOTAL | X10: PRES. | Y10: DIFER. | AA10: ANT | AB10: M | AC10: V | AD10: S | AE10: T | AF10: N | AG10: TOTAL | AI10: PRES | AJ10: DIFER. | AL10: M | AM10: V | AN10: S | AO10: T | AP10: N | AQ10: TOTAL | AS10: PRES. | AT10: DIFER.
H11: =SUM(H12:H15) -> 1010900
B12: 001 | C12: 160100 | D12: 50550 | E12: 8250 | F12: 28200 | G12: 82700 | H12: =SUM(C12:G12) -> 329800 | I12: 001 | J12: 27724.94 | K12: 300100 | M12: =SUM(J12:L12) -> 327824.94 | N12: =H12-M12 -> 1975.06 | V12: =U12+T12+S12+R12+Q12 -> 0 | X12: 0 | Y12: =V12-X12 -> 0 | Z12: V | AA12: 2 | AC12: 1 | AG12: =AF12+AE12+AD12+AC12+AB12+AA12 -> 3 | AI12: 0 | AJ12: =AG12-AI12 -> 3 | AL12: 85 | AM12: 26 | AN12: 10 | AO12: 11 | AP12: 37 | AQ12: =AP12+AO12+AN12+AM12+AL12 -> 169 | AS12: 0 | AT12: =AQ12-AS12 -> 169
B13: 002 | H13: =SUM(C13:G13) -> 0 | I13: 002 | M13: =SUM(J13:L13) -> 0 | N13: =H13-M13 -> 0 | V13: =U13+T13+S13+R13+Q13 -> 0 | X13: 0 | Y13: =V13-X13 -> 0 | Z13: L | AG13: =AF13+AE13+AD13+AC13+AB13+AA13 -> 0 | AJ13: =AG13-AI13 -> 0 | AQ13: =AP13+AO13+AN13+AM13+AL13 -> 0 | AS13: 0 | AT13: =AQ13-AS13 -> 0
B14: 003 | C14: 276650 | D14: 188350 | E14: 58900 | F14: 50900 | G14: 106300 | H14: =SUM(C14:G14) -> 681100 | I14: 003 | J14: 182260.91 | K14: 498839.09 | M14: =SUM(J14:L14) -> 681100 | N14: =H14-M14 -> 0 | T14: 2 | V14: =U14+T14+S14+R14+Q14 -> 2 | X14: 0 | Y14: =V14-X14 -> 2 | Z14: M | AA14: 1 | AC14: 3 | AG14: =AF14+AE14+AD14+AC14+AB14+AA14 -> 4 | AJ14: =AG14-AI14 -> 4 | AL14: 114 | AM14: 93 | AN14: 32 | AO14: 27 | AP14: 50 | AQ14: =AP14+AO14+AN14+AM14+AL14 -> 316 | AS14: 0 | AT14: =AQ14-AS14 -> 316
B15: 004 | H15: =SUM(C15:G15) -> 0 | I15: 004 | M15: =SUM(J15:L15) -> 0 | N15: =H15-M15 -> 0 | V15: =U15+T15+S15+R15+Q15 -> 0 | X15: 0 | Y15: =V15-X15 -> 0 | AG15: =AF15+AE15+AD15+AC15+AB15+AA15 -> 0 | AJ15: =AG15-AI15 -> 0 | AQ15: =AP15+AO15+AN15+AM15+AL15 -> 0 | AS15: 0 | AT15: =AQ15-AS15 -> 0
B16: 26/001 | C16: 125800 | D16: 92100 | E16: 25800 | F16: 44400 | G16: 106400 | H16: =SUM(C16:G16) -> 394500 | I16: 01 | J16: 100873.41 | K16: 293626.59 | M16: =SUM(J16:L16) -> 394500 | N16: =H16-M16 -> 0 | Q16: 3 | V16: =U16+T16+S16+R16+Q16 -> 3 | X16: 0 | Y16: =V16-X16 -> 3 | Z16: 01 | AB16: 4 | AG16: =AF16+AE16+AD16+AC16+AB16+AA16 -> 4 | AJ16: =AG16-AI16 -> 4 | AK16: 01 | AL16: 80 | AM16: 63 | AN16: 15 | AO16: 26 | AP16: 67 | AQ16: =AP16+AO16+AN16+AM16+AL16 -> 251 | AS16: 0 | AT16: =AQ16-AS16 -> 251
B17: 26/002 | C17: 305100 | D17: 239250 | E17: 162300 | F17: 152050 | G17: 330900 | H17: =SUM(C17:G17) -> 1189600 | I17: 02 | J17: 715607.96 | K17: 473992.04 | M17: =SUM(J17:L17) -> 1189600 | N17: =H17-M17 -> 0 | Q17: 1 | R17: 2 | V17: =U17+T17+S17+R17+Q17 -> 3 | X17: 0 | Y17: =V17-X17 -> 3 | Z17: 02 | AA17: 5 | AB17: 4 | AC17: 12 | AD17: 2 | AE17: 1 | AG17: =AF17+AE17+AD17+AC17+AB17+AA17 -> 24 | AJ17: =AG17-AI17 -> 24 | AK17: 02 | AL17: 193 | AM17: 145 | AN17: 147 | AO17: 118 | AP17: 204 | AQ17: =AP17+AO17+AN17+AM17+AL17 -> 807 | AS17: 0 | AT17: =AQ17-AS17 -> 807
B18: 26/003 | C18: 104100 | D18: 76000 | E18: 67400 | F18: 57900 | G18: 96550 | H18: =SUM(C18:G18) -> 401950 | I18: 03 | J18: 380621.83 | K18: 21328.17 | M18: =SUM(J18:L18) -> 401950 | N18: =H18-M18 -> 0 | V18: =U18+T18+S18+R18+Q18 -> 0 | X18: 0 | Y18: =V18-X18 -> 0 | Z18: 03 | AB18: 1 | AC18: 4 | AD18: 2 | AE18: 1 | AG18: =AF18+AE18+AD18+AC18+AB18+AA18 -> 8 | AJ18: =AG18-AI18 -> 8 | AK18: 03 | AL18: 58 | AM18: 49 | AN18: 43 | AO18: 42 | AP18: 59 | AQ18: =AP18+AO18+AN18+AM18+AL18 -> 251 | AS18: 0 | AT18: =AQ18-AS18 -> 251
B19: 26/004 | C19: 93900 | D19: 113200 | E19: 48980 | F19: 85550 | G19: 228750 | H19: =SUM(C19:G19) -> 570380 | I19: 04 | J19: 3154955.2 | L19: -2588575.2 | M19: =SUM(J19:L19) -> 566380 | N19: =H19-M19 -> 4000 | R19: 1 | V19: =U19+T19+S19+R19+Q19 -> 1 | X19: 0 | Y19: =V19-X19 -> 1 | Z19: 04 | AC19: 10 | AG19: =AF19+AE19+AD19+AC19+AB19+AA19 -> 10 | AJ19: =AG19-AI19 -> 10 | AK19: 04 | AL19: 67 | AM19: 65 | AN19: 34 | AO19: 45 | AP19: 113 | AQ19: =AP19+AO19+AN19+AM19+AL19 -> 324 | AS19: 0 | AT19: =AQ19-AS19 -> 324
B20: 26/005 | C20: 50900 | D20: 67600 | E20: 56100 | F20: 64900 | G20: 90800 | H20: =SUM(C20:G20) -> 330300 | I20: 05 | J20: 164699.22 | K20: 165600.78 | M20: =SUM(J20:L20) -> 330300 | N20: =H20-M20 -> 0 | Q20: 1 | V20: =U20+T20+S20+R20+Q20 -> 1 | X20: 0 | Y20: =V20-X20 -> 1 | Z20: 05 | AB20: 1 | AC20: 2 | AD20: 1 | AE20: 1 | AG20: =AF20+AE20+AD20+AC20+AB20+AA20 -> 5 | AJ20: =AG20-AI20 -> 5 | AK20: 05 | AL20: 28 | AM20: 50 | AN20: 40 | AO20: 45 | AP20: 58 | AQ20: =AP20+AO20+AN20+AM20+AL20 -> 221 | AS20: 0 | AT20: =AQ20-AS20 -> 221
B21: 26/006 | C21: 126500 | D21: 130800 | E21: 81500 | F21: 90300 | G21: 159900 | H21: =SUM(C21:G21) -> 589000 | I21: 06 | J21: 410086.8 | K21: 178913.2 | M21: =SUM(J21:L21) -> 589000 | N21: =H21-M21 -> 0 | Q21: 3 | R21: 2 | T21: 1 | V21: =U21+T21+S21+R21+Q21 -> 6 | X21: 0 | Y21: =V21-X21 -> 6 | Z21: 06 | AA21: 6 | AB21: 5 | AC21: 7 | AD21: 1 | AE21: 3 | AG21: =AF21+AE21+AD21+AC21+AB21+AA21 -> 22 | AJ21: =AG21-AI21 -> 22 | AK21: 06 | AL21: 84 | AM21: 92 | AN21: 58 | AO21: 64 | AP21: 101 | AQ21: =AP21+AO21+AN21+AM21+AL21 -> 399 | AS21: 0 | AT21: =AQ21-AS21 -> 399
B22: 26/007 | C22: 161250 | D22: 170650 | E22: 68150 | F22: 97350 | G22: 178300 | H22: =SUM(C22:G22) -> 675700 | I22: 07 | J22: 408586.71 | K22: 267113.29 | M22: =SUM(J22:L22) -> 675700 | N22: =H22-M22 -> 0 | V22: =U22+T22+S22+R22+Q22 -> 0 | X22: 0 | Y22: =V22-X22 -> 0 | Z22: 07 | AA22: 3 | AB22: 2 | AC22: 7 | AE22: 1 | AG22: =AF22+AE22+AD22+AC22+AB22+AA22 -> 13 | AJ22: =AG22-AI22 -> 13 | AK22: 07 | AL22: 117 | AM22: 107 | AN22: 46 | AO22: 66 | AP22: 120 | AQ22: =AP22+AO22+AN22+AM22+AL22 -> 456 | AS22: 0 | AT22: =AQ22-AS22 -> 456
B23: 26/008 | C23: 82200 | D23: 76300 | E23: 1500 | F23: 57800 | G23: 39200 | H23: =SUM(C23:G23) -> 257000 | I23: 08 | J23: 154000 | K23: 103000 | M23: =SUM(J23:L23) -> 257000 | N23: =H23-M23 -> 0 | Q23: 2 | V23: =U23+T23+S23+R23+Q23 -> 2 | X23: 0 | Y23: =V23-X23 -> 2 | Z23: 08 | AA23: 5 | AG23: =AF23+AE23+AD23+AC23+AB23+AA23 -> 5 | AJ23: =AG23-AI23 -> 5 | AK23: 08 | AL23: 36 | AM23: 50 | AN23: 1 | AO23: 39 | AP23: 30 | AQ23: =AP23+AO23+AN23+AM23+AL23 -> 156 | AS23: 0 | AT23: =AQ23-AS23 -> 156
B24: 26/009 | C24: 75800 | D24: 106500 | E24: 63500 | F24: 94000 | G24: 169200 | H24: =SUM(C24:G24) -> 509000 | I24: 09 | J24: 534276.8 | L24: -25276.8 | M24: =SUM(J24:L24) -> 509000 | N24: =H24-M24 -> 0 | R24: 1 | V24: =U24+T24+S24+R24+Q24 -> 1 | X24: 0 | Y24: =V24-X24 -> 1 | Z24: 09 | AB24: 1 | AC24: 9 | AE24: 1 | AG24: =AF24+AE24+AD24+AC24+AB24+AA24 -> 11 | AJ24: =AG24-AI24 -> 11 | AK24: 09 | AL24: 44 | AM24: 74 | AN24: 33 | AO24: 53 | AP24: 115 | AQ24: =AP24+AO24+AN24+AM24+AL24 -> 319 | AS24: 0 | AT24: =AQ24-AS24 -> 319
B25: 26/010 | H25: =SUM(C25:G25) -> 0 | I25: 10 | M25: =SUM(J25:L25) -> 0 | N25: =H25-M25 -> 0 | V25: =U25+T25+S25+R25+Q25 -> 0 | X25: 0 | Y25: =V25-X25 -> 0 | Z25: 10 | AG25: =AF25+AE25+AD25+AC25+AB25+AA25 -> 0 | AJ25: =AG25-AI25 -> 0 | AK25: 10 | AQ25: =AP25+AO25+AN25+AM25+AL25 -> 0 | AS25: 0 | AT25: =AQ25-AS25 -> 0
B26: 26/011 | C26: 52800 | D26: 68500 | E26: 41200 | F26: 34400 | G26: 74000 | H26: =SUM(C26:G26) -> 270900 | I26: 11 | J26: 65075.36 | K26: 205824.64 | M26: =SUM(J26:L26) -> 270900 | N26: =H26-M26 -> 0 | R26: 1 | V26: =U26+T26+S26+R26+Q26 -> 1 | X26: 0 | Y26: =V26-X26 -> 1 | Z26: 11 | AA26: 2 | AB26: 2 | AC26: 2 | AE26: 1 | AG26: =AF26+AE26+AD26+AC26+AB26+AA26 -> 7 | AJ26: =AG26-AI26 -> 7 | AK26: 11 | AL26: 53 | AM26: 53 | AN26: 38 | AO26: 39 | AP26: 64 | AQ26: =AP26+AO26+AN26+AM26+AL26 -> 247 | AS26: 0 | AT26: =AQ26-AS26 -> 247
B27: 26/012 | C27: 88300 | D27: 128750 | E27: 38250 | F27: 56500 | G27: 113400 | H27: =SUM(C27:G27) -> 425200 | I27: 12 | J27: 642301.61 | L27: -217101.61 | M27: =SUM(J27:L27) -> 425200 | N27: =H27-M27 -> 0 | R27: 2 | V27: =U27+T27+S27+R27+Q27 -> 2 | X27: 0 | Y27: =V27-X27 -> 2 | Z27: 12 | AA27: 2 | AB27: 1 | AC27: 12 | AG27: =AF27+AE27+AD27+AC27+AB27+AA27 -> 15 | AJ27: =AG27-AI27 -> 15 | AK27: 12 | AL27: 75 | AM27: 97 | AN27: 34 | AO27: 41 | AP27: 116 | AQ27: =AP27+AO27+AN27+AM27+AL27 -> 363 | AS27: 0 | AT27: =AQ27-AS27 -> 363
B28: 26/013 | C28: 121850 | D28: 154600 | E28: 99050 | F28: 93450 | G28: 168150 | H28: =SUM(C28:G28) -> 637100 | I28: 13 | J28: 160236.51 | K28: 476863.29 | M28: =SUM(J28:L28) -> 637099.8 | N28: =H28-M28 -> 0.2 | Q28: 2 | S28: 1 | V28: =U28+T28+S28+R28+Q28 -> 3 | X28: 0 | Y28: =V28-X28 -> 3 | Z28: 13 | AA28: 1 | AC28: 5 | AD28: 1 | AG28: =AF28+AE28+AD28+AC28+AB28+AA28 -> 7 | AJ28: =AG28-AI28 -> 7 | AK28: 13 | AL28: 63 | AM28: 81 | AN28: 54 | AO28: 43 | AP28: 81 | AQ28: =AP28+AO28+AN28+AM28+AL28 -> 322 | AS28: 0 | AT28: =AQ28-AS28 -> 322
B29: 26/014 | C29: 82400 | D29: 59200 | E29: 20800 | F29: 28200 | G29: 36400 | H29: =SUM(C29:G29) -> 227000 | I29: 14 | J29: 86824.23 | K29: 140175.77 | M29: =SUM(J29:L29) -> 227000 | N29: =H29-M29 -> 0 | Q29: 1 | V29: =U29+T29+S29+R29+Q29 -> 1 | X29: 0 | Y29: =V29-X29 -> 1 | Z29: 14 | AA29: 1 | AC29: 4 | AG29: =AF29+AE29+AD29+AC29+AB29+AA29 -> 5 | AJ29: =AG29-AI29 -> 5 | AK29: 14 | AL29: 65 | AM29: 37 | AN29: 15 | AO29: 18 | AP29: 30 | AQ29: =AP29+AO29+AN29+AM29+AL29 -> 165 | AS29: 0 | AT29: =AQ29-AS29 -> 165
B30: 26/015 | H30: =SUM(C30:G30) -> 0 | I30: 15 | M30: =SUM(J30:L30) -> 0 | N30: =H30-M30 -> 0 | V30: =U30+T30+S30+R30+Q30 -> 0 | X30: 0 | Y30: =V30-X30 -> 0 | Z30: 15 | AG30: =AF30+AE30+AD30+AC30+AB30+AA30 -> 0 | AJ30: =AG30-AI30 -> 0 | AK30: 15 | AQ30: =AP30+AO30+AN30+AM30+AL30 -> 0 | AS30: 0 | AT30: =AQ30-AS30 -> 0
B31: 26/016 | C31: 161900 | D31: 150700 | E31: 86500 | F31: 120900 | G31: 139300 | H31: =SUM(C31:G31) -> 659300 | I31: 16 | J31: 168403.71 | K31: 490896.29 | M31: =SUM(J31:L31) -> 659300 | N31: =H31-M31 -> 0 | V31: =U31+T31+S31+R31+Q31 -> 0 | X31: 0 | Y31: =V31-X31 -> 0 | Z31: 16 | AA31: 2 | AC31: 5 | AG31: =AF31+AE31+AD31+AC31+AB31+AA31 -> 7 | AJ31: =AG31-AI31 -> 7 | AK31: 16 | AL31: 79 | AM31: 77 | AN31: 43 | AO31: 55 | AP31: 85 | AQ31: =AP31+AO31+AN31+AM31+AL31 -> 339 | AS31: 0 | AT31: =AQ31-AS31 -> 339
B32: 26/017 | C32: 45850 | D32: 64950 | E32: 18750 | F32: 24200 | G32: 37800 | H32: =SUM(C32:G32) -> 191550 | I32: 17 | J32: 134498.71 | K32: 57051.29 | M32: =SUM(J32:L32) -> 191550 | N32: =H32-M32 -> 0 | V32: =U32+T32+S32+R32+Q32 -> 0 | X32: 0 | Y32: =V32-X32 -> 0 | Z32: 17 | AC32: 4 | AG32: =AF32+AE32+AD32+AC32+AB32+AA32 -> 4 | AJ32: =AG32-AI32 -> 4 | AK32: 17 | AL32: 44 | AM32: 44 | AN32: 24 | AO32: 17 | AP32: 22 | AQ32: =AP32+AO32+AN32+AM32+AL32 -> 151 | AS32: 0 | AT32: =AQ32-AS32 -> 151
B33: 26/018 | H33: =SUM(C33:G33) -> 0 | I33: 18 | M33: =SUM(J33:L33) -> 0 | N33: =H33-M33 -> 0 | V33: =U33+T33+S33+R33+Q33 -> 0 | X33: 0 | Y33: =V33-X33 -> 0 | Z33: 18 | AG33: =AF33+AE33+AD33+AC33+AB33+AA33 -> 0 | AJ33: =AG33-AI33 -> 0 | AK33: 18 | AQ33: =AP33+AO33+AN33+AM33+AL33 -> 0 | AS33: 0 | AT33: =AQ33-AS33 -> 0
B34: 26/019 | H34: =SUM(C34:G34) -> 0 | I34: 19 | M34: =SUM(J34:L34) -> 0 | N34: =H34-M34 -> 0 | V34: =U34+T34+S34+R34+Q34 -> 0 | X34: 0 | Y34: =V34-X34 -> 0 | Z34: 19 | AG34: =AF34+AE34+AD34+AC34+AB34+AA34 -> 0 | AJ34: =AG34-AI34 -> 0 | AK34: 19 | AQ34: =AP34+AO34+AN34+AM34+AL34 -> 0 | AS34: 0 | AT34: =AQ34-AS34 -> 0
C36: =SUM(C12:C34) -> 2115400 | D36: =SUM(D12:D34) -> 1938000 | E36: =SUM(E12:E34) -> 946930 | F36: =SUM(F12:F34) -> 1181000 | G36: =SUM(G12:G34) -> 2158050 | H36: =SUM(H12:H34) -> 8339380 | J36: =SUM(J12:J34) -> 7491034 | K36: =SUM(K12:K35) -> 3673324.4 | L36: =SUM(L13:L34) -> -2830953.6 | M36: =SUM(M12:M34) -> 8333404.7 | Q36: TOTAL ANULADAS | U36: =SUM(V12:V34) -> 26 | X36: =SUM(X12:X34) -> 0 | AA36: TOTAL PREMIADAS | AF36: =SUM(AG12:AG34) -> 154 | AI36: =SUM(AI12:AI34) -> 0 | AL36: TOTAL VENDIDAS | AP36: =SUM(AQ12:AQ34) -> 5256 | AS36: =SUM(AS12:AS34) -> 0
B38: DEBEN / SALIDA | J38: PAGAN / ENTRADA
B40: MARTIN GASTOS | D40: 0 | E40: DEPOSITOS | H40: =D41+C72 -> 7846009 | J40: DEUDA DE CAJA s/l/v | L40: 0 | M40: EXCEDENTE | N40: 0
B41: PREMIOS | D41: =J36 -> 7491034 | E41: PREST. PALP. | H41: 0 | J41: FALTANTE DE CAJA | L41: 0 | M41: MARTIN | N41: 0
B42: LIBRERIA | D42: 0 | E42: PREST. TELEKINO | H42: 0 | J42: PREST. PALP./ REVISTA | L42: 0 | M42: PREMIOS | N42: 0
B43: LIMPIEZA | D43: 0 | E43: PREST. JGOS. MENORES | H43: 0 | J43: PREST. TELEKINO | L43: 0 | N43: 0
B44: SODA/AGUA | D44: 0 | E44: IMPUESTOS | H44: 0 | J44: PREST. JGOS. MENORES | L44: 0 | N44: 0
B45: GASTOS VARIOS | D45: 0 | E45: OTROS | H45: =SUM(N12:N34) -> 5975.26 | L45: 0 | N45: 0
B47: SUB TOTAL | D47: =D40+D41+D42+D43+D44+D45+H41+H42+H43+H44+H45 -> 7497009.2 | G47: TOTAL | H47: =D47+H40 -> 15343018 | M47: SUB TOTAL | N47: =L40+L41+L42+L43+L44+L45+N40+N41+N42+N43+N44+N45 -> 0
C49: DETALLE RECAUDACION DE CAJA | H49: IMPORTE | J49: FECHA | L49: DETALLE CIERRE DE CAJA
C51: 20000 x | D51: 10 | E51: =20000*D51 -> 200000 | I51: MAT | L51: 20000 x | M51: 145 | N51: =20000*M51 -> 2900000
C52: 10000 x | D52: 29 | E52: =10000*D52 -> 290000 | I52: MAT | L52: 10000 x | M52: 16 | N52: =10000*M52 -> 160000
C53: 2000 x | D53: 117 | E53: =2000*D53 -> 234000 | I53: MAT | L53: 2000 x | M53: 110 | N53: =2000*M53 -> 220000
C54: 1000 x | D54: 78 | E54: =1000*D54 -> 78000 | I54: MAT | L54: 1000 x | M54: 1386 | N54: =1000*M54 -> 1386000
C55: 500 x | D55: 51 | E55: =500*D55 -> 25500 | I55: MAT | K55: =SUM(H51:H55) -> 0 | L55: 500 x | M55: 349 | N55: =500*M55 -> 174500
C56: 200 x | D56: 27 | E56: =200*D56 -> 5400 | I56: VEP | L56: 200 x | M56: 853 | N56: =200*M56 -> 170600
C57: 100 x | D57: 96 | E57: =100*D57 -> 9600 | I57: VEP | L57: 100 x | M57: 260 | N57: =100*M57 -> 26000
C58: 50 x | D58: 1 | E58: =50*D58 -> 50 | I58: VEP | L58: 50 x | M58: 1793 | N58: =50*M58 -> 89650
C59: 20 x | D59: 0 | E59: =20*D59 -> 0 | I59: VEP | L59: 20 x | M59: 1509 | N59: =20*M59 -> 30180
C60: 10 x | D60: 1 | E60: =10*D60 -> 10 | I60: VEP | K60: =SUM(H56:H60) -> 0 | L60: 10 x | M60: 361 | N60: =10*M60 -> 3610
C61: 5 x | D61: 0 | E61: =5*D61 -> 0 | I61: TAR | L61: 5 x | M61: 0 | N61: =5*M61 -> 0
C62: 2 x | D62: 0 | E62: =2*D62 -> 0 | I62: TAR | L62: 2 x | M62: 0 | N62: =2*M62 -> 0
C63: 1 x | D63: 0 | E63: =1*D63 -> 0 | I63: TAR | L63: 1 x | M63: 0 | N63: =1*M63 -> 0
C64: SUB - TOTAL | E64: =SUM(E51:F63) -> 842560 | I64: TAR | L64: SUB - TOTAL | N64: =SUM(N51:N63) -> 5160540
I65: TAR | K65: =SUM(H61:H65) -> 0
D66: TOTAL | F66: =D47+E64 -> 8339569.2 | I66: NOC | L66: PREMOS | N66: 0
I67: NOC | L67: TELEKINOS | N67: 0
D68: DIFERENCIA | F68: =F66-H36 -> 189.21 | I68: NOC | L68: BOL. S/PREMIOS | N68: 3115613.4
I69: NOC | L69: OTROS | N69: 0
C70: DEPOSITO | I70: NOC | M70: SUB- TOTAL | N70: =SUM(N66:N69) -> 3115613.4
I71: NOC | K71: =SUM(H66:H71) -> 0
C72: 354975
H73: =SUM(H51:H71) -> 0 | M73: TOTAL | N73: =N64+N70 -> 8276153.4
L75: ARQUEO DE CAJA AL CIERRE (COMPOSICION DEL SALDO)
C76: TOTAL DE INGRESO | H76: =H8+H36+N47 -> 16080783 | L76: PREMIOS | N76: =N70 -> 3115613.4
L77: EFECTIVO | N77: =N64 -> 5160540
C78: TOTAL DE EGRESO | H78: =H73+H40+D40+D42+D43+D44+D45+H41+H42+H43+H44+H45 -> 7851984.2 | L78: TOTAL DE CAJA AL CIERRE | N78: =N70+N64 -> 8276153.4
C80: SALDO DEL DIA | H80: =H76-H78 -> 8228799.2 | L80: DIFERENCIA DE CAJA | N80: =N78-H80 -> 47354.21
L81: (+) POSITIVO | M81: (-) NEGATIVO

Sheet 0401
A1: z
D2: PLANILLA DE RECAUDACION DIARIA DE APUESTA Y PREMIOS | M2: ='0101'!M2 -> 2025
D4: FECHA : | E4: 45170 | G4: RECAUDACION DEL DIA: | I4: 45169
C6: 26 | D6: SALDO DEL DIA ANTERIOR | G6: PREMIOS | H6: ='0301'!N76 -> 3115613.4
G7: EFECTIVO | H7: ='0301'!N77 -> 5160540
G8: TOTAL | H8: =H6+H7 -> 8276153.4 | Q8: TICKET ANULADOS | AA8: TICKET PREMIADOS | AL8: TICKET VENDIDOS
C10: MATUTINA | D10: VESPERT. | E10: SIESTA | F10: TARDE | G10: NOCT. | H10: TOTAL | J10: PREMIOS | K10: EFECTIVO | L10: MONEDAS | M10: TOTAL | N10: DIFER. | Q10: M | R10: V | S10: S | T10: T | U10: N | V10: TOTAL | X10: PRES. | Y10: DIFER. | AA10: ANT | AB10: M | AC10: V | AD10: S | AE10: T | AF10: N | AG10: TOTAL | AI10: PRES | AJ10: DIFER. | AL10: M | AM10: V | AN10: S | AO10: T | AP10: N | AQ10: TOTAL | AS10: PRES. | AT10: DIFER.
H11: =SUM(H12:H15) -> 727300
B12: 001 | C12: 135200 | D12: 31000 | E12: 2500 | F12: 47000 | G12: 83200 | H12: =SUM(C12:G12) -> 298900 | I12: 001 | J12: 14000 | K12: 284900 | M12: =SUM(J12:L12) -> 298900 | N12: =H12-M12 -> 0 | Q12: 1 | T12: 1 | V12: =U12+T12+S12+R12+Q12 -> 2 | X12: 0 | Y12: =V12-X12 -> 2 | Z12: V | AA12: 2 | AG12: =AF12+AE12+AD12+AC12+AB12+AA12 -> 2 | AI12: 0 | AJ12: =AG12-AI12 -> 2 | AL12: 92 | AM12: 24 | AN12: 4 | AO12: 16 | AP12: 37 | AQ12: =AP12+AO12+AN12+AM12+AL12 -> 173 | AS12: 0 | AT12: =AQ12-AS12 -> 173
B13: 002 | H13: =SUM(C13:G13) -> 0 | I13: 002 | M13: =SUM(J13:L13) -> 0 | N13: =H13-M13 -> 0 | V13: =U13+T13+S13+R13+Q13 -> 0 | X13: 0 | Y13: =V13-X13 -> 0 | Z13: L | AG13: =AF13+AE13+AD13+AC13+AB13+AA13 -> 0 | AJ13: =AG13-AI13 -> 0 | AQ13: =AP13+AO13+AN13+AM13+AL13 -> 0 | AS13: 0 | AT13: =AQ13-AS13 -> 0
B14: 003 | C14: 139700 | D14: 122500 | E14: 39400 | F14: 45500 | G14: 81300 | H14: =SUM(C14:G14) -> 428400 | I14: 003 | J14: 142598.97 | K14: 285900 | L14: -98.97 | M14: =SUM(J14:L14) -> 428400 | N14: =H14-M14 -> 0 | V14: =U14+T14+S14+R14+Q14 -> 0 | X14: 0 | Y14: =V14-X14 -> 0 | Z14: M | AA14: 4 | AB14: 1 | AC14: 1 | AG14: =AF14+AE14+AD14+AC14+AB14+AA14 -> 6 | AJ14: =AG14-AI14 -> 6 | AL14: 87 | AM14: 68 | AN14: 22 | AO14: 19 | AP14: 40 | AQ14: =AP14+AO14+AN14+AM14+AL14 -> 236 | AS14: 0 | AT14: =AQ14-AS14 -> 236
B15: 004 | H15: =SUM(C15:G15) -> 0 | I15: 004 | J15: 14000 | L15: -14000 | M15: =SUM(J15:L15) -> 0 | N15: =H15-M15 -> 0 | V15: =U15+T15+S15+R15+Q15 -> 0 | X15: 0 | Y15: =V15-X15 -> 0 | AG15: =AF15+AE15+AD15+AC15+AB15+AA15 -> 0 | AJ15: =AG15-AI15 -> 0 | AQ15: =AP15+AO15+AN15+AM15+AL15 -> 0 | AS15: 0 | AT15: =AQ15-AS15 -> 0
B16: 26/001 | C16: 197100 | D16: 94600 | E16: 19200 | F16: 53300 | G16: 91600 | H16: =SUM(C16:G16) -> 455800 | I16: 01 | J16: 101500 | K16: 196090 | L16: 158210 | M16: =SUM(J16:L16) -> 455800 | N16: =H16-M16 -> 0 | Q16: 4 | R16: 1 | S16: 1 | T16: 1 | U16: 2 | V16: =U16+T16+S16+R16+Q16 -> 9 | X16: 0 | Y16: =V16-X16 -> 9 | Z16: 01 | AC16: 4 | AD16: 1 | AG16: =AF16+AE16+AD16+AC16+AB16+AA16 -> 5 | AJ16: =AG16-AI16 -> 5 | AK16: 01 | AL16: 111 | AM16: 73 | AN16: 23 | AO16: 49 | AP16: 77 | AQ16: =AP16+AO16+AN16+AM16+AL16 -> 333 | AS16: 0 | AT16: =AQ16-AS16 -> 333
B17: 26/002 | C17: 263350 | D17: 217900 | E17: 173050 | F17: 160400 | G17: 283455 | H17: =SUM(C17:G17) -> 1098155 | I17: 02 | J17: 432420.1 | K17: 665750 | L17: -15.1 | M17: =SUM(J17:L17) -> 1098155 | N17: =H17-M17 -> 0 | Q17: 2 | V17: =U17+T17+S17+R17+Q17 -> 2 | X17: 0 | Y17: =V17-X17 -> 2 | Z17: 02 | AA17: 4 | AG17: =AF17+AE17+AD17+AC17+AB17+AA17 -> 4 | AJ17: =AG17-AI17 -> 4 | AK17: 02 | AL17: 184 | AM17: 130 | AN17: 128 | AO17: 100 | AP17: 170 | AQ17: =AP17+AO17+AN17+AM17+AL17 -> 712 | AS17: 0 | AT17: =AQ17-AS17 -> 712
B18: 26/003 | C18: 135800 | D18: 108700 | E18: 90200 | F18: 76800 | G18: 122500 | H18: =SUM(C18:G18) -> 534000 | I18: 03 | J18: 161700 | K18: 372300 | M18: =SUM(J18:L18) -> 534000 | N18: =H18-M18 -> 0 | V18: =U18+T18+S18+R18+Q18 -> 0 | X18: 0 | Y18: =V18-X18 -> 0 | Z18: 03 | AC18: 1 | AD18: 4 | AE18: 2 | AG18: =AF18+AE18+AD18+AC18+AB18+AA18 -> 7 | AJ18: =AG18-AI18 -> 7 | AK18: 03 | AL18: 81 | AM18: 67 | AN18: 42 | AO18: 40 | AP18: 77 | AQ18: =AP18+AO18+AN18+AM18+AL18 -> 307 | AS18: 0 | AT18: =AQ18-AS18 -> 307
B19: 26/004 | C19: 94300 | D19: 108300 | E19: 58000 | F19: 98000 | G19: 222000 | H19: =SUM(C19:G19) -> 580600 | I19: 04 | J19: 225400 | K19: 335100 | L19: 10087.4 | M19: =SUM(J19:L19) -> 570587.4 | N19: =H19-M19 -> 10012.6 | V19: =U19+T19+S19+R19+Q19 -> 0 | X19: 0 | Y19: =V19-X19 -> 0 | Z19: 04 | AA19: 2 | AB19: 2 | AC19: 1 | AG19: =AF19+AE19+AD19+AC19+AB19+AA19 -> 5 | AJ19: =AG19-AI19 -> 5 | AK19: 04 | AL19: 59 | AM19: 56 | AN19: 33 | AO19: 43 | AP19: 106 | AQ19: =AP19+AO19+AN19+AM19+AL19 -> 297 | AS19: 0 | AT19: =AQ19-AS19 -> 297
B20: 26/005 | C20: 114500 | D20: 64200 | E20: 13300 | F20: 30800 | G20: 72100 | H20: =SUM(C20:G20) -> 294900 | I20: 05 | J20: 10224.94 | K20: 284700 | L20: -24.94 | M20: =SUM(J20:L20) -> 294900 | N20: =H20-M20 -> 0 | Q20: 1 | V20: =U20+T20+S20+R20+Q20 -> 1 | X20: 0 | Y20: =V20-X20 -> 1 | Z20: 05 | AA20: 1 | AB20: 1 | AG20: =AF20+AE20+AD20+AC20+AB20+AA20 -> 2 | AJ20: =AG20-AI20 -> 2 | AK20: 05 | AL20: 42 | AM20: 45 | AN20: 8 | AO20: 20 | AP20: 34 | AQ20: =AP20+AO20+AN20+AM20+AL20 -> 149 | AS20: 0 | AT20: =AQ20-AS20 -> 149
B21: 26/006 | C21: 141900 | D21: 130100 | E21: 59900 | F21: 61500 | G21: 171800 | H21: =SUM(C21:G21) -> 565200 | I21: 06 | J21: 93274.56 | K21: 471925.74 | M21: =SUM(J21:L21) -> 565200.3 | N21: =H21-M21 -> -0.3 | Q21: 1 | R21: 2 | T21: 1 | V21: =U21+T21+S21+R21+Q21 -> 4 | X21: 0 | Y21: =V21-X21 -> 4 | Z21: 06 | AA21: 5 | AB21: 1 | AC21: 1 | AD21: 1 | AE21: 1 | AG21: =AF21+AE21+AD21+AC21+AB21+AA21 -> 9 | AJ21: =AG21-AI21 -> 9 | AK21: 06 | AL21: 88 | AM21: 79 | AN21: 47 | AO21: 45 | AP21: 85 | AQ21: =AP21+AO21+AN21+AM21+AL21 -> 344 | AS21: 0 | AT21: =AQ21-AS21 -> 344
B22: 26/007 | C22: 159650 | D22: 116300 | E22: 46000 | F22: 102050 | G22: 122500 | H22: =SUM(C22:G22) -> 546500 | I22: 07 | J22: 109900 | K22: 436600 | M22: =SUM(J22:L22) -> 546500 | N22: =H22-M22 -> 0 | V22: =U22+T22+S22+R22+Q22 -> 0 | X22: 0 | Y22: =V22-X22 -> 0 | Z22: 07 | AA22: 2 | AC22: 1 | AE22: 2 | AG22: =AF22+AE22+AD22+AC22+AB22+AA22 -> 5 | AJ22: =AG22-AI22 -> 5 | AK22: 07 | AL22: 97 | AM22: 98 | AN22: 37 | AO22: 77 | AP22: 92 | AQ22: =AP22+AO22+AN22+AM22+AL22 -> 401 | AS22: 0 | AT22: =AQ22-AS22 -> 401
B23: 26/008 | C23: 66300 | D23: 45605 | E23: 9000 | F23: 31100 | G23: 46095 | H23: =SUM(C23:G23) -> 198100 | I23: 08 | J23: 31850 | K23: 166250 | M23: =SUM(J23:L23) -> 198100 | N23: =H23-M23 -> 0 | Q23: 1 | V23: =U23+T23+S23+R23+Q23 -> 1 | X23: 0 | Y23: =V23-X23 -> 1 | Z23: 08 | AA23: 3 | AB23: 1 | AE23: 1 | AG23: =AF23+AE23+AD23+AC23+AB23+AA23 -> 5 | AJ23: =AG23-AI23 -> 5 | AK23: 08 | AL23: 34 | AM23: 34 | AN23: 16 | AO23: 25 | AP23: 30 | AQ23: =AP23+AO23+AN23+AM23+AL23 -> 139 | AS23: 0 | AT23: =AQ23-AS23 -> 139
B24: 26/009 | C24: 137900 | D24: 102050 | E24: 39550 | F24: 53900 | G24: 152800 | H24: =SUM(C24:G24) -> 486200 | I24: 09 | J24: 104300 | K24: 381000 | L24: 900 | M24: =SUM(J24:L24) -> 486200 | N24: =H24-M24 -> 0 | R24: 1 | V24: =U24+T24+S24+R24+Q24 -> 1 | X24: 0 | Y24: =V24-X24 -> 1 | Z24: 09 | AA24: 2 | AB24: 3 | AD24: 1 | AG24: =AF24+AE24+AD24+AC24+AB24+AA24 -> 6 | AJ24: =AG24-AI24 -> 6 | AK24: 09 | AL24: 76 | AM24: 64 | AN24: 29 | AO24: 35 | AP24: 91 | AQ24: =AP24+AO24+AN24+AM24+AL24 -> 295 | AS24: 0 | AT24: =AQ24-AS24 -> 295
B25: 26/010 | H25: =SUM(C25:G25) -> 0 | I25: 10 | M25: =SUM(J25:L25) -> 0 | N25: =H25-M25 -> 0 | V25: =U25+T25+S25+R25+Q25 -> 0 | X25: 0 | Y25: =V25-X25 -> 0 | Z25: 10 | AG25: =AF25+AE25+AD25+AC25+AB25+AA25 -> 0 | AJ25: =AG25-AI25 -> 0 | AK25: 10 | AQ25: =AP25+AO25+AN25+AM25+AL25 -> 0 | AS25: 0 | AT25: =AQ25-AS25 -> 0
B26: 26/011 | C26: 57700 | D26: 62000 | E26: 25200 | F26: 48000 | G26: 56900 | H26: =SUM(C26:G26) -> 249800 | I26: 11 | J26: 80087.4 | K26: 169712.6 | M26: =SUM(J26:L26) -> 249800 | N26: =H26-M26 -> 0 | V26: =U26+T26+S26+R26+Q26 -> 0 | X26: 0 | Y26: =V26-X26 -> 0 | Z26: 11 | AA26: 1 | AC26: 1 | AG26: =AF26+AE26+AD26+AC26+AB26+AA26 -> 2 | AJ26: =AG26-AI26 -> 2 | AK26: 11 | AL26: 51 | AM26: 59 | AN26: 31 | AO26: 50 | AP26: 55 | AQ26: =AP26+AO26+AN26+AM26+AL26 -> 246 | AS26: 0 | AT26: =AQ26-AS26 -> 246
B27: 26/012 | C27: 97200 | D27: 122050 | E27: 63050 | F27: 57700 | G27: 125600 | H27: =SUM(C27:G27) -> 465600 | I27: 12 | J27: 171454.95 | K27: 294145.04 | M27: =SUM(J27:L27) -> 465599.99 | N27: =H27-M27 -> 0.01 | Q27: 1 | U27: 1 | V27: =U27+T27+S27+R27+Q27 -> 2 | X27: 0 | Y27: =V27-X27 -> 2 | Z27: 12 | AA27: 2 | AB27: 3 | AC27: 4 | AD27: 1 | AE27: 3 | AG27: =AF27+AE27+AD27+AC27+AB27+AA27 -> 13 | AJ27: =AG27-AI27 -> 13 | AK27: 12 | AL27: 58 | AM27: 64 | AN27: 46 | AO27: 47 | AP27: 103 | AQ27: =AP27+AO27+AN27+AM27+AL27 -> 318 | AS27: 0 | AT27: =AQ27-AS27 -> 318
B28: 26/013 | C28: 140200 | D28: 182900 | E28: 70600 | F28: 74900 | G28: 140000 | H28: =SUM(C28:G28) -> 608600 | I28: 13 | J28: 225274.81 | K28: 383325.19 | M28: =SUM(J28:L28) -> 608600 | N28: =H28-M28 -> 0 | Q28: 1 | R28: 2 | S28: 1 | U28: 1 | V28: =U28+T28+S28+R28+Q28 -> 5 | X28: 0 | Y28: =V28-X28 -> 5 | Z28: 13 | AA28: 2 | AB28: 3 | AC28: 2 | AE28: 1 | AG28: =AF28+AE28+AD28+AC28+AB28+AA28 -> 8 | AJ28: =AG28-AI28 -> 8 | AK28: 13 | AL28: 72 | AM28: 83 | AN28: 36 | AO28: 33 | AP28: 66 | AQ28: =AP28+AO28+AN28+AM28+AL28 -> 290 | AS28: 0 | AT28: =AQ28-AS28 -> 290
B29: 26/014 | C29: 98400 | D29: 56500 | E29: 22000 | F29: 25500 | G29: 70400 | H29: =SUM(C29:G29) -> 272800 | I29: 14 | J29: 160049.61 | K29: 111800 | L29: 950 | M29: =SUM(J29:L29) -> 272799.61 | N29: =H29-M29 -> 0.39 | V29: =U29+T29+S29+R29+Q29 -> 0 | X29: 0 | Y29: =V29-X29 -> 0 | Z29: 14 | AA29: 4 | AB29: 1 | AD29: 1 | AE29: 2 | AG29: =AF29+AE29+AD29+AC29+AB29+AA29 -> 8 | AJ29: =AG29-AI29 -> 8 | AK29: 14 | AL29: 73 | AM29: 55 | AN29: 18 | AO29: 16 | AP29: 42 | AQ29: =AP29+AO29+AN29+AM29+AL29 -> 204 | AS29: 0 | AT29: =AQ29-AS29 -> 204
B30: 26/015 | H30: =SUM(C30:G30) -> 0 | I30: 15 | M30: =SUM(J30:L30) -> 0 | N30: =H30-M30 -> 0 | V30: =U30+T30+S30+R30+Q30 -> 0 | X30: 0 | Y30: =V30-X30 -> 0 | Z30: 15 | AG30: =AF30+AE30+AD30+AC30+AB30+AA30 -> 0 | AJ30: =AG30-AI30 -> 0 | AK30: 15 | AL30: 109 | AM30: 67 | AN30: 48 | AO30: 30 | AP30: 82 | AQ30: =AP30+AO30+AN30+AM30+AL30 -> 336 | AS30: 0 | AT30: =AQ30-AS30 -> 336
B31: 26/016 | C31: 167050 | D31: 134750 | E31: 93600 | F31: 64000 | G31: 145300 | H31: =SUM(C31:G31) -> 604700 | I31: 16 | J31: 182824.94 | K31: 421875.06 | M31: =SUM(J31:L31) -> 604700 | N31: =H31-M31 -> 0 | U31: 3 | V31: =U31+T31+S31+R31+Q31 -> 3 | X31: 0 | Y31: =V31-X31 -> 3 | Z31: 16 | AA31: 8 | AD31: 1 | AG31: =AF31+AE31+AD31+AC31+AB31+AA31 -> 9 | AJ31: =AG31-AI31 -> 9 | AK31: 16 | AL31: 28 | AM31: 17 | AN31: 8 | AO31: 16 | AP31: 35 | AQ31: =AP31+AO31+AN31+AM31+AL31 -> 104 | AS31: 0 | AT31: =AQ31-AS31 -> 104
B32: 26/017 | C32: 23550 | D32: 22900 | E32: 7400 | F32: 19400 | G32: 30200 | H32: =SUM(C32:G32) -> 103450 | I32: 17 | J32: 6999.99 | K32: 96450 | M32: =SUM(J32:L32) -> 103449.99 | N32: =H32-M32 -> 0.01 | V32: =U32+T32+S32+R32+Q32 -> 0 | X32: 0 | Y32: =V32-X32 -> 0 | Z32: 17 | AA32: 3 | AG32: =AF32+AE32+AD32+AC32+AB32+AA32 -> 3 | AJ32: =AG32-AI32 -> 3 | AK32: 17 | AQ32: =AP32+AO32+AN32+AM32+AL32 -> 0 | AS32: 0 | AT32: =AQ32-AS32 -> 0
B33: 26/018 | H33: =SUM(C33:G33) -> 0 | I33: 18 | M33: =SUM(J33:L33) -> 0 | N33: =H33-M33 -> 0 | V33: =U33+T33+S33+R33+Q33 -> 0 | X33: 0 | Y33: =V33-X33 -> 0 | Z33: 18 | AG33: =AF33+AE33+AD33+AC33+AB33+AA33 -> 0 | AJ33: =AG33-AI33 -> 0 | AK33: 18 | AQ33: =AP33+AO33+AN33+AM33+AL33 -> 0 | AS33: 0 | AT33: =AQ33-AS33 -> 0
B34: 26/019 | H34: =SUM(C34:G34) -> 0 | I34: 19 | M34: =SUM(J34:L34) -> 0 | N34: =H34-M34 -> 0 | V34: =U34+T34+S34+R34+Q34 -> 0 | X34: 0 | Y34: =V34-X34 -> 0 | Z34: 19 | AG34: =AF34+AE34+AD34+AC34+AB34+AA34 -> 0 | AJ34: =AG34-AI34 -> 0 | AK34: 19 | AQ34: =AP34+AO34+AN34+AM34+AL34 -> 0 | AS34: 0 | AT34: =AQ34-AS34 -> 0
C36: =SUM(C12:C34) -> 2169800 | D36: =SUM(D12:D34) -> 1722355 | E36: =SUM(E12:E34) -> 831950 | F36: =SUM(F12:F34) -> 1049850 | G36: =SUM(G12:G34) -> 2017750 | H36: =SUM(H12:H34) -> 7791705 | J36: =SUM(J12:J34) -> 2267860.3 | K36: =SUM(K12:K35) -> 5357823.6 | L36: =SUM(L13:L34) -> 156008.39 | M36: =SUM(M12:M34) -> 7781692.3 | Q36: TOTAL ANULADAS | U36: =SUM(V12:V34) -> 30 | X36: =SUM(X12:X34) -> 0 | AA36: TOTAL PREMIADAS | AF36: =SUM(AG12:AG34) -> 99 | AI36: =SUM(AI12:AI34) -> 0 | AL36: TOTAL VENDIDAS | AP36: =SUM(AQ12:AQ34) -> 4884 | AS36: =SUM(AS12:AS34) -> 0
B38: DEBEN / SALIDA | J38: PAGAN / ENTRADA
B40: MARTIN GASTOS | D40: 0 | E40: DEPOSITOS | H40: =D41+C72 -> 8339379.2 | J40: DEUDA DE CAJA s/l/v | L40: 0 | M40: EXCEDENTE | N40: 0
B41: PREMIOS | D41: =J36 -> 2267860.3 | E41: PREST. PALP. | H41: 0 | J41: FALTANTE DE CAJA | L41: 0 | M41: MARTIN | N41: 0
B42: LIBRERIA | D42: 0 | E42: PREST. TELEKINO | H42: 0 | J42: PREST. PALP./ REVISTA | L42: 0 | M42: PREMIOS | N42: 0
B43: LIMPIEZA | D43: 0 | E43: PREST. JGOS. MENORES | H43: 0 | J43: PREST. TELEKINO | L43: 0 | N43: 0
B44: SODA/AGUA | D44: 0 | E44: IMPUESTOS | H44: 0 | J44: PREST. JGOS. MENORES | L44: 0 | N44: 0
B45: GASTOS VARIOS | D45: 0 | E45: OTROS | H45: =SUM(N12:N34) -> 10012.71 | L45: 0 | N45: 0
B47: SUB TOTAL | D47: =D40+D41+D42+D43+D44+D45+H41+H42+H43+H44+H45 -> 2277873 | G47: TOTAL | H47: =D47+H40 -> 10617252 | M47: SUB TOTAL | N47: =L40+L41+L42+L43+L44+L45+N40+N41+N42+N43+N44+N45 -> 0
C49: DETALLE RECAUDACION DE CAJA | H49: IMPORTE | J49: FECHA | L49: DETALLE CIERRE DE CAJA
C51: 20000 x | D51: 51 | E51: =20000*D51 -> 1020000 | I51: MAT | L51: 20000 x | M51: 82 | N51: =20000*M51 -> 1640000
C52: 10000 x | D52: 210 | E52: =10000*D52 -> 2100000 | I52: MAT | L52: 10000 x | M52: 33 | N52: =10000*M52 -> 330000
C53: 2000 x | D53: 368 | E53: =2000*D53 -> 736000 | I53: MAT | L53: 2000 x | M53: 11 | N53: =2000*M53 -> 22000
C54: 1000 x | D54: 1261 | E54: =1000*D54 -> 1261000 | I54: MAT | L54: 1000 x | M54: 1025 | N54: =1000*M54 -> 1025000
C55: 500 x | D55: 99 | E55: =500*D55 -> 49500 | I55: MAT | K55: =SUM(H51:H55) -> 0 | L55: 500 x | M55: 454 | N55: =500*M55 -> 227000
C56: 200 x | D56: 51 | E56: =200*D56 -> 10200 | I56: VEP | L56: 200 x | M56: 818 | N56: =200*M56 -> 163600
C57: 100 x | D57: 63 | E57: =100*D57 -> 6300 | I57: VEP | L57: 100 x | M57: 117 | N57: =100*M57 -> 11700
C58: 50 x | D58: 1 | E58: =50*D58 -> 50 | I58: VEP | L58: 50 x | M58: 1794 | N58: =50*M58 -> 89700
C59: 20 x | D59: 1 | E59: =20*D59 -> 20 | I59: VEP | L59: 20 x | M59: 1509 | N59: =20*M59 -> 30180
C60: 10 x | D60: 2 | E60: =10*D60 -> 20 | I60: VEP | K60: =SUM(H56:H60) -> 0 | L60: 10 x | M60: 361 | N60: =10*M60 -> 3610
C61: 5 x | D61: 0 | E61: =5*D61 -> 0 | I61: TAR | L61: 5 x | M61: 0 | N61: =5*M61 -> 0
C62: 2 x | D62: 0 | E62: =2*D62 -> 0 | I62: TAR | L62: 2 x | M62: 0 | N62: =2*M62 -> 0
C63: 1 x | D63: 0 | E63: =1*D63 -> 0 | I63: TAR | L63: 1 x | M63: 0 | N63: =1*M63 -> 0
C64: SUB - TOTAL | E64: =SUM(E51:F63) -> 5183090 | I64: TAR | L64: SUB - TOTAL | N64: =SUM(N51:N63) -> 3542790
I65: TAR | K65: =SUM(H61:H65) -> 0
D66: TOTAL | F66: =D47+E64 -> 7460963 | I66: NOC | L66: PREMOS | N66: 1060087.4
I67: NOC | L67: TELEKINOS | N67: 0
D68: DIFERENCIA | F68: =F66-H36 -> -330742.02 | I68: NOC | L68: BOL. S/PREMIOS | N68: 3115613.4
I69: NOC | L69: OTROS | N69: 0
C70: DEPOSITO | I70: NOC | M70: SUB- TOTAL | N70: =SUM(N66:N69) -> 4175700.8
I71: NOC | K71: =SUM(H66:H71) -> 0
C72: 6071518.9
H73: =SUM(H51:H71) -> 0 | M73: TOTAL | N73: =N64+N70 -> 7718490.8
L75: ARQUEO DE CAJA AL CIERRE (COMPOSICION DEL SALDO)
C76: TOTAL DE INGRESO | H76: =H8+H36+N47 -> 16067858 | L76: PREMIOS | N76: =N70 -> 4175700.8
L77: EFECTIVO | N77: =N64 -> 3542790
C78: TOTAL DE EGRESO | H78: =H73+H40+D40+D42+D43+D44+D45+H41+H42+H43+H44+H45 -> 8349391.9 | L78: TOTAL DE CAJA AL CIERRE | N78: =N70+N64 -> 7718490.8
C80: SALDO DEL DIA | H80: =H76-H78 -> 7718466.5 | L80: DIFERENCIA DE CAJA | N80: =N78-H80 -> 24.3
L81: (+) POSITIVO | M81: (-) NEGATIVO

Sheet 0501
A1: z
D2: PLANILLA DE RECAUDACION DIARIA DE APUESTA Y PREMIOS | M2: ='0101'!M2 -> 2025
D4: FECHA : | E4: 45170 | G4: RECAUDACION DEL DIA: | I4: 45169
C6: 26 | D6: SALDO DEL DIA ANTERIOR | G6: PREMIOS | H6: ='0401'!N76 -> 4175700.8
G7: EFECTIVO | H7: ='0401'!N77 -> 3542790
G8: TOTAL | H8: =H6+H7 -> 7718490.8 | Q8: TICKET ANULADOS | AA8: TICKET PREMIADOS | AL8: TICKET VENDIDOS
C10: MATUTINA | D10: VESPERT. | E10: SIESTA | F10: TARDE | G10: NOCT. | H10: TOTAL | J10: PREMIOS | K10: EFECTIVO | L10: MONEDAS | M10: TOTAL | N10: DIFER. | Q10: M | R10: V | S10: S | T10: T | U10: N | V10: TOTAL | X10: PRES. | Y10: DIFER. | AA10: ANT | AB10: M | AC10: V | AD10: S | AE10: T | AF10: N | AG10: TOTAL | AI10: PRES | AJ10: DIFER. | AL10: M | AM10: V | AN10: S | AO10: T | AP10: N | AQ10: TOTAL | AS10: PRES. | AT10: DIFER.
H11: =SUM(H12:H15) -> 1031500
B12: 001 | C12: 187500 | D12: 35400 | E12: 4400 | F12: 22300 | G12: 148200 | H12: =SUM(C12:G12) -> 397800 | I12: 001 | J12: 147368.42 | K12: 250200 | M12: =SUM(J12:L12) -> 397568.42 | N12: =H12-M12 -> 231.58 | Q12: 2 | V12: =U12+T12+S12+R12+Q12 -> 2 | X12: 0 | Y12: =V12-X12 -> 2 | Z12: V | AA12: 3 | AC12: 1 | AG12: =AF12+AE12+AD12+AC12+AB12+AA12 -> 4 | AI12: 0 | AJ12: =AG12-AI12 -> 4 | AL12: 89 | AM12: 28 | AN12: 6 | AO12: 19 | AP12: 73 | AQ12: =AP12+AO12+AN12+AM12+AL12 -> 215 | AS12: 0 | AT12: =AQ12-AS12 -> 215
B13: 002 | E13: 52000 | F13: 65300 | G13: 101200 | H13: =SUM(C13:G13) -> 218500 | I13: 002 | J13: 92289.47 | K13: 126300 | L13: -89.47 | M13: =SUM(J13:L13) -> 218500 | N13: =H13-M13 -> 0 | S13: 1 | V13: =U13+T13+S13+R13+Q13 -> 1 | X13: 0 | Y13: =V13-X13 -> 1 | Z13: L | AA13: 1 | AB13: 1 | AE13: 4 | AG13: =AF13+AE13+AD13+AC13+AB13+AA13 -> 6 | AJ13: =AG13-AI13 -> 6 | AN13: 18 | AO13: 26 | AP13: 53 | AQ13: =AP13+AO13+AN13+AM13+AL13 -> 97 | AS13: 0 | AT13: =AQ13-AS13 -> 97
B14: 003 | C14: 227600 | D14: 137050 | E14: 19850 | F14: 14650 | G14: 16050 | H14: =SUM(C14:G14) -> 415200 | I14: 003 | J14: 126000 | K14: 289200 | M14: =SUM(J14:L14) -> 415200 | N14: =H14-M14 -> 0 | V14: =U14+T14+S14+R14+Q14 -> 0 | X14: 0 | Y14: =V14-X14 -> 0 | Z14: M | AA14: 4 | AB14: 1 | AG14: =AF14+AE14+AD14+AC14+AB14+AA14 -> 5 | AJ14: =AG14-AI14 -> 5 | AL14: 111 | AM14: 90 | AN14: 23 | AO14: 17 | AP14: 18 | AQ14: =AP14+AO14+AN14+AM14+AL14 -> 259 | AS14: 0 | AT14: =AQ14-AS14 -> 259
B15: 004 | H15: =SUM(C15:G15) -> 0 | I15: 004 | J15: 1060087.4 | L15: -1060087.4 | M15: =SUM(J15:L15) -> 0 | N15: =H15-M15 -> 0 | V15: =U15+T15+S15+R15+Q15 -> 0 | X15: 0 | Y15: =V15-X15 -> 0 | AG15: =AF15+AE15+AD15+AC15+AB15+AA15 -> 0 | AJ15: =AG15-AI15 -> 0 | AQ15: =AP15+AO15+AN15+AM15+AL15 -> 0 | AS15: 0 | AT15: =AQ15-AS15 -> 0
B16: 26/001 | C16: 190350 | D16: 85650 | E16: 20350 | F16: 39850 | G16: 108550 | H16: =SUM(C16:G16) -> 444750 | I16: 01 | J16: 252000 | K16: 192800 | L16: -50 | M16: =SUM(J16:L16) -> 444750 | N16: =H16-M16 -> 0 | Q16: 3 | S16: 1 | U16: 1 | V16: =U16+T16+S16+R16+Q16 -> 5 | X16: 0 | Y16: =V16-X16 -> 5 | Z16: 01 | AA16: 5 | AB16: 1 | AC16: 2 | AD16: 1 | AG16: =AF16+AE16+AD16+AC16+AB16+AA16 -> 9 | AJ16: =AG16-AI16 -> 9 | AK16: 01 | AL16: 108 | AM16: 65 | AN16: 27 | AO16: 28 | AP16: 65 | AQ16: =AP16+AO16+AN16+AM16+AL16 -> 293 | AS16: 0 | AT16: =AQ16-AS16 -> 293
B17: 26/002 | C17: 358350 | D17: 285900 | E17: 103750 | F17: 128650 | G17: 216050 | H17: =SUM(C17:G17) -> 1092700 | I17: 02 | J17: 651000 | K17: 441700 | M17: =SUM(J17:L17) -> 1092700 | N17: =H17-M17 -> 0 | Q17: 2 | R17: 2 | S17: 4 | T17: 1 | U17: 1 | V17: =U17+T17+S17+R17+Q17 -> 10 | X17: 0 | Y17: =V17-X17 -> 10 | Z17: 02 | AA17: 10 | AC17: 1 | AE17: 2 | AG17: =AF17+AE17+AD17+AC17+AB17+AA17 -> 13 | AJ17: =AG17-AI17 -> 13 | AK17: 02 | AL17: 215 | AM17: 155 | AN17: 96 | AO17: 98 | AP17: 187 | AQ17: =AP17+AO17+AN17+AM17+AL17 -> 751 | AS17: 0 | AT17: =AQ17-AS17 -> 751
B18: 26/003 | C18: 162000 | D18: 124200 | E18: 116000 | F18: 122300 | G18: 195300 | H18: =SUM(C18:G18) -> 719800 | I18: 03 | J18: 306600 | K18: 413200 | M18: =SUM(J18:L18) -> 719800 | N18: =H18-M18 -> 0 | V18: =U18+T18+S18+R18+Q18 -> 0 | X18: 0 | Y18: =V18-X18 -> 0 | Z18: 03 | AA18: 3 | AB18: 1 | AC18: 3 | AE18: 1 | AG18: =AF18+AE18+AD18+AC18+AB18+AA18 -> 8 | AJ18: =AG18-AI18 -> 8 | AK18: 03 | AL18: 79 | AM18: 75 | AN18: 61 | AO18: 48 | AP18: 100 | AQ18: =AP18+AO18+AN18+AM18+AL18 -> 363 | AS18: 0 | AT18: =AQ18-AS18 -> 363
B19: 26/004 | C19: 137850 | D19: 145050 | E19: 88000 | F19: 112350 | G19: 208100 | H19: =SUM(C19:G19) -> 691350 | I19: 04 | J19: 745500 | L19: -58150 | M19: =SUM(J19:L19) -> 687350 | N19: =H19-M19 -> 4000 | U19: 1 | V19: =U19+T19+S19+R19+Q19 -> 1 | X19: 0 | Y19: =V19-X19 -> 1 | Z19: 04 | AA19: 7 | AC19: 2 | AE19: 1 | AG19: =AF19+AE19+AD19+AC19+AB19+AA19 -> 10 | AJ19: =AG19-AI19 -> 10 | AK19: 04 | AL19: 62 | AM19: 83 | AN19: 45 | AO19: 58 | AP19: 104 | AQ19: =AP19+AO19+AN19+AM19+AL19 -> 352 | AS19: 0 | AT19: =AQ19-AS19 -> 352
B20: 26/005 | C20: 61100 | D20: 79900 | E20: 62200 | F20: 27200 | G20: 78400 | H20: =SUM(C20:G20) -> 308800 | I20: 05 | J20: 227500 | K20: 81300 | M20: =SUM(J20:L20) -> 308800 | N20: =H20-M20 -> 0 | Q20: 1 | R20: 4 | S20: 1 | V20: =U20+T20+S20+R20+Q20 -> 6 | X20: 0 | Y20: =V20-X20 -> 6 | Z20: 05 | AC20: 2 | AD20: 1 | AG20: =AF20+AE20+AD20+AC20+AB20+AA20 -> 3 | AJ20: =AG20-AI20 -> 3 | AK20: 05 | AL20: 36 | AM20: 45 | AN20: 25 | AO20: 17 | AP20: 41 | AQ20: =AP20+AO20+AN20+AM20+AL20 -> 164 | AS20: 0 | AT20: =AQ20-AS20 -> 164
B21: 26/006 | C21: 134300 | D21: 139800 | E21: 65600 | F21: 92100 | G21: 168300 | H21: =SUM(C21:G21) -> 600100 | I21: 06 | J21: 332150 | K21: 268000 | L21: -50 | M21: =SUM(J21:L21) -> 600100 | N21: =H21-M21 -> 0 | R21: 1 | T21: 1 | U21: 3 | V21: =U21+T21+S21+R21+Q21 -> 5 | X21: 0 | Y21: =V21-X21 -> 5 | Z21: 06 | AA21: 4 | AB21: 1 | AC21: 8 | AD21: 1 | AE21: 3 | AG21: =AF21+AE21+AD21+AC21+AB21+AA21 -> 17 | AJ21: =AG21-AI21 -> 17 | AK21: 06 | AL21: 64 | AM21: 96 | AN21: 45 | AO21: 49 | AP21: 97 | AQ21: =AP21+AO21+AN21+AM21+AL21 -> 351 | AS21: 0 | AT21: =AQ21-AS21 -> 351
B22: 26/007 | C22: 132550 | D22: 179850 | E22: 75600 | F22: 150300 | G22: 283050 | H22: =SUM(C22:G22) -> 821350 | I22: 07 | J22: 833773.2 | L22: -12423.2 | M22: =SUM(J22:L22) -> 821350 | N22: =H22-M22 -> 0 | V22: =U22+T22+S22+R22+Q22 -> 0 | X22: 0 | Y22: =V22-X22 -> 0 | Z22: 07 | AA22: 5 | AB22: 1 | AC22: 5 | AD22: 1 | AE22: 2 | AG22: =AF22+AE22+AD22+AC22+AB22+AA22 -> 14 | AJ22: =AG22-AI22 -> 14 | AK22: 07 | AL22: 99 | AM22: 130 | AN22: 57 | AO22: 105 | AP22: 157 | AQ22: =AP22+AO22+AN22+AM22+AL22 -> 548 | AS22: 0 | AT22: =AQ22-AS22 -> 548
B23: 26/008 | C23: 34100 | D23: 36000 | E23: 39000 | F23: 19000 | G23: 22800 | H23: =SUM(C23:G23) -> 150900 | I23: 08 | J23: 220500 | L23: -69600 | M23: =SUM(J23:L23) -> 150900 | N23: =H23-M23 -> 0 | V23: =U23+T23+S23+R23+Q23 -> 0 | X23: 0 | Y23: =V23-X23 -> 0 | Z23: 08 | AA23: 3 | AC23: 3 | AE23: 2 | AG23: =AF23+AE23+AD23+AC23+AB23+AA23 -> 8 | AJ23: =AG23-AI23 -> 8 | AK23: 08 | AL23: 32 | AM23: 37 | AN23: 22 | AO23: 23 | AP23: 26 | AQ23: =AP23+AO23+AN23+AM23+AL23 -> 140 | AS23: 0 | AT23: =AQ23-AS23 -> 140
B24: 26/009 | C24: 70600 | D24: 111300 | E24: 16200 | F24: 39500 | G24: 133000 | H24: =SUM(C24:G24) -> 370600 | I24: 09 | J24: 129500 | K24: 241100 | M24: =SUM(J24:L24) -> 370600 | N24: =H24-M24 -> 0 | Q24: 1 | R24: 1 | V24: =U24+T24+S24+R24+Q24 -> 2 | X24: 0 | Y24: =V24-X24 -> 2 | Z24: 09 | AA24: 5 | AC24: 1 | AE24: 2 | AG24: =AF24+AE24+AD24+AC24+AB24+AA24 -> 8 | AJ24: =AG24-AI24 -> 8 | AK24: 09 | AL24: 57 | AM24: 75 | AN24: 14 | AO24: 32 | AP24: 72 | AQ24: =AP24+AO24+AN24+AM24+AL24 -> 250 | AS24: 0 | AT24: =AQ24-AS24 -> 250
B25: 26/010 | H25: =SUM(C25:G25) -> 0 | I25: 10 | M25: =SUM(J25:L25) -> 0 | N25: =H25-M25 -> 0 | V25: =U25+T25+S25+R25+Q25 -> 0 | X25: 0 | Y25: =V25-X25 -> 0 | Z25: 10 | AG25: =AF25+AE25+AD25+AC25+AB25+AA25 -> 0 | AJ25: =AG25-AI25 -> 0 | AK25: 10 | AQ25: =AP25+AO25+AN25+AM25+AL25 -> 0 | AS25: 0 | AT25: =AQ25-AS25 -> 0
B26: 26/011 | C26: 66200 | D26: 43200 | E26: 67300 | F26: 74650 | G26: 94000 | H26: =SUM(C26:G26) -> 345350 | I26: 11 | J26: 105000 | K26: 240350 | M26: =SUM(J26:L26) -> 345350 | N26: =H26-M26 -> 0 | Q26: 1 | T26: 1 | V26: =U26+T26+S26+R26+Q26 -> 2 | X26: 0 | Y26: =V26-X26 -> 2 | Z26: 11 | AC26: 2 | AE26: 2 | AG26: =AF26+AE26+AD26+AC26+AB26+AA26 -> 4 | AJ26: =AG26-AI26 -> 4 | AK26: 11 | AL26: 51 | AM26: 36 | AN26: 59 | AO26: 57 | AP26: 78 | AQ26: =AP26+AO26+AN26+AM26+AL26 -> 281 | AS26: 0 | AT26: =AQ26-AS26 -> 281
B27: 26/012 | C27: 88750 | D27: 126455 | E27: 65650 | F27: 55050 | G27: 125850 | H27: =SUM(C27:G27) -> 461755 | I27: 12 | J27: 407750 | K27: 54000 | M27: =SUM(J27:L27) -> 461750 | N27: =H27-M27 -> 5 | Q27: 2 | R27: 2 | V27: =U27+T27+S27+R27+Q27 -> 4 | X27: 0 | Y27: =V27-X27 -> 4 | Z27: 12 | AA27: 6 | AB27: 1 | AC27: 5 | AD27: 1 | AE27: 2 | AG27: =AF27+AE27+AD27+AC27+AB27+AA27 -> 15 | AJ27: =AG27-AI27 -> 15 | AK27: 12 | AL27: 79 | AM27: 74 | AN27: 48 | AO27: 41 | AP27: 114 | AQ27: =AP27+AO27+AN27+AM27+AL27 -> 356 | AS27: 0 | AT27: =AQ27-AS27 -> 356
B28: 26/013 | C28: 111950 | D28: 193750 | E28: 135100 | F28: 75300 | G28: 240400 | H28: =SUM(C28:G28) -> 756500 | I28: 13 | J28: 75600 | K28: 680900 | M28: =SUM(J28:L28) -> 756500 | N28: =H28-M28 -> 0 | S28: 2 | T28: 1 | V28: =U28+T28+S28+R28+Q28 -> 3 | X28: 0 | Y28: =V28-X28 -> 3 | Z28: 13 | AA28: 2 | AC28: 2 | AD28: 2 | AG28: =AF28+AE28+AD28+AC28+AB28+AA28 -> 6 | AJ28: =AG28-AI28 -> 6 | AK28: 13 | AL28: 55 | AM28: 87 | AN28: 62 | AO28: 34 | AP28: 86 | AQ28: =AP28+AO28+AN28+AM28+AL28 -> 324 | AS28: 0 | AT28: =AQ28-AS28 -> 324
B29: 26/014 | C29: 72800 | D29: 37300 | E29: 24700 | F29: 41000 | G29: 71400 | H29: =SUM(C29:G29) -> 247200 | I29: 14 | J29: 106400 | K29: 139800 | L29: 1000 | M29: =SUM(J29:L29) -> 247200 | N29: =H29-M29 -> 0 | V29: =U29+T29+S29+R29+Q29 -> 0 | X29: 0 | Y29: =V29-X29 -> 0 | Z29: 14 | AA29: 2 | AC29: 1 | AD29: 1 | AE29: 3 | AG29: =AF29+AE29+AD29+AC29+AB29+AA29 -> 7 | AJ29: =AG29-AI29 -> 7 | AK29: 14 | AL29: 62 | AM29: 28 | AN29: 17 | AO29: 28 | AP29: 62 | AQ29: =AP29+AO29+AN29+AM29+AL29 -> 197 | AS29: 0 | AT29: =AQ29-AS29 -> 197
B30: 26/015 | H30: =SUM(C30:G30) -> 0 | I30: 15 | M30: =SUM(J30:L30) -> 0 | N30: =H30-M30 -> 0 | V30: =U30+T30+S30+R30+Q30 -> 0 | X30: 0 | Y30: =V30-X30 -> 0 | Z30: 15 | AG30: =AF30+AE30+AD30+AC30+AB30+AA30 -> 0 | AJ30: =AG30-AI30 -> 0 | AK30: 15 | AQ30: =AP30+AO30+AN30+AM30+AL30 -> 0 | AS30: 0 | AT30: =AQ30-AS30 -> 0
B31: 26/016 | C31: 162000 | D31: 198900 | E31: 111100 | F31: 111400 | G31: 133000 | H31: =SUM(C31:G31) -> 716400 | I31: 16 | J31: 132200 | K31: 584200 | M31: =SUM(J31:L31) -> 716400 | N31: =H31-M31 -> 0 | R31: 1 | V31: =U31+T31+S31+R31+Q31 -> 1 | X31: 0 | Y31: =V31-X31 -> 1 | Z31: 16 | AA31: 2 | AB31: 2 | AC31: 1 | AE31: 2 | AG31: =AF31+AE31+AD31+AC31+AB31+AA31 -> 7 | AJ31: =AG31-AI31 -> 7 | AK31: 16 | AL31: 90 | AM31: 115 | AN31: 55 | AO31: 57 | AP31: 77 | AQ31: =AP31+AO31+AN31+AM31+AL31 -> 394 | AS31: 0 | AT31: =AQ31-AS31 -> 394
B32: 26/017 | C32: 61900 | D32: 44800 | E32: 12000 | F32: 23000 | G32: 36600 | H32: =SUM(C32:G32) -> 178300 | I32: 17 | J32: 77000 | K32: 101200 | M32: =SUM(J32:L32) -> 178200 | N32: =H32-M32 -> 100 | V32: =U32+T32+S32+R32+Q32 -> 0 | X32: 0 | Y32: =V32-X32 -> 0 | Z32: 17 | AA32: 2 | AG32: =AF32+AE32+AD32+AC32+AB32+AA32 -> 2 | AJ32: =AG32-AI32 -> 2 | AK32: 17 | AL32: 44 | AM32: 24 | AN32: 11 | AO32: 14 | AP32: 25 | AQ32: =AP32+AO32+AN32+AM32+AL32 -> 118 | AS32: 0 | AT32: =AQ32-AS32 -> 118
B33: 26/018 | H33: =SUM(C33:G33) -> 0 | I33: 18 | M33: =SUM(J33:L33) -> 0 | N33: =H33-M33 -> 0 | V33: =U33+T33+S33+R33+Q33 -> 0 | X33: 0 | Y33: =V33-X33 -> 0 | Z33: 18 | AG33: =AF33+AE33+AD33+AC33+AB33+AA33 -> 0 | AJ33: =AG33-AI33 -> 0 | AK33: 18 | AQ33: =AP33+AO33+AN33+AM33+AL33 -> 0 | AS33: 0 | AT33: =AQ33-AS33 -> 0
B34: 26/019 | H34: =SUM(C34:G34) -> 0 | I34: 19 | M34: =SUM(J34:L34) -> 0 | N34: =H34-M34 -> 0 | V34: =U34+T34+S34+R34+Q34 -> 0 | X34: 0 | Y34: =V34-X34 -> 0 | Z34: 19 | AG34: =AF34+AE34+AD34+AC34+AB34+AA34 -> 0 | AJ34: =AG34-AI34 -> 0 | AK34: 19 | AQ34: =AP34+AO34+AN34+AM34+AL34 -> 0 | AS34: 0 | AT34: =AQ34-AS34 -> 0
C36: =SUM(C12:C34) -> 2259900 | D36: =SUM(D12:D34) -> 2004505 | E36: =SUM(E12:E34) -> 1078800 | F36: =SUM(F12:F34) -> 1213900 | G36: =SUM(G12:G34) -> 2380250 | H36: =SUM(H12:H34) -> 8937355 | J36: =SUM(J12:J34) -> 6028218.5 | K36: =SUM(K12:K35) -> 4104250 | L36: =SUM(L13:L34) -> -1199450.1 | M36: =SUM(M12:M34) -> 8933018.4 | Q36: TOTAL ANULADAS | U36: =SUM(V12:V34) -> 42 | X36: =SUM(X12:X34) -> 0 | AA36: TOTAL PREMIADAS | AF36: =SUM(AG12:AG34) -> 146 | AI36: =SUM(AI12:AI34) -> 0 | AL36: TOTAL VENDIDAS | AP36: =SUM(AQ12:AQ34) -> 5453 | AS36: =SUM(AS12:AS34) -> 0
B38: DEBEN / SALIDA | J38: PAGAN / ENTRADA
B40: MARTIN GASTOS | D40: 0 | E40: DEPOSITOS | H40: =D41+C72 -> 6028218.5 | J40: DEUDA DE CAJA s/l/v | L40: 0 | M40: EXCEDENTE | N40: 0
B41: PREMIOS | D41: =J36 -> 6028218.5 | E41: PREST. PALP. | H41: 0 | J41: FALTANTE DE CAJA | L41: 0 | M41: MARTIN | N41: 0
B42: LIBRERIA | D42: 0 | E42: PREST. TELEKINO | H42: 0 | J42: PREST. PALP./ REVISTA | L42: 0 | M42: PREMIOS | N42: 0
B43: LIMPIEZA | D43: 0 | E43: PREST. JGOS. MENORES | H43: 0 | J43: PREST. TELEKINO | L43: 0 | N43: 0
B44: SODA/AGUA | D44: 0 | E44: IMPUESTOS | H44: 0 | J44: PREST. JGOS. MENORES | L44: 0 | N44: 0
B45: GASTOS VARIOS | D45: 0 | E45: OTROS | H45: =SUM(N12:N34) -> 4336.58 | L45: 0 | N45: 0
B47: SUB TOTAL | D47: =D40+D41+D42+D43+D44+D45+H41+H42+H43+H44+H45 -> 6032555.1 | G47: TOTAL | H47: =D47+H40 -> 12060774 | M47: SUB TOTAL | N47: =L40+L41+L42+L43+L44+L45+N40+N41+N42+N43+N44+N45 -> 0
C49: DETALLE RECAUDACION DE CAJA | H49: IMPORTE | J49: FECHA | L49: DETALLE CIERRE DE CAJA
C51: 20000 x | D51: 58 | E51: =20000*D51 -> 1160000 | I51: MAT | L51: 20000 x | M51: 141 | N51: =20000*M51 -> 2820000
C52: 10000 x | D52: 156 | E52: =10000*D52 -> 1560000 | I52: MAT | L52: 10000 x | M52: 207 | N52: =10000*M52 -> 2070000
C53: 2000 x | D53: 296 | E53: =2000*D53 -> 592000 | I53: MAT | L53: 2000 x | M53: 305 | N53: =2000*M53 -> 610000
C54: 1000 x | D54: 670 | E54: =1000*D54 -> 670000 | I54: MAT | L54: 1000 x | M54: 229 | N54: =1000*M54 -> 229000
C55: 500 x | D55: 85 | E55: =500*D55 -> 42500 | I55: MAT | K55: =SUM(H51:H55) -> 0 | L55: 500 x | M55: 362 | N55: =500*M55 -> 181000
C56: 200 x | D56: 52 | E56: =200*D56 -> 10400 | I56: VEP | L56: 200 x | M56: 772 | N56: =200*M56 -> 154400
C57: 100 x | D57: 122 | E57: =100*D57 -> 12200 | I57: VEP | L57: 100 x | M57: 38 | N57: =100*M57 -> 3800
C58: 50 x | D58: 0 | E58: =50*D58 -> 0 | I58: VEP | L58: 50 x | M58: 1794 | N58: =50*M58 -> 89700
C59: 20 x | D59: 0 | E59: =20*D59 -> 0 | I59: VEP | L59: 20 x | M59: 1515 | N59: =20*M59 -> 30300
C60: 10 x | D60: 0 | E60: =10*D60 -> 0 | I60: VEP | K60: =SUM(H56:H60) -> 0 | L60: 10 x | M60: 340 | N60: =10*M60 -> 3400
C61: 5 x | D61: 0 | E61: =5*D61 -> 0 | I61: TAR | L61: 5 x | M61: 0 | N61: =5*M61 -> 0
C62: 2 x | D62: 0 | E62: =2*D62 -> 0 | I62: TAR | L62: 2 x | M62: 0 | N62: =2*M62 -> 0
C63: 1 x | D63: 0 | E63: =1*D63 -> 0 | I63: TAR | L63: 1 x | M63: 0 | N63: =1*M63 -> 0
C64: SUB - TOTAL | E64: =SUM(E51:F63) -> 4047100 | I64: TAR | L64: SUB - TOTAL | N64: =SUM(N51:N63) -> 6191600
I65: TAR | K65: =SUM(H61:H65) -> 0
D66: TOTAL | F66: =D47+F64 -> 6032555.1 | I66: NOC | L66: PREMOS | N66: 1316000
I67: NOC | L67: TELEKINOS | N67: 0
D68: DIFERENCIA | F68: =F66-H36 -> -2904799.9 | I68: NOC | L68: BOL. S/PREMIOS | N68: 3115613.4
I69: NOC | L69: OTROS | N69: 0
C70: DEPOSITO | I70: NOC | M70: SUB- TOTAL | N70: =SUM(N66:N69) -> 4431613.4
I71: NOC | K71: =SUM(H66:H71) -> 0
C72: 0
H73: =SUM(H51:H71) -> 0 | M73: TOTAL | N73: =N64+N70 -> 10623213
L75: ARQUEO DE CAJA AL CIERRE (COMPOSICION DEL SALDO)
C76: TOTAL DE INGRESO | H76: =H8+H36+N47 -> 16655846 | L76: PREMIOS | N76: =N70 -> 4431613.4
L77: EFECTIVO | N77: =N64 -> 6191600
C78: TOTAL DE EGRESO | H78: =H73+H40+D40+D42+D43+D44+D45+H41+H42+H43+H44+H45 -> 6032555.1 | L78: TOTAL DE CAJA AL CIERRE | N78: =N70+N64 -> 10623213
C80: SALDO DEL DIA | H80: =H76-H78 -> 10623291 | L80: DIFERENCIA DE CAJA | N80: =N78-H80 -> -77.33
L81: (+) POSITIVO | M81: (-) NEGATIVO

Sheet 0601
D3: PLANILLA DE RECAUDACION DIARIA DE APUESTA Y PREMIOS | M3: ='0101'!M2 -> 2025
D5: FECHA : | E5: 45170 | G5: RECAUDACION DEL DIA: | I5: 45169
C7: 26 | D7: SALDO DEL DIA ANTERIOR | G7: PREMIOS | H7: ='0501'!N76 -> 4431613.4
G8: EFECTIVO | H8: ='0501'!N77 -> 6191600
G9: TOTAL | H9: =H7+H8 -> 10623213 | Q9: TICKET ANULADOS | AA9: TICKET PREMIADOS | AL9: TICKET VENDIDOS
C11: MATUTINA | D11: VESPERT. | E11: SIESTA | F11: TARDE | G11: NOCT. | H11: TOTAL | J11: PREMIOS | K11: EFECTIVO | L11: MONEDAS | M11: TOTAL | N11: DIFER. | Q11: M | R11: V | S11: S | T11: T | U11: N | V11: TOTAL | X11: PRES. | Y11: DIFER. | AA11: ANT | AB11: M | AC11: V | AD11: S | AE11: T | AF11: N | AG11: TOTAL | AI11: PRES | AJ11: DIFER. | AL11: M | AM11: V | AN11: S | AO11: T | AP11: N | AQ11: TOTAL | AS11: PRES. | AT11: DIFER.
H12: =SUM(H13:H16) -> 1086900
B13: 001 | C13: 171400 | D13: 142600 | E13: 13700 | F13: 14500 | G13: 23600 | H13: =SUM(C13:G13) -> 365800 | I13: 001 | J13: 85750 | K13: 279000 | M13: =SUM(J13:L13) -> 364750 | N13: =H13-M13 -> 1050 | Q13: 4 | V13: =U13+T13+S13+R13+Q13 -> 4 | X13: 0 | Y13: =V13-X13 -> 4 | Z13: V | AA13: 7 | AG13: =AF13+AE13+AD13+AC13+AB13+AA13 -> 7 | AI13: 0 | AJ13: =AG13-AI13 -> 7 | AL13: 102 | AM13: 73 | AN13: 9 | AO13: 6 | AP13: 14 | AQ13: =AP13+AO13+AN13+AM13+AL13 -> 204 | AS13: 0 | AT13: =AQ13-AS13 -> 204
B14: 002 | E14: 4600 | F14: 26900 | G14: 60900 | H14: =SUM(C14:G14) -> 92400 | I14: 002 | K14: 92400 | M14: =SUM(J14:L14) -> 92400 | N14: =H14-M14 -> 0 | V14: =U14+T14+S14+R14+Q14 -> 0 | X14: 0 | Y14: =V14-X14 -> 0 | Z14: L | AD14: 1 | AE14: 1 | AG14: =AF14+AE14+AD14+AC14+AB14+AA14 -> 2 | AJ14: =AG14-AI14 -> 2 | AN14: 7 | AO14: 14 | AP14: 37 | AQ14: =AP14+AO14+AN14+AM14+AL14 -> 58 | AS14: 0 | AT14: =AQ14-AS14 -> 58
B15: 003 | C15: 190500 | D15: 119900 | E15: 46000 | F15: 75700 | G15: 196600 | H15: =SUM(C15:G15) -> 628700 | I15: 003 | J15: 243900 | K15: 384800 | M15: =SUM(J15:L15) -> 628700 | N15: =H15-M15 -> 0 | V15: =U15+T15+S15+R15+Q15 -> 0 | X15: 0 | Y15: =V15-X15 -> 0 | Z15: M | AA15: 4 | AB15: 1 | AG15: =AF15+AE15+AD15+AC15+AB15+AA15 -> 5 | AJ15: =AG15-AI15 -> 5 | AL15: 98 | AM15: 73 | AN15: 26 | AO15: 45 | AP15: 87 | AQ15: =AP15+AO15+AN15+AM15+AL15 -> 329 | AS15: 0 | AT15: =AQ15-AS15 -> 329
B16: 004 | H16: =SUM(C16:G16) -> 0 | I16: 004 | J16: 1316000 | L16: -1316000 | M16: =SUM(J16:L16) -> 0 | N16: =H16-M16 -> 0 | V16: =U16+T16+S16+R16+Q16 -> 0 | X16: 0 | Y16: =V16-X16 -> 0 | AG16: =AF16+AE16+AD16+AC16+AB16+AA16 -> 0 | AJ16: =AG16-AI16 -> 0 | AQ16: =AP16+AO16+AN16+AM16+AL16 -> 0 | AS16: 0 | AT16: =AQ16-AS16 -> 0
B17: 26/001 | C17: 84850 | D17: 102750 | E17: 32800 | F17: 33950 | G17: 107800 | H17: =SUM(C17:G17) -> 362150 | I17: 01 | J17: 178500 | K17: 183700 | L17: -50 | M17: =SUM(J17:L17) -> 362150 | N17: =H17-M17 -> 0 | Q17: 1 | R17: 1 | V17: =U17+T17+S17+R17+Q17 -> 2 | X17: 0 | Y17: =V17-X17 -> 2 | Z17: 01 | AB17: 2 | AC17: 3 | AD17: 4 | AG17: =AF17+AE17+AD17+AC17+AB17+AA17 -> 9 | AJ17: =AG17-AI17 -> 9 | AK17: 01 | AL17: 56 | AM17: 78 | AN17: 38 | AO17: 47 | AP17: 88 | AQ17: =AP17+AO17+AN17+AM17+AL17 -> 307 | AS17: 0 | AT17: =AQ17-AS17 -> 307
B18: 26/002 | C18: 477115 | D18: 338265 | E18: 196350 | F18: 301850 | G18: 403050 | H18: =SUM(C18:G18) -> 1716630 | I18: 02 | J18: 846778.95 | K18: 869850 | M18: =SUM(J18:L18) -> 1716628.9 | N18: =H18-M18 -> 1.05 | Q18: 2 | V18: =U18+T18+S18+R18+Q18 -> 2 | X18: 0 | Y18: =V18-X18 -> 2 | Z18: 02 | AA18: 19 | AB18: 7 | AC18: 2 | AD18: 3 | AE18: 6 | AG18: =AF18+AE18+AD18+AC18+AB18+AA18 -> 37 | AJ18: =AG18-AI18 -> 37 | AK18: 02 | AL18: 264 | AM18: 201 | AN18: 132 | AO18: 175 | AP18: 250 | AQ18: =AP18+AO18+AN18+AM18+AL18 -> 1022 | AS18: 0 | AT18: =AQ18-AS18 -> 1022
B19: 26/003 | C19: 160600 | D19: 195200 | E19: 74400 | F19: 116100 | G19: 178100 | H19: =SUM(C19:G19) -> 724400 | I19: 03 | J19: 451500 | K19: 272900 | M19: =SUM(J19:L19) -> 724400 | N19: =H19-M19 -> 0 | V19: =U19+T19+S19+R19+Q19 -> 0 | X19: 0 | Y19: =V19-X19 -> 0 | Z19: 03 | AA19: 5 | AB19: 1 | AD19: 2 | AE19: 5 | AG19: =AF19+AE19+AD19+AC19+AB19+AA19 -> 13 | AJ19: =AG19-AI19 -> 13 | AK19: 03 | AL19: 85 | AM19: 99 | AN19: 39 | AO19: 58 | AP19: 105 | AQ19: =AP19+AO19+AN19+AM19+AL19 -> 386 | AS19: 0 | AT19: =AQ19-AS19 -> 386
B20: 26/004 | C20: 227400 | D20: 230400 | E20: 108900 | F20: 125750 | G20: 260450 | H20: =SUM(C20:G20) -> 952900 | I20: 04 | J20: 665000 | K20: 287900 | M20: =SUM(J20:L20) -> 952900 | N20: =H20-M20 -> 0 | T20: 1 | U20: 4 | V20: =U20+T20+S20+R20+Q20 -> 5 | X20: 0 | Y20: =V20-X20 -> 5 | Z20: 04 | AA20: 7 | AB20: 1 | AE20: 1 | AG20: =AF20+AE20+AD20+AC20+AB20+AA20 -> 9 | AJ20: =AG20-AI20 -> 9 | AK20: 04 | AL20: 103 | AM20: 111 | AN20: 54 | AO20: 78 | AP20: 127 | AQ20: =AP20+AO20+AN20+AM20+AL20 -> 473 | AS20: 0 | AT20: =AQ20-AS20 -> 473
B21: 26/005 | C21: 131300 | D21: 146000 | E21: 45800 | F21: 65800 | G21: 127200 | H21: =SUM(C21:G21) -> 516100 | I21: 05 | J21: 521500 | L21: -5400 | M21: =SUM(J21:L21) -> 516100 | N21: =H21-M21 -> 0 | V21: =U21+T21+S21+R21+Q21 -> 0 | X21: 0 | Y21: =V21-X21 -> 0 | Z21: 05 | AA21: 1 | AB21: 3 | AC21: 2 | AD21: 2 | AE21: 2 | AG21: =AF21+AE21+AD21+AC21+AB21+AA21 -> 10 | AJ21: =AG21-AI21 -> 10 | AK21: 05 | AL21: 54 | AM21: 69 | AN21: 25 | AO21: 34 | AP21: 68 | AQ21: =AP21+AO21+AN21+AM21+AL21 -> 250 | AS21: 0 | AT21: =AQ21-AS21 -> 250
B22: 26/006 | C22: 161700 | D22: 186950 | E22: 72800 | F22: 57600 | G22: 195850 | H22: =SUM(C22:G22) -> 674900 | I22: 06 | J22: 175700 | K22: 499200 | M22: =SUM(J22:L22) -> 674900 | N22: =H22-M22 -> 0 | Q22: 2 | R22: 1 | U22: 2 | V22: =U22+T22+S22+R22+Q22 -> 5 | X22: 0 | Y22: =V22-X22 -> 5 | Z22: 06 | AA22: 5 | AB22: 3 | AC22: 1 | AD22: 1 | AE22: 2 | AG22: =AF22+AE22+AD22+AC22+AB22+AA22 -> 12 | AJ22: =AG22-AI22 -> 12 | AK22: 06 | AL22: 114 | AM22: 125 | AN22: 52 | AO22: 45 | AP22: 117 | AQ22: =AP22+AO22+AN22+AM22+AL22 -> 453 | AS22: 0 | AT22: =AQ22-AS22 -> 453
B23: 26/007 | C23: 330550 | D23: 308200 | E23: 175750 | F23: 237100 | G23: 295950 | H23: =SUM(C23:G23) -> 1347550 | I23: 07 | J23: 639100 | K23: 708500 | L23: -50 | M23: =SUM(J23:L23) -> 1347550 | N23: =H23-M23 -> 0 | V23: =U23+T23+S23+R23+Q23 -> 0 | X23: 0 | Y23: =V23-X23 -> 0 | Z23: 07 | AA23: 9 | AB23: 1 | AD23: 1 | AE23: 9 | AG23: =AF23+AE23+AD23+AC23+AB23+AA23 -> 20 | AJ23: =AG23-AI23 -> 20 | AK23: 07 | AL23: 181 | AM23: 173 | AN23: 95 | AO23: 112 | AP23: 157 | AQ23: =AP23+AO23+AN23+AM23+AL23 -> 718 | AS23: 0 | AT23: =AQ23-AS23 -> 718
B24: 26/008 | C24: 50300 | D24: 73900 | F24: 23500 | G24: 28200 | H24: =SUM(C24:G24) -> 175900 | I24: 08 | J24: 147000 | K24: 28900 | M24: =SUM(J24:L24) -> 175900 | N24: =H24-M24 -> 0 | Q24: 1 | R24: 2 | V24: =U24+T24+S24+R24+Q24 -> 3 | X24: 0 | Y24: =V24-X24 -> 3 | Z24: 08 | AA24: 2 | AB24: 2 | AG24: =AF24+AE24+AD24+AC24+AB24+AA24 -> 4 | AJ24: =AG24-AI24 -> 4 | AK24: 08 | AL24: 30 | AM24: 30 | AO24: 9 | AP24: 24 | AQ24: =AP24+AO24+AN24+AM24+AL24 -> 93 | AS24: 0 | AT24: =AQ24-AS24 -> 93
B25: 26/009 | C25: 109800 | D25: 147400 | E25: 54000 | F25: 77800 | G25: 153650 | H25: =SUM(C25:G25) -> 542650 | I25: 09 | J25: 478100 | K25: 64550 | M25: =SUM(J25:L25) -> 542650 | N25: =H25-M25 -> 0 | Q25: 1 | V25: =U25+T25+S25+R25+Q25 -> 1 | X25: 0 | Y25: =V25-X25 -> 1 | Z25: 09 | AA25: 6 | AB25: 2 | AC25: 1 | AD25: 6 | AE25: 6 | AG25: =AF25+AE25+AD25+AC25+AB25+AA25 -> 21 | AJ25: =AG25-AI25 -> 21 | AK25: 09 | AL25: 81 | AM25: 81 | AN25: 24 | AO25: 41 | AP25: 115 | AQ25: =AP25+AO25+AN25+AM25+AL25 -> 342 | AS25: 0 | AT25: =AQ25-AS25 -> 342
B26: 26/010 | H26: =SUM(C26:G26) -> 0 | I26: 10 | M26: =SUM(J26:L26) -> 0 | N26: =H26-M26 -> 0 | V26: =U26+T26+S26+R26+Q26 -> 0 | X26: 0 | Y26: =V26-X26 -> 0 | Z26: 10 | AG26: =AF26+AE26+AD26+AC26+AB26+AA26 -> 0 | AJ26: =AG26-AI26 -> 0 | AK26: 10 | AQ26: =AP26+AO26+AN26+AM26+AL26 -> 0 | AS26: 0 | AT26: =AQ26-AS26 -> 0
B27: 26/011 | C27: 82400 | D27: 97250 | E27: 42800 | F27: 34000 | G27: 88600 | H27: =SUM(C27:G27) -> 345050 | I27: 11 | J27: 343233.35 | K27: 1850 | L27: -33.35 | M27: =SUM(J27:L27) -> 345050 | N27: =H27-M27 -> 0 | R27: 1 | S27: 2 | V27: =U27+T27+S27+R27+Q27 -> 3 | X27: 0 | Y27: =V27-X27 -> 3 | Z27: 11 | AA27: 12 | AB27: 1 | AC27: 1 | AD27: 4 | AE27: 2 | AG27: =AF27+AE27+AD27+AC27+AB27+AA27 -> 20 | AJ27: =AG27-AI27 -> 20 | AK27: 11 | AL27: 67 | AM27: 82 | AN27: 39 | AO27: 35 | AP27: 57 | AQ27: =AP27+AO27+AN27+AM27+AL27 -> 280 | AS27: 0 | AT27: =AQ27-AS27 -> 280
B28: 26/012 | C28: 131800 | D28: 135350 | E28: 50050 | F28: 84500 | G28: 226650 | H28: =SUM(C28:G28) -> 628350 | I28: 12 | J28: 732550 | L28: -104200 | M28: =SUM(J28:L28) -> 628350 | N28: =H28-M28 -> 0 | Q28: 4 | S28: 1 | V28: =U28+T28+S28+R28+Q28 -> 5 | X28: 0 | Y28: =V28-X28 -> 5 | Z28: 12 | AA28: 9 | AB28: 1 | AC28: 1 | AD28: 4 | AE28: 5 | AG28: =AF28+AE28+AD28+AC28+AB28+AA28 -> 20 | AJ28: =AG28-AI28 -> 20 | AK28: 12 | AL28: 109 | AM28: 105 | AN28: 43 | AO28: 63 | AP28: 147 | AQ28: =AP28+AO28+AN28+AM28+AL28 -> 467 | AS28: 0 | AT28: =AQ28-AS28 -> 467
B29: 26/013 | C29: 189000 | D29: 206400 | E29: 117550 | F29: 87500 | G29: 163300 | H29: =SUM(C29:G29) -> 763750 | I29: 13 | J29: 114100 | K29: 649650 | M29: =SUM(J29:L29) -> 763750 | N29: =H29-M29 -> 0 | R29: 2 | T29: 2 | U29: 2 | V29: =U29+T29+S29+R29+Q29 -> 6 | X29: 0 | Y29: =V29-X29 -> 6 | Z29: 13 | AA29: 1 | AC29: 1 | AD29: 2 | AE29: 2 | AG29: =AF29+AE29+AD29+AC29+AB29+AA29 -> 6 | AJ29: =AG29-AI29 -> 6 | AK29: 13 | AL29: 84 | AM29: 90 | AN29: 54 | AO29: 49 | AP29: 82 | AQ29: =AP29+AO29+AN29+AM29+AL29 -> 359 | AS29: 0 | AT29: =AQ29-AS29 -> 359
B30: 26/014 | C30: 60900 | D30: 86700 | E30: 72450 | F30: 93500 | G30: 159600 | H30: =SUM(C30:G30) -> 473150 | I30: 14 | J30: 159000 | K30: 312650 | L30: 1500 | M30: =SUM(J30:L30) -> 473150 | N30: =H30-M30 -> 0 | U30: 1 | V30: =U30+T30+S30+R30+Q30 -> 1 | X30: 0 | Y30: =V30-X30 -> 1 | Z30: 14 | AA30: 3 | AC30: 1 | AD30: 1 | AG30: =AF30+AE30+AD30+AC30+AB30+AA30 -> 5 | AJ30: =AG30-AI30 -> 5 | AK30: 14 | AL30: 46 | AM30: 47 | AN30: 54 | AO30: 69 | AP30: 110 | AQ30: =AP30+AO30+AN30+AM30+AL30 -> 326 | AS30: 0 | AT30: =AQ30-AS30 -> 326
B31: 26/015 | H31: =SUM(C31:G31) -> 0 | I31: 15 | M31: =SUM(J31:L31) -> 0 | N31: =H31-M31 -> 0 | V31: =U31+T31+S31+R31+Q31 -> 0 | X31: 0 | Y31: =V31-X31 -> 0 | Z31: 15 | AG31: =AF31+AE31+AD31+AC31+AB31+AA31 -> 0 | AJ31: =AG31-AI31 -> 0 | AK31: 15 | AQ31: =AP31+AO31+AN31+AM31+AL31 -> 0 | AS31: 0 | AT31: =AQ31-AS31 -> 0
B32: 26/016 | C32: 123100 | D32: 100000 | E32: 139100 | F32: 110900 | G32: 197400 | H32: =SUM(C32:G32) -> 670500 | I32: 16 | J32: 94500 | K32: 576000 | M32: =SUM(J32:L32) -> 670500 | N32: =H32-M32 -> 0 | Q32: 1 | S32: 1 | V32: =U32+T32+S32+R32+Q32 -> 2 | X32: 0 | Y32: =V32-X32 -> 2 | Z32: 16 | AA32: 3 | AB32: 1 | AD32: 2 | AE32: 2 | AG32: =AF32+AE32+AD32+AC32+AB32+AA32 -> 8 | AJ32: =AG32-AI32 -> 8 | AK32: 16 | AL32: 90 | AM32: 89 | AN32: 93 | AO32: 79 | AP32: 127 | AQ32: =AP32+AO32+AN32+AM32+AL32 -> 478 | AS32: 0 | AT32: =AQ32-AS32 -> 478
B33: 26/017 | C33: 47800 | D33: 127100 | E33: 10100 | F33: 23500 | G33: 45400 | H33: =SUM(C33:G33) -> 253900 | I33: 17 | J33: 296666.66 | L33: -42750 | M33: =SUM(J33:L33) -> 253916.66 | N33: =H33-M33 -> -16.66 | V33: =U33+T33+S33+R33+Q33 -> 0 | X33: 0 | Y33: =V33-X33 -> 0 | Z33: 17 | AA33: 3 | AB33: 1 | AC33: 1 | AE33: 4 | AG33: =AF33+AE33+AD33+AC33+AB33+AA33 -> 9 | AJ33: =AG33-AI33 -> 9 | AK33: 17 | AL33: 32 | AM33: 41 | AN33: 10 | AO33: 17 | AP33: 33 | AQ33: =AP33+AO33+AN33+AM33+AL33 -> 133 | AS33: 0 | AT33: =AQ33-AS33 -> 133
B34: 26/018 | H34: =SUM(C34:G34) -> 0 | I34: 18 | M34: =SUM(J34:L34) -> 0 | N34: =H34-M34 -> 0 | V34: =U34+T34+S34+R34+Q34 -> 0 | X34: 0 | Y34: =V34-X34 -> 0 | Z34: 18 | AG34: =AF34+AE34+AD34+AC34+AB34+AA34 -> 0 | AJ34: =AG34-AI34 -> 0 | AK34: 18 | AQ34: =AP34+AO34+AN34+AM34+AL34 -> 0 | AS34: 0 | AT34: =AQ34-AS34 -> 0
B35: 26/019 | H35: =SUM(C35:G35) -> 0 | I35: 19 | M35: =SUM(J35:L35) -> 0 | N35: =H35-M35 -> 0 | V35: =U35+T35+S35+R35+Q35 -> 0 | X35: 0 | Y35: =V35-X35 -> 0 | Z35: 19 | AG35: =AF35+AE35+AD35+AC35+AB35+AA35 -> 0 | AJ35: =AG35-AI35 -> 0 | AK35: 19 | AQ35: =AP35+AO35+AN35+AM35+AL35 -> 0 | AS35: 0 | AT35: =AQ35-AS35 -> 0
C37: =SUM(C13:C35) -> 2730515 | D37: =SUM(D13:D35) -> 2744365 | E37: =SUM(E13:E35) -> 1257150 | F37: =SUM(F13:F35) -> 1590450 | G37: =SUM(G13:G35) -> 2912300 | H37: =SUM(H13:H35) -> 11234780 | J37: =SUM(J13:J35) -> 7488879 | K37: =SUM(K13:K36) -> 5211850 | L37: =SUM(L14:L35) -> -1466983.4 | M37: =SUM(M13:M35) -> 11233746 | Q37: TOTAL ANULADAS | U37: =SUM(V13:V35) -> 39 | X37: =SUM(X13:X35) -> 0 | AA37: TOTAL PREMIADAS | AF37: =SUM(AG13:AG35) -> 217 | AI37: =SUM(AI13:AI35) -> 0 | AL37: TOTAL VENDIDAS | AP37: =SUM(AQ13:AQ35) -> 6678 | AS37: =SUM(AS13:AS35) -> 0
B39: DEBEN / SALIDA | J39: PAGAN / ENTRADA
B41: MARTIN GASTOS | D41: 0 | E41: DEPOSITOS | H41: =D42+C73 -> 21746622 | J41: DEUDA DE CAJA s/l/v | L41: 0 | M41: EXCEDENTE | N41: 0
B42: PREMIOS | D42: =J37 -> 7488879 | E42: PREST. PALP. | H42: 0 | J42: FALTANTE DE CAJA | L42: 0 | M42: MARTIN | N42: 4000000
B43: LIBRERIA | D43: 0 | E43: PREST. TELEKINO | H43: 0 | J43: PREST. PALP./ REVISTA | L43: 0 | M43: PREMIOS | N43: 0
B44: LIMPIEZA | D44: 0 | E44: PREST. JGOS. MENORES | H44: 0 | J44: PREST. TELEKINO | L44: 0 | N44: 0
B45: SODA/AGUA | D45: 0 | E45: IMPUESTOS | H45: 0 | J45: PREST. JGOS. MENORES | L45: 0 | N45: 0
B46: GASTOS VARIOS | D46: 0 | E46: OTROS | H46: =SUM(N13:N35) -> 1034.39 | L46: 0 | N46: 0
B48: SUB TOTAL | D48: =D41+D42+D43+D44+D45+D46+H42+H43+H44+H45+H46 -> 7489913.3 | G48: TOTAL | H48: =D48+H41 -> 29236535 | M48: SUB TOTAL | N48: =L41+L42+L43+L44+L45+L46+N41+N42+N43+N44+N45+N46 -> 4000000
C50: DETALLE RECAUDACION DE CAJA | H50: IMPORTE | J50: FECHA | L50: DETALLE CIERRE DE CAJA
C52: 20000 x | D52: 76 | E52: =20000*D52 -> 1520000 | I52: MAT | L52: 20000 x | M52: 0 | N52: =20000*M52 -> 0
C53: 10000 x | D53: 192 | E53: =10000*D53 -> 1920000 | I53: MAT | L53: 10000 x | M53: 18 | N53: =10000*M53 -> 180000
C54: 2000 x | D54: 403 | E54: =2000*D54 -> 806000 | I54: MAT | L54: 2000 x | M54: 205 | N54: =2000*M54 -> 410000
C55: 1000 x | D55: 915 | E55: =1000*D55 -> 915000 | I55: MAT | L55: 1000 x | M55: 222 | N55: =1000*M55 -> 222000
C56: 500 x | D56: 73 | E56: =500*D56 -> 36500 | I56: MAT | K56: =SUM(H52:H56) -> 0 | L56: 500 x | M56: 33 | N56: =500*M56 -> 16500
C57: 200 x | D57: 35 | E57: =200*D57 -> 7000 | I57: VEP | L57: 200 x | M57: 201 | N57: =200*M57 -> 40200
C58: 100 x | D58: 86 | E58: =100*D58 -> 8600 | I58: VEP | L58: 100 x | M58: 24 | N58: =100*M58 -> 2400
C59: 50 x | D59: 0 | E59: =50*D59 -> 0 | I59: VEP | L59: 50 x | M59: 1796 | N59: =50*M59 -> 89800
C60: 20 x | D60: 0 | E60: =20*D60 -> 0 | I60: VEP | L60: 20 x | M60: 1511 | N60: =20*M60 -> 30220
C61: 10 x | D61: 0 | E61: =10*D61 -> 0 | I61: VEP | K61: =SUM(H57:H61) -> 0 | L61: 10 x | M61: 360 | N61: =10*M61 -> 3600
C62: 5 x | D62: 0 | E62: =5*D62 -> 0 | I62: TAR | L62: 5 x | M62: 0 | N62: =5*M62 -> 0
C63: 2 x | D63: 0 | E63: =2*D63 -> 0 | I63: TAR | L63: 2 x | M63: 0 | N63: =2*M63 -> 0
C64: 1 x | D64: 0 | E64: =1*D64 -> 0 | I64: TAR | L64: 1 x | M64: 0 | N64: =1*M64 -> 0
C65: SUB - TOTAL | E65: =SUM(E52:F64) -> 5213100 | I65: TAR | L65: SUB - TOTAL | N65: =SUM(N52:N64) -> 994720
I66: TAR | K66: =SUM(H62:H66) -> 0
D67: TOTAL | F67: =D48+E65 -> 12703013 | I67: NOC | L67: PREMOS | N67: 0
I68: NOC | L68: TELEKINOS | N68: 0
D69: DIFERENCIA | F69: =F67-H37 -> 1468233.3 | I69: NOC | L69: BOL. S/PREMIOS | N69: 3115613.4
I70: NOC | L70: OTROS | N70: 0
C71: DEPOSITO | I71: NOC | M71: SUB- TOTAL | N71: =SUM(N67:N70) -> 3115613.4
I72: NOC | K72: =SUM(H67:H72) -> 0
C73: 14257743
H74: =SUM(H52:H72) -> 0 | M74: TOTAL | N74: =N65+N71 -> 4110333.4
L76: ARQUEO DE CAJA AL CIERRE (COMPOSICION DEL SALDO)
C77: TOTAL DE INGRESO | H77: =H9+H37+N48 -> 25857993 | L77: PREMIOS | N77: =N71 -> 3115613.4
L78: EFECTIVO | N78: =N65 -> 994720
C79: TOTAL DE EGRESO | H79: =H74+H41+D41+D43+D44+D45+D46+H42+H43+H44+H45+H46 -> 21747656 | L79: TOTAL DE CAJA AL CIERRE | N79: =N71+N65 -> 4110333.4
C81: SALDO DEL DIA | H81: =H77-H79 -> 4110337.5 | L81: DIFERENCIA DE CAJA | N81: =N79-H81 -> -4.1
L82: (+) POSITIVO | M82: (-) NEGATIVO

Sheet 0701
D3: PLANILLA DE RECAUDACION DIARIA DE APUESTA Y PREMIOS | M3: ='0101'!M2 -> 2025
D5: FECHA : | E5: 45170 | G5: RECAUDACION DEL DIA: | I5: 45169
C7: 26 | D7: SALDO DEL DIA ANTERIOR | G7: PREMIOS | H7: ='0601'!N77 -> 3115613.4
G8: EFECTIVO | H8: ='0601'!N78 -> 994720
G9: TOTAL | H9: =H7+H8 -> 4110333.4 | Q9: TICKET ANULADOS | AA9: TICKET PREMIADOS | AL9: TICKET VENDIDOS
B11: SUB | C11: MATUTINA | D11: VESPERT. | E11: SIESTA | F11: TARDE | G11: NOCT. | H11: TOTAL | J11: PREMIOS | K11: EFECTIVO | L11: MONEDAS | M11: TOTAL | N11: DIFER. | Q11: M | R11: V | S11: S | T11: T | U11: N | V11: TOTAL | X11: PRES. | Y11: DIFER. | AA11: ANT | AB11: M | AC11: V | AD11: S | AE11: T | AF11: N | AG11: TOTAL | AI11: PRES | AJ11: DIFER. | AL11: M | AM11: V | AN11: S | AO11: T | AP11: N | AQ11: TOTAL | AS11: PRES. | AT11: DIFER.
H12: =SUM(H13:H16) -> 0
B13: 001 | H13: =SUM(C13:G13) -> 0 | I13: 001 | M13: =SUM(J13:L13) -> 0 | N13: =H13-M13 -> 0 | V13: =U13+T13+S13+R13+Q13 -> 0 | X13: 0 | Y13: =V13-X13 -> 0 | Z13: V | AG13: =AF13+AE13+AD13+AC13+AB13+AA13 -> 0 | AI13: 0 | AJ13: =AG13-AI13 -> 0 | AQ13: =AP13+AO13+AN13+AM13+AL13 -> 0 | AS13: 0 | AT13: =AQ13-AS13 -> 0
B14: 002 | H14: =SUM(C14:G14) -> 0 | I14: 002 | M14: =SUM(J14:L14) -> 0 | N14: =H14-M14 -> 0 | V14: =U14+T14+S14+R14+Q14 -> 0 | X14: 0 | Y14: =V14-X14 -> 0 | Z14: L | AG14: =AF14+AE14+AD14+AC14+AB14+AA14 -> 0 | AJ14: =AG14-AI14 -> 0 | AQ14: =AP14+AO14+AN14+AM14+AL14 -> 0 | AS14: 0 | AT14: =AQ14-AS14 -> 0
B15: 003 | H15: =SUM(C15:G15) -> 0 | I15: 003 | M15: =SUM(J15:L15) -> 0 | N15: =H15-M15 -> 0 | V15: =U15+T15+S15+R15+Q15 -> 0 | X15: 0 | Y15: =V15-X15 -> 0 | Z15: M | AG15: =AF15+AE15+AD15+AC15+AB15+AA15 -> 0 | AJ15: =AG15-AI15 -> 0 | AQ15: =AP15+AO15+AN15+AM15+AL15 -> 0 | AS15: 0 | AT15: =AQ15-AS15 -> 0
B16: 004 | H16: =SUM(C16:G16) -> 0 | I16: 004 | M16: =SUM(J16:L16) -> 0 | N16: =H16-M16 -> 0 | V16: =U16+T16+S16+R16+Q16 -> 0 | X16: 0 | Y16: =V16-X16 -> 0 | AG16: =AF16+AE16+AD16+AC16+AB16+AA16 -> 0 | AJ16: =AG16-AI16 -> 0 | AQ16: =AP16+AO16+AN16+AM16+AL16 -> 0 | AS16: 0 | AT16: =AQ16-AS16 -> 0
B17: 26/001 | H17: =SUM(C17:G17) -> 0 | I17: 01 | M17: =SUM(J17:L17) -> 0 | N17: =H17-M17 -> 0 | V17: =U17+T17+S17+R17+Q17 -> 0 | X17: 0 | Y17: =V17-X17 -> 0 | Z17: 01 | AG17: =AF17+AE17+AD17+AC17+AB17+AA17 -> 0 | AJ17: =AG17-AI17 -> 0 | AK17: 01 | AQ17: =AP17+AO17+AN17+AM17+AL17 -> 0 | AS17: 0 | AT17: =AQ17-AS17 -> 0
B18: 26/002 | H18: =SUM(C18:G18) -> 0 | I18: 02 | M18: =SUM(J18:L18) -> 0 | N18: =H18-M18 -> 0 | V18: =U18+T18+S18+R18+Q18 -> 0 | X18: 0 | Y18: =V18-X18 -> 0 | Z18: 02 | AG18: =AF18+AE18+AD18+AC18+AB18+AA18 -> 0 | AJ18: =AG18-AI18 -> 0 | AK18: 02 | AQ18: =AP18+AO18+AN18+AM18+AL18 -> 0 | AS18: 0 | AT18: =AQ18-AS18 -> 0
B19: 26/003 | H19: =SUM(C19:G19) -> 0 | I19: 03 | M19: =SUM(J19:L19) -> 0 | N19: =H19-M19 -> 0 | V19: =U19+T19+S19+R19+Q19 -> 0 | X19: 0 | Y19: =V19-X19 -> 0 | Z19: 03 | AG19: =AF19+AE19+AD19+AC19+AB19+AA19 -> 0 | AJ19: =AG19-AI19 -> 0 | AK19: 03 | AQ19: =AP19+AO19+AN19+AM19+AL19 -> 0 | AS19: 0 | AT19: =AQ19-AS19 -> 0
B20: 26/004 | H20: =SUM(C20:G20) -> 0 | I20: 04 | M20: =SUM(J20:L20) -> 0 | N20: =H20-M20 -> 0 | V20: =U20+T20+S20+R20+Q20 -> 0 | X20: 0 | Y20: =V20-X20 -> 0 | Z20: 04 | AG20: =AF20+AE20+AD20+AC20+AB20+AA20 -> 0 | AJ20: =AG20-AI20 -> 0 | AK20: 04 | AQ20: =AP20+AO20+AN20+AM20+AL20 -> 0 | AS20: 0 | AT20: =AQ20-AS20 -> 0
B21: 26/005 | H21: =SUM(C21:G21) -> 0 | I21: 05 | M21: =SUM(J21:L21) -> 0 | N21: =H21-M21 -> 0 | V21: =U21+T21+S21+R21+Q21 -> 0 | X21: 0 | Y21: =V21-X21 -> 0 | Z21: 05 | AG21: =AF21+AE21+AD21+AC21+AB21+AA21 -> 0 | AJ21: =AG21-AI21 -> 0 | AK21: 05 | AQ21: =AP21+AO21+AN21+AM21+AL21 -> 0 | AS21: 0 | AT21: =AQ21-AS21 -> 0
B22: 26/006 | H22: =SUM(C22:G22) -> 0 | I22: 06 | M22: =SUM(J22:L22) -> 0 | N22: =H22-M22 -> 0 | V22: =U22+T22+S22+R22+Q22 -> 0 | X22: 0 | Y22: =V22-X22 -> 0 | Z22: 06 | AG22: =AF22+AE22+AD22+AC22+AB22+AA22 -> 0 | AJ22: =AG22-AI22 -> 0 | AK22: 06 | AQ22: =AP22+AO22+AN22+AM22+AL22 -> 0 | AS22: 0 | AT22: =AQ22-AS22 -> 0
B23: 26/007 | H23: =SUM(C23:G23) -> 0 | I23: 07 | M23: =SUM(J23:L23) -> 0 | N23: =H23-M23 -> 0 | V23: =U23+T23+S23+R23+Q23 -> 0 | X23: 0 | Y23: =V23-X23 -> 0 | Z23: 07 | AG23: =AF23+AE23+AD23+AC23+AB23+AA23 -> 0 | AJ23: =AG23-AI23 -> 0 | AK23: 07 | AQ23: =AP23+AO23+AN23+AM23+AL23 -> 0 | AS23: 0 | AT23: =AQ23-AS23 -> 0
B24: 26/008 | H24: =SUM(C24:G24) -> 0 | I24: 08 | M24: =SUM(J24:L24) -> 0 | N24: =H24-M24 -> 0 | V24: =U24+T24+S24+R24+Q24 -> 0 | X24: 0 | Y24: =V24-X24 -> 0 | Z24: 08 | AG24: =AF24+AE24+AD24+AC24+AB24+AA24 -> 0 | AJ24: =AG24-AI24 -> 0 | AK24: 08 | AQ24: =AP24+AO24+AN24+AM24+AL24 -> 0 | AS24: 0 | AT24: =AQ24-AS24 -> 0
B25: 26/009 | H25: =SUM(C25:G25) -> 0 | I25: 09 | M25: =SUM(J25:L25) -> 0 | N25: =H25-M25 -> 0 | V25: =U25+T25+S25+R25+Q25 -> 0 | X25: 0 | Y25: =V25-X25 -> 0 | Z25: 09 | AG25: =AF25+AE25+AD25+AC25+AB25+AA25 -> 0 | AJ25: =AG25-AI25 -> 0 | AK25: 09 | AQ25: =AP25+AO25+AN25+AM25+AL25 -> 0 | AS25: 0 | AT25: =AQ25-AS25 -> 0
B26: 26/010 | H26: =SUM(C26:G26) -> 0 | I26: 10 | M26: =SUM(J26:L26) -> 0 | N26: =H26-M26 -> 0 | V26: =U26+T26+S26+R26+Q26 -> 0 | X26: 0 | Y26: =V26-X26 -> 0 | Z26: 10 | AG26: =AF26+AE26+AD26+AC26+AB26+AA26 -> 0 | AJ26: =AG26-AI26 -> 0 | AK26: 10 | AQ26: =AP26+AO26+AN26+AM26+AL26 -> 0 | AS26: 0 | AT26: =AQ26-AS26 -> 0
B27: 26/011 | H27: =SUM(C27:G27) -> 0 | I27: 11 | M27: =SUM(J27:L27) -> 0 | N27: =H27-M27 -> 0 | V27: =U27+T27+S27+R27+Q27 -> 0 | X27: 0 | Y27: =V27-X27 -> 0 | Z27: 11 | AG27: =AF27+AE27+AD27+AC27+AB27+AA27 -> 0 | AJ27: =AG27-AI27 -> 0 | AK27: 11 | AQ27: =AP27+AO27+AN27+AM27+AL27 -> 0 | AS27: 0 | AT27: =AQ27-AS27 -> 0
B28: 26/012 | H28: =SUM(C28:G28) -> 0 | I28: 12 | M28: =SUM(J28:L28) -> 0 | N28: =H28-M28 -> 0 | V28: =U28+T28+S28+R28+Q28 -> 0 | X28: 0 | Y28: =V28-X28 -> 0 | Z28: 12 | AG28: =AF28+AE28+AD28+AC28+AB28+AA28 -> 0 | AJ28: =AG28-AI28 -> 0 | AK28: 12 | AQ28: =AP28+AO28+AN28+AM28+AL28 -> 0 | AS28: 0 | AT28: =AQ28-AS28 -> 0
... B35: 26/019 | H35: =SUM(C35:G35) -> 0 | I35: 19 | M35: =SUM(J35:L35) -> 0 | N35: =H35-M35 -> 0 | V35: =U35+T35+S35+R35+Q35 -> 0 | X35: 0 | Y35: =V35-X35 -> 0 | Z35: 19 | AG35: =AF35+AE35+AD35+AC35+AB35+AA35 -> 0 | AJ35: =AG35-AI35 -> 0 | AK35: 19 | AQ35: =AP35+AO35+AN35+AM35+AL35 -> 0 | AS35: 0 | AT35: =AQ35-AS35 -> 0
C37: =SUM(C13:C35) -> 0 | D37: =SUM(D13:D35) -> 0 | E37: =SUM(E13:E35) -> 0 | F37: =SUM(F13:F35) -> 0 | G37: =SUM(G13:G35) -> 0 | H37: =SUM(H13:H35) -> 0 | J37: =SUM(J13:J35) -> 0 | K37: =SUM(K13:K36) -> 0 | L37: =SUM(L14:L35) -> 0 | M37: =SUM(M13:M35) -> 0 | Q37: TOTAL ANULADAS | U37: =SUM(V13:V35) -> 0 | X37: =SUM(X13:X35) -> 0 | AA37: TOTAL PREMIADAS | AF37: =SUM(AG13:AG35) -> 0 | AI37: =SUM(AI13:AI35) -> 0 | AL37: TOTAL VENDIDAS | AP37: =SUM(AQ13:AQ35) -> 0 | AS37: =SUM(AS13:AS35) -> 0
B39: DEBEN / SALIDA | J39: PAGAN / ENTRADA
B41: MARTIN GASTOS | D41: 0 | E41: DEPOSITOS | H41: =D42+C73 -> 0 | J41: DEUDA DE CAJA s/l/v | L41: 0 | M41: EXCEDENTE | N41: 0
B42: PREMIOS | D42: =J37 -> 0 | E42: PREST. PALP. | H42: 0 | J42: FALTANTE DE CAJA | L42: 0 | M42: MARTIN | N42: 0
B43: LIBRERIA | D43: 0 | E43: PREST. TELEKINO | H43: 0 | J43: PREST. PALP./ REVISTA | L43: 0 | M43: PREMIOS | N43: 0
B44: LIMPIEZA | D44: 0 | E44: PREST. JGOS. MENORES | H44: 0 | J44: PREST. TELEKINO | L44: 0 | N44: 0
B45: SODA/AGUA | D45: 0 | E45: IMPUESTOS | H45: 0 | J45: PREST. JGOS. MENORES | L45: 0 | N45: 0
B46: GASTOS VARIOS | D46: 0 | E46: OTROS | H46: =SUM(N13:N35) -> 0 | L46: 0 | N46: 0
B48: SUB TOTAL | D48: =D41+D42+D43+D44+D45+D46+H42+H43+H44+H45+H46 -> 0 | G48: TOTAL | H48: =D48+H41 -> 0 | M48: SUB TOTAL | N48: =L41+L42+L43+L44+L45+L46+N41+N42+N43+N44+N45+N46 -> 0
C50: DETALLE RECAUDACION DE CAJA | H50: IMPORTE | J50: FECHA | L50: DETALLE CIERRE DE CAJA
C52: 20000 x | D52: 0 | E52: =20000*D52 -> 0 | I52: MAT | L52: 20000 x | M52: 0 | N52: =20000*M52 -> 0
C53: 10000 x | D53: 0 | E53: =10000*D53 -> 0 | I53: MAT | L53: 10000 x | M53: 0 | N53: =10000*M53 -> 0
C54: 2000 x | D54: 0 | E54: =2000*D54 -> 0 | I54: MAT | L54: 2000 x | M54: 0 | N54: =2000*M54 -> 0
C55: 1000 x | D55: 0 | E55: =1000*D55 -> 0 | I55: MAT | L55: 1000 x | M55: 0 | N55: =1000*M55 -> 0
C56: 500 x | D56: 0 | E56: =500*D56 -> 0 | I56: MAT | K56: =SUM(H52:H56) -> 0 | L56: 500 x | M56: 0 | N56: =500*M56 -> 0
C57: 200 x | D57: 0 | E57: =200*D57 -> 0 | I57: VEP | L57: 200 x | M57: 0 | N57: =200*M57 -> 0
C58: 100 x | D58: 0 | E58: =100*D58 -> 0 | I58: VEP | L58: 100 x | M58: 0 | N58: =100*M58 -> 0
C59: 50 x | D59: 0 | E59: =50*D59 -> 0 | I59: VEP | L59: 50 x | M59: 0 | N59: =50*M59 -> 0
C60: 20 x | D60: 0 | E60: =20*D60 -> 0 | I60: VEP | L60: 20 x | M60: 0 | N60: =20*M60 -> 0
C61: 10 x | D61: 0 | E61: =10*D61 -> 0 | I61: VEP | K61: =SUM(H57:H61) -> 0 | L61: 10 x | M61: 0 | N61: =10*M61 -> 0
C62: 5 x | D62: 0 | E62: =5*D62 -> 0 | I62: TAR | L62: 5 x | M62: 0 | N62: =5*M62 -> 0
C63: 2 x | D63: 0 | E63: =2*D63 -> 0 | I63: TAR | L63: 2 x | M63: 0 | N63: =2*M63 -> 0
C64: 1 x | D64: 0 | E64: =1*D64 -> 0 | I64: TAR | L64: 1 x | M64: 0 | N64: =1*M64 -> 0
C65: SUB - TOTAL | E65: =SUM(E52:F64) -> 0 | I65: TAR | L65: SUB - TOTAL | N65: =SUM(N52:N64) -> 0
I66: TAR | K66: =SUM(H62:H66) -> 0
D67: TOTAL | F67: =D48+E65 -> 0 | I67: NOC | L67: PREMOS | N67: 0
I68: NOC | L68: TELEKINOS | N68: 0
D69: DIFERENCIA | F69: =F67-H37 -> 0 | I69: NOC | L69: BOL. S/PREMIOS | N69: 0
I70: NOC | L70: OTROS | N70: 0
C71: DEPOSITO | I71: NOC | M71: SUB- TOTAL | N71: =SUM(N67:N70) -> 0
I72: NOC | K72: =SUM(H67:H72) -> 0
C73: 0
H74: =SUM(H52:H72) -> 0 | M74: TOTAL | N74: =N65+N71 -> 0
L76: ARQUEO DE CAJA AL CIERRE (COMPOSICION DEL SALDO)
C77: TOTAL DE INGRESO | H77: =H9+H37+N48 -> 4110333.4 | L77: PREMIOS | N77: =N71 -> 0
L78: EFECTIVO | N78: =N65 -> 0
C79: TOTAL DE EGRESO | H79: =H74+H41+D41+D43+D44+D45+D46+H42+H43+H44+H45+H46 -> 0 | L79: TOTAL DE CAJA AL CIERRE | N79: =N71+N65 -> 0
C81: SALDO DEL DIA | H81: =H77-H79 -> 4110333.4 | L81: DIFERENCIA DE CAJA | N81: =N79-H81 -> -4110333.4
L82: (+) POSITIVO | M82: (-) NEGATIVO

Sheet 0801
D3: PLANILLA DE RECAUDACION DIARIA DE APUESTA Y PREMIOS | M3: ='0101'!M2 -> 2025
D5: FECHA : | E5: 45170 | G5: RECAUDACION DEL DIA: | I5: 45169
C7: 26 | D7: SALDO DEL DIA ANTERIOR | G7: PREMIOS | H7: ='0701'!N77 -> 0
G8: EFECTIVO | H8: ='0701'!N78 -> 0
G9: TOTAL | H9: =H7+H8 -> 0 | Q9: TICKET ANULADOS | AA9: TICKET PREMIADOS | AL9: TICKET VENDIDOS
B11: SUB | C11: MATUTINA | D11: VESPERT. | E11: SIESTA | F11: TARDE | G11: NOCT. | H11: TOTAL | J11: PREMIOS | K11: EFECTIVO | L11: MONEDAS | M11: TOTAL | N11: DIFER. | Q11: M | R11: V | S11: S | T11: T | U11: N | V11: TOTAL | X11: PRES. | Y11: DIFER. | AA11: ANT | AB11: M | AC11: V | AD11: S | AE11: T | AF11: N | AG11: TOTAL | AI11: PRES | AJ11: DIFER. | AL11: M | AM11: V | AN11: S | AO11: T | AP11: N | AQ11: TOTAL | AS11: PRES. | AT11: DIFER.
H12: =SUM(H13:H16) -> 0
B13: 001 | H13: =SUM(C13:G13) -> 0 | I13: 001 | M13: =SUM(J13:L13) -> 0 | N13: =H13-M13 -> 0 | V13: =U13+T13+S13+R13+Q13 -> 0 | X13: 0 | Y13: =V13-X13 -> 0 | Z13: V | AG13: =AF13+AE13+AD13+AC13+AB13+AA13 -> 0 | AI13: 0 | AJ13: =AG13-AI13 -> 0 | AQ13: =AP13+AO13+AN13+AM13+AL13 -> 0 | AS13: 0 | AT13: =AQ13-AS13 -> 0
B14: 002 | H14: =SUM(C14:G14) -> 0 | I14: 002 | M14: =SUM(J14:L14) -> 0 | N14: =H14-M14 -> 0 | V14: =U14+T14+S14+R14+Q14 -> 0 | X14: 0 | Y14: =V14-X14 -> 0 | Z14: L | AG14: =AF14+AE14+AD14+AC14+AB14+AA14 -> 0 | AJ14: =AG14-AI14 -> 0 | AQ14: =AP14+AO14+AN14+AM14+AL14 -> 0 | AS14: 0 | AT14: =AQ14-AS14 -> 0
B15: 003 | H15: =SUM(C15:G15) -> 0 | I15: 003 | M15: =SUM(J15:L15) -> 0 | N15: =H15-M15 -> 0 | V15: =U15+T15+S15+R15+Q15 -> 0 | X15: 0 | Y15: =V15-X15 -> 0 | Z15: M | AG15: =AF15+AE15+AD15+AC15+AB15+AA15 -> 0 | AJ15: =AG15-AI15 -> 0 | AQ15: =AP15+AO15+AN15+AM15+AL15 -> 0 | AS15: 0 | AT15: =AQ15-AS15 -> 0
B16: 004 | H16: =SUM(C16:G16) -> 0 | I16: 004 | M16: =SUM(J16:L16) -> 0 | N16: =H16-M16 -> 0 | V16: =U16+T16+S16+R16+Q16 -> 0 | X16: 0 | Y16: =V16-X16 -> 0 | AG16: =AF16+AE16+AD16+AC16+AB16+AA16 -> 0 | AJ16: =AG16-AI16 -> 0 | AQ16: =AP16+AO16+AN16+AM16+AL16 -> 0 | AS16: 0 | AT16: =AQ16-AS16 -> 0
B17: 26/001 | H17: =SUM(C17:G17) -> 0 | I17: 01 | M17: =SUM(J17:L17) -> 0 | N17: =H17-M17 -> 0 | V17: =U17+T17+S17+R17+Q17 -> 0 | X17: 0 | Y17: =V17-X17 -> 0 | Z17: 01 | AG17: =AF17+AE17+AD17+AC17+AB17+AA17 -> 0 | AJ17: =AG17-AI17 -> 0 | AK17: 01 | AQ17: =AP17+AO17+AN17+AM17+AL17 -> 0 | AS17: 0 | AT17: =AQ17-AS17 -> 0
B18: 26/002 | H18: =SUM(C18:G18) -> 0 | I18: 02 | M18: =SUM(J18:L18) -> 0 | N18: =H18-M18 -> 0 | V18: =U18+T18+S18+R18+Q18 -> 0 | X18: 0 | Y18: =V18-X18 -> 0 | Z18: 02 | AG18: =AF18+AE18+AD18+AC18+AB18+AA18 -> 0 | AJ18: =AG18-AI18 -> 0 | AK18: 02 | AQ18: =AP18+AO18+AN18+AM18+AL18 -> 0 | AS18: 0 | AT18: =AQ18-AS18 -> 0
B19: 26/003 | H19: =SUM(C19:G19) -> 0 | I19: 03 | M19: =SUM(J19:L19) -> 0 | N19: =H19-M19 -> 0 | V19: =U19+T19+S19+R19+Q19 -> 0 | X19: 0 | Y19: =V19-X19 -> 0 | Z19: 03 | AG19: =AF19+AE19+AD19+AC19+AB19+AA19 -> 0 | AJ19: =AG19-AI19 -> 0 | AK19: 03 | AQ19: =AP19+AO19+AN19+AM19+AL19 -> 0 | AS19: 0 | AT19: =AQ19-AS19 -> 0
B20: 26/004 | H20: =SUM(C20:G20) -> 0 | I20: 04 | M20: =SUM(J20:L20) -> 0 | N20: =H20-M20 -> 0 | V20: =U20+T20+S20+R20+Q20 -> 0 | X20: 0 | Y20: =V20-X20 -> 0 | Z20: 04 | AG20: =AF20+AE20+AD20+AC20+AB20+AA20 -> 0 | AJ20: =AG20-AI20 -> 0 | AK20: 04 | AQ20: =AP20+AO20+AN20+AM20+AL20 -> 0 | AS20: 0 | AT20: =AQ20-AS20 -> 0
B21: 26/005 | H21: =SUM(C21:G21) -> 0 | I21: 05 | M21: =SUM(J21:L21) -> 0 | N21: =H21-M21 -> 0 | V21: =U21+T21+S21+R21+Q21 -> 0 | X21: 0 | Y21: =V21-X21 -> 0 | Z21: 05 | AG21: =AF21+AE21+AD21+AC21+AB21+AA21 -> 0 | AJ21: =AG21-AI21 -> 0 | AK21: 05 | AQ21: =AP21+AO21+AN21+AM21+AL21 -> 0 | AS21: 0 | AT21: =AQ21-AS21 -> 0
B22: 26/006 | H22: =SUM(C22:G22) -> 0 | I22: 06 | M22: =SUM(J22:L22) -> 0 | N22: =H22-M22 -> 0 | V22: =U22+T22+S22+R22+Q22 -> 0 | X22: 0 | Y22: =V22-X22 -> 0 | Z22: 06 | AG22: =AF22+AE22+AD22+AC22+AB22+AA22 -> 0 | AJ22: =AG22-AI22 -> 0 | AK22: 06 | AQ22: =AP22+AO22+AN22+AM22+AL22 -> 0 | AS22: 0 | AT22: =AQ22-AS22 -> 0
B23: 26/007 | H23: =SUM(C23:G23) -> 0 | I23: 07 | M23: =SUM(J23:L23) -> 0 | N23: =H23-M23 -> 0 | V23: =U23+T23+S23+R23+Q23 -> 0 | X23: 0 | Y23: =V23-X23 -> 0 | Z23: 07 | AG23: =AF23+AE23+AD23+AC23+AB23+AA23 -> 0 | AJ23: =AG23-AI23 -> 0 | AK23: 07 | AQ23: =AP23+AO23+AN23+AM23+AL23 -> 0 | AS23: 0 | AT23: =AQ23-AS23 -> 0
B24: 26/008 | H24: =SUM(C24:G24) -> 0 | I24: 08 | M24: =SUM(J24:L24) -> 0 | N24: =H24-M24 -> 0 | V24: =U24+T24+S24+R24+Q24 -> 0 | X24: 0 | Y24: =V24-X24 -> 0 | Z24: 08 | AG24: =AF24+AE24+AD24+AC24+AB24+AA24 -> 0 | AJ24: =AG24-AI24 -> 0 | AK24: 08 | AQ24: =AP24+AO24+AN24+AM24+AL24 -> 0 | AS24: 0 | AT24: =AQ24-AS24 -> 0
B25: 26/009 | H25: =SUM(C25:G25) -> 0 | I25: 09 | M25: =SUM(J25:L25) -> 0 | N25: =H25-M25 -> 0 | V25: =U25+T25+S25+R25+Q25 -> 0 | X25: 0 | Y25: =V25-X25 -> 0 | Z25: 09 | AG25: =AF25+AE25+AD25+AC25+AB25+AA25 -> 0 | AJ25: =AG25-AI25 -> 0 | AK25: 09 | AQ25: =AP25+AO25+AN25+AM25+AL25 -> 0 | AS25: 0 | AT25: =AQ25-AS25 -> 0
B26: 26/010 | H26: =SUM(C26:G26) -> 0 | I26: 10 | M26: =SUM(J26:L26) -> 0 | N26: =H26-M26 -> 0 | V26: =U26+T26+S26+R26+Q26 -> 0 | X26: 0 | Y26: =V26-X26 -> 0 | Z26: 10 | AG26: =AF26+AE26+AD26+AC26+AB26+AA26 -> 0 | AJ26: =AG26-AI26 -> 0 | AK26: 10 | AQ26: =AP26+AO26+AN26+AM26+AL26 -> 0 | AS26: 0 | AT26: =AQ26-AS26 -> 0
B27: 26/011 | H27: =SUM(C27:G27) -> 0 | I27: 11 | M27: =SUM(J27:L27) -> 0 | N27: =H27-M27 -> 0 | V27: =U27+T27+S27+R27+Q27 -> 0 | X27: 0 | Y27: =V27-X27 -> 0 | Z27: 11 | AG27: =AF27+AE27+AD27+AC27+AB27+AA27 -> 0 | AJ27: =AG27-AI27 -> 0 | AK27: 11 | AQ27: =AP27+AO27+AN27+AM27+AL27 -> 0 | AS27: 0 | AT27: =AQ27-AS27 -> 0
B28: 26/012 | H28: =SUM(C28:G28) -> 0 | I28: 12 | M28: =SUM(J28:L28) -> 0 | N28: =H28-M28 -> 0 | V28: =U28+T28+S28+R28+Q28 -> 0 | X28: 0 | Y28: =V28-X28 -> 0 | Z28: 12 | AG28: =AF28+AE28+AD28+AC28+AB28+AA28 -> 0 | AJ28: =AG28-AI28 -> 0 | AK28: 12 | AQ28: =AP28+AO28+AN28+AM28+AL28 -> 0 | AS28: 0 | AT28: =AQ28-AS28 -> 0
... B35: 26/019 | H35: =SUM(C35:G35) -> 0 | I35: 19 | M35: =SUM(J35:L35) -> 0 | N35: =H35-M35 -> 0 | V35: =U35+T35+S35+R35+Q35 -> 0 | X35: 0 | Y35: =V35-X35 -> 0 | Z35: 19 | AG35: =AF35+AE35+AD35+AC35+AB35+AA35 -> 0 | AJ35: =AG35-AI35 -> 0 | AK35: 19 | AQ35: =AP35+AO35+AN35+AM35+AL35 -> 0 | AS35: 0 | AT35: =AQ35-AS35 -> 0
C37: =SUM(C13:C35) -> 0 | D37: =SUM(D13:D35) -> 0 | E37: =SUM(E13:E35) -> 0 | F37: =SUM(F13:F35) -> 0 | G37: =SUM(G13:G35) -> 0 | H37: =SUM(H13:H35) -> 0 | J37: =SUM(J13:J35) -> 0 | K37: =SUM(K13:K36) -> 0 | L37: =SUM(L14:L35) -> 0 | M37: =SUM(M13:M35) -> 0 | Q37: TOTAL ANULADAS | U37: =SUM(V13:V35) -> 0 | X37: =SUM(X13:X35) -> 0 | AA37: TOTAL PREMIADAS | AF37: =SUM(AG13:AG35) -> 0 | AI37: =SUM(AI13:AI35) -> 0 | AL37: TOTAL VENDIDAS | AP37: =SUM(AQ13:AQ35) -> 0 | AS37: =SUM(AS13:AS35) -> 0
B39: DEBEN / SALIDA | J39: PAGAN / ENTRADA
B41: MARTIN GASTOS | D41: 0 | E41: DEPOSITOS | H41: =D42+C73 -> 0 | J41: DEUDA DE CAJA s/l/v | L41: 0 | M41: EXCEDENTE | N41: 0
B42: PREMIOS | D42: =J37 -> 0 | E42: PREST. PALP. | H42: 0 | J42: FALTANTE DE CAJA | L42: 0 | M42: MARTIN | N42: 0
B43: LIBRERIA | D43: 0 | E43: PREST. TELEKINO | H43: 0 | J43: PREST. PALP./ REVISTA | L43: 0 | M43: PREMIOS | N43: 0
B44: LIMPIEZA | D44: 0 | E44: PREST. JGOS. MENORES | H44: 0 | J44: PREST. TELEKINO | L44: 0 | N44: 0
B45: SODA/AGUA | D45: 0 | E45: IMPUESTOS | H45: 0 | J45: PREST. JGOS. MENORES | L45: 0 | N45: 0
B46: GASTOS VARIOS | D46: 0 | E46: OTROS | H46: =SUM(N13:N35) -> 0 | L46: 0 | N46: 0
B48: SUB TOTAL | D48: =D41+D42+D43+D44+D45+D46+H42+H43+H44+H45+H46 -> 0 | G48: TOTAL | H48: =D48+H41 -> 0 | M48: SUB TOTAL | N48: =L41+L42+L43+L44+L45+L46+N41+N42+N43+N44+N45+N46 -> 0
C50: DETALLE RECAUDACION DE CAJA | H50: IMPORTE | J50: FECHA | L50: DETALLE CIERRE DE CAJA
C52: 20000 x | D52: 0 | E52: =20000*D52 -> 0 | I52: MAT | L52: 20000 x | M52: 0 | N52: =20000*M52 -> 0
C53: 10000 x | D53: 0 | E53: =10000*D53 -> 0 | I53: MAT | L53: 10000 x | M53: 0 | N53: =10000*M53 -> 0
C54: 2000 x | D54: 0 | E54: =2000*D54 -> 0 | I54: MAT | L54: 2000 x | M54: 0 | N54: =2000*M54 -> 0
C55: 1000 x | D55: 0 | E55: =1000*D55 -> 0 | I55: MAT | L55: 1000 x | M55: 0 | N55: =1000*M55 -> 0
C56: 500 x | D56: 0 | E56: =500*D56 -> 0 | I56: MAT | K56: =SUM(H52:H56) -> 0 | L56: 500 x | M56: 0 | N56: =500*M56 -> 0
C57: 200 x | D57: 0 | E57: =200*D57 -> 0 | I57: VEP | L57: 200 x | M57: 0 | N57: =200*M57 -> 0
C58: 100 x | D58: 0 | E58: =100*D58 -> 0 | I58: VEP | L58: 100 x | M58: 0 | N58: =100*M58 -> 0
C59: 50 x | D59: 0 | E59: =50*D59 -> 0 | I59: VEP | L59: 50 x | M59: 0 | N59: =50*M59 -> 0
C60: 20 x | D60: 0 | E60: =20*D60 -> 0 | I60: VEP | L60: 20 x | M60: 0 | N60: =20*M60 -> 0
C61: 10 x | D61: 0 | E61: =10*D61 -> 0 | I61: VEP | K61: =SUM(H57:H61) -> 0 | L61: 10 x | M61: 0 | N61: =10*M61 -> 0
C62: 5 x | D62: 0 | E62: =5*D62 -> 0 | I62: TAR | L62: 5 x | M62: 0 | N62: =5*M62 -> 0
C63: 2 x | D63: 0 | E63: =2*D63 -> 0 | I63: TAR | L63: 2 x | M63: 0 | N63: =2*M63 -> 0
C64: 1 x | D64: 0 | E64: =1*D64 -> 0 | I64: TAR | L64: 1 x | M64: 0 | N64: =1*M64 -> 0
C65: SUB - TOTAL | E65: =SUM(E52:F64) -> 0 | I65: TAR | L65: SUB - TOTAL | N65: =SUM(N52:N64) -> 0
I66: TAR | K66: =SUM(H62:H66) -> 0
D67: TOTAL | F67: =D48+E65 -> 0 | I67: NOC | L67: PREMOS | N67: 0
I68: NOC | L68: TELEKINOS | N68: 0
D69: DIFERENCIA | F69: =F67-H37 -> 0 | I69: NOC | L69: BOL. S/PREMIOS | N69: 0
I70: NOC | L70: OTROS | N70: 0
C71: DEPOSITO | I71: NOC | M71: SUB- TOTAL | N71: =SUM(N67:N70) -> 0
I72: NOC | K72: =SUM(H67:H72) -> 0
C73: 0
H74: =SUM(H52:H72) -> 0 | M74: TOTAL | N74: =N65+N71 -> 0
L76: ARQUEO DE CAJA AL CIERRE (COMPOSICION DEL SALDO)
C77: TOTAL DE INGRESO | H77: =H9+H37+N48 -> 0 | L77: PREMIOS | N77: =N71 -> 0
L78: EFECTIVO | N78: =N65 -> 0
C79: TOTAL DE EGRESO | H79: =H74+H41+D41+D43+D44+D45+D46+H42+H43+H44+H45+H46 -> 0 | L79: TOTAL DE CAJA AL CIERRE | N79: =N71+N65 -> 0
C81: SALDO DEL DIA | H81: =H77-H79 -> 0 | L81: DIFERENCIA DE CAJA | N81: =N79-H81 -> 0
L82: (+) POSITIVO | M82: (-) NEGATIVO

Sheet 0901
D3: PLANILLA DE RECAUDACION DIARIA DE APUESTA Y PREMIOS | M3: ='0101'!M2 -> 2025
D5: FECHA : | E5: 45170 | G5: RECAUDACION DEL DIA: | I5: 45169
C7: 26 | D7: SALDO DEL DIA ANTERIOR | G7: PREMIOS | H7: ='0601'!N77 -> 3115613.4
G8: EFECTIVO | H8: ='0601'!N78 -> 994720
G9: TOTAL | H9: =H7+H8 -> 4110333.4 | Q9: TICKET ANULADOS | AA9: TICKET PREMIADOS | AL9: TICKET VENDIDOS
B11: SUB | C11: MATUTINA | D11: VESPERT. | E11: SIESTA | F11: TARDE | G11: NOCT. | H11: TOTAL | J11: PREMIOS | K11: EFECTIVO | L11: MONEDAS | M11: TOTAL | N11: DIFER. | Q11: M | R11: V | S11: S | T11: T | U11: N | V11: TOTAL | X11: PRES. | Y11: DIFER. | AA11: ANT | AB11: M | AC11: V | AD11: S | AE11: T | AF11: N | AG11: TOTAL | AI11: PRES | AJ11: DIFER. | AL11: M | AM11: V | AN11: S | AO11: T | AP11: N | AQ11: TOTAL | AS11: PRES. | AT11: DIFER.
H12: =SUM(H13:H16) -> 1167600
B13: 001 | C13: 259200 | D13: 77100 | E13: 5500 | F13: 53600 | G13: 81400 | H13: =SUM(C13:G13) -> 476800 | I13: 001 | J13: 280000 | K13: 196600 | M13: =SUM(J13:L13) -> 476600 | N13: =H13-M13 -> 200 | S13: 3 | V13: =U13+T13+S13+R13+Q13 -> 3 | Y13: =V13-X13 -> 3 | Z13: V | AA13: 3 | AG13: =AF13+AE13+AD13+AC13+AB13+AA13 -> 3 | AI13: 0 | AJ13: =AG13-AI13 -> 3 | AL13: 127 | AM13: 51 | AN13: 3 | AO13: 31 | AP13: 46 | AQ13: =AP13+AO13+AN13+AM13+AL13 -> 258 | AS13: 5 | AT13: =AQ13-AS13 -> 253
B14: 002 | H14: =SUM(C14:G14) -> 0 | I14: 002 | M14: =SUM(J14:L14) -> 0 | N14: =H14-M14 -> 0 | V14: =U14+T14+S14+R14+Q14 -> 0 | X14: 0 | Y14: =V14-X14 -> 0 | Z14: L | AG14: =AF14+AE14+AD14+AC14+AB14+AA14 -> 0 | AJ14: =AG14-AI14 -> 0 | AQ14: =AP14+AO14+AN14+AM14+AL14 -> 0 | AS14: 0 | AT14: =AQ14-AS14 -> 0
B15: 003 | C15: 291500 | D15: 129250 | E15: 70050 | F15: 76800 | G15: 123200 | H15: =SUM(C15:G15) -> 690800 | I15: 003 | J15: 235774.81 | K15: 455100 | L15: -74.81 | M15: =SUM(J15:L15) -> 690800 | N15: =H15-M15 -> 0 | V15: =U15+T15+S15+R15+Q15 -> 0 | X15: 0 | Y15: =V15-X15 -> 0 | Z15: M | AA15: 5 | AC15: 1 | AD15: 2 | AG15: =AF15+AE15+AD15+AC15+AB15+AA15 -> 8 | AJ15: =AG15-AI15 -> 8 | AL15: 127 | AM15: 68 | AN15: 32 | AO15: 46 | AP15: 71 | AQ15: =AP15+AO15+AN15+AM15+AL15 -> 344 | AS15: 0 | AT15: =AQ15-AS15 -> 344
B16: 004 | H16: =SUM(C16:G16) -> 0 | I16: 004 | M16: =SUM(J16:L16) -> 0 | N16: =H16-M16 -> 0 | V16: =U16+T16+S16+R16+Q16 -> 0 | X16: 0 | Y16: =V16-X16 -> 0 | AG16: =AF16+AE16+AD16+AC16+AB16+AA16 -> 0 | AJ16: =AG16-AI16 -> 0 | AQ16: =AP16+AO16+AN16+AM16+AL16 -> 0 | AS16: 0 | AT16: =AQ16-AS16 -> 0
B17: 26/001 | C17: 141850 | D17: 113250 | E17: 5650 | F17: 14500 | G17: 118600 | H17: =SUM(C17:G17) -> 393850 | I17: 01 | J17: 166600 | K17: 227300 | L17: -50 | M17: =SUM(J17:L17) -> 393850 | N17: =H17-M17 -> 0 | Q17: 1 | R17: 1 | S17: 1 | V17: =U17+T17+S17+R17+Q17 -> 3 | X17: 0 | Y17: =V17-X17 -> 3 | Z17: 01 | AB17: 4 | AC17: 4 | AG17: =AF17+AE17+AD17+AC17+AB17+AA17 -> 8 | AJ17: =AG17-AI17 -> 8 | AK17: 01 | AL17: 86 | AM17: 67 | AN17: 11 | AO17: 16 | AP17: 80 | AQ17: =AP17+AO17+AN17+AM17+AL17 -> 260 | AS17: 0 | AT17: =AQ17-AS17 -> 260
B18: 26/002 | C18: 378120 | D18: 289300 | E18: 132950 | F18: 102350 | G18: 218650 | H18: =SUM(C18:G18) -> 1121370 | I18: 02 | J18: 194250 | K18: 927150 | L18: -30 | M18: =SUM(J18:L18) -> 1121370 | N18: =H18-M18 -> 0 | Q18: 1 | V18: =U18+T18+S18+R18+Q18 -> 1 | X18: 0 | Y18: =V18-X18 -> 1 | Z18: 02 | AA18: 4 | AB18: 3 | AC18: 1 | AD18: 3 | AG18: =AF18+AE18+AD18+AC18+AB18+AA18 -> 11 | AJ18: =AG18-AI18 -> 11 | AK18: 02 | AL18: 238 | AM18: 176 | AN18: 119 | AO18: 105 | AP18: 163 | AQ18: =AP18+AO18+AN18+AM18+AL18 -> 801 | AS18: 0 | AT18: =AQ18-AS18 -> 801
B19: 26/003 | C19: 157200 | D19: 141000 | E19: 90000 | F19: 119100 | G19: 155400 | H19: =SUM(C19:G19) -> 662700 | I19: 03 | J19: 126000 | K19: 536700 | M19: =SUM(J19:L19) -> 662700 | N19: =H19-M19 -> 0 | V19: =U19+T19+S19+R19+Q19 -> 0 | X19: 0 | Y19: =V19-X19 -> 0 | Z19: 03 | AB19: 3 | AC19: 2 | AD19: 4 | AE19: 3 | AG19: =AF19+AE19+AD19+AC19+AB19+AA19 -> 12 | AJ19: =AG19-AI19 -> 12 | AK19: 03 | AL19: 97 | AM19: 80 | AN19: 49 | AO19: 64 | AP19: 86 | AQ19: =AP19+AO19+AN19+AM19+AL19 -> 376 | AS19: 0 | AT19: =AQ19-AS19 -> 376
B20: 26/004 | C20: 104950 | D20: 136150 | E20: 51800 | F20: 89800 | G20: 117000 | H20: =SUM(C20:G20) -> 499700 | I20: 04 | J20: 165900 | K20: 329800 | M20: =SUM(J20:L20) -> 495700 | N20: =H20-M20 -> 4000 | Q20: 1 | V20: =U20+T20+S20+R20+Q20 -> 1 | X20: 0 | Y20: =V20-X20 -> 1 | Z20: 04 | AA20: 2 | AB20: 1 | AC20: 1 | AD20: 3 | AE20: 1 | AG20: =AF20+AE20+AD20+AC20+AB20+AA20 -> 8 | AJ20: =AG20-AI20 -> 8 | AK20: 04 | AL20: 63 | AM20: 99 | AN20: 37 | AO20: 51 | AP20: 87 | AQ20: =AP20+AO20+AN20+AM20+AL20 -> 337 | AS20: 0 | AT20: =AQ20-AS20 -> 337
B21: 26/005 | C21: 75700 | D21: 101800 | E21: 66000 | F21: 54700 | G21: 92000 | H21: =SUM(C21:G21) -> 390200 | I21: 05 | J21: 560000 | L21: -169800 | M21: =SUM(J21:L21) -> 390200 | N21: =H21-M21 -> 0 | Q21: 2 | R21: 3 | U21: 1 | V21: =U21+T21+S21+R21+Q21 -> 6 | X21: 0 | Y21: =V21-X21 -> 6 | Z21: 05 | AA21: 3 | AC21: 1 | AD21: 2 | AG21: =AF21+AE21+AD21+AC21+AB21+AA21 -> 6 | AJ21: =AG21-AI21 -> 6 | AK21: 05 | AL21: 41 | AM21: 50 | AN21: 28 | AO21: 28 | AP21: 49 | AQ21: =AP21+AO21+AN21+AM21+AL21 -> 196 | AS21: 0 | AT21: =AQ21-AS21 -> 196
B22: 26/006 | C22: 204350 | D22: 188200 | E22: 58900 | F22: 68300 | G22: 185700 | H22: =SUM(C22:G22) -> 705450 | I22: 06 | J22: 253750 | K22: 451700 | M22: =SUM(J22:L22) -> 705450 | N22: =H22-M22 -> 0 | R22: 1 | S22: 1 | T22: 1 | V22: =U22+T22+S22+R22+Q22 -> 3 | X22: 0 | Y22: =V22-X22 -> 3 | Z22: 06 | AA22: 3 | AB22: 2 | AC22: 4 | AD22: 1 | AG22: =AF22+AE22+AD22+AC22+AB22+AA22 -> 10 | AJ22: =AG22-AI22 -> 10 | AK22: 06 | AL22: 112 | AM22: 110 | AN22: 47 | AO22: 38 | AP22: 115 | AQ22: =AP22+AO22+AN22+AM22+AL22 -> 422 | AS22: 0 | AT22: =AQ22-AS22 -> 422
B23: 26/007 | C23: 207950 | D23: 213050 | E23: 46000 | F23: 106900 | G23: 165150 | H23: =SUM(C23:G23) -> 739050 | I23: 07 | J23: 393400 | K23: 345700 | L23: -50 | M23: =SUM(J23:L23) -> 739050 | N23: =H23-M23 -> 0 | V23: =U23+T23+S23+R23+Q23 -> 0 | X23: 0 | Y23: =V23-X23 -> 0 | Z23: 07 | AA23: 4 | AB23: 1 | AC23: 3 | AD23: 1 | AE23: 3 | AG23: =AF23+AE23+AD23+AC23+AB23+AA23 -> 12 | AJ23: =AG23-AI23 -> 12 | AK23: 07 | AL23: 130 | AM23: 138 | AN23: 34 | AO23: 67 | AP23: 101 | AQ23: =AP23+AO23+AN23+AM23+AL23 -> 470 | AS23: 0 | AT23: =AQ23-AS23 -> 470
B24: 26/008 | C24: 59500 | D24: 44000 | E24: 2400 | F24: 43600 | G24: 24400 | H24: =SUM(C24:G24) -> 173900 | I24: 08 | J24: 22400 | K24: 151500 | M24: =SUM(J24:L24) -> 173900 | N24: =H24-M24 -> 0 | Q24: 1 | V24: =U24+T24+S24+R24+Q24 -> 1 | X24: 0 | Y24: =V24-X24 -> 1 | Z24: 08 | AA24: 1 | AC24: 1 | AG24: =AF24+AE24+AD24+AC24+AB24+AA24 -> 2 | AJ24: =AG24-AI24 -> 2 | AK24: 08 | AL24: 28 | AM24: 35 | AN24: 5 | AO24: 32 | AP24: 21 | AQ24: =AP24+AO24+AN24+AM24+AL24 -> 121 | AS24: 0 | AT24: =AQ24-AS24 -> 121
B25: 26/009 | C25: 158600 | D25: 142800 | E25: 25100 | F25: 36900 | G25: 92100 | H25: =SUM(C25:G25) -> 455500 | I25: 09 | J25: 44800 | K25: 410700 | M25: =SUM(J25:L25) -> 455500 | N25: =H25-M25 -> 0 | Q25: 2 | U25: 1 | V25: =U25+T25+S25+R25+Q25 -> 3 | X25: 0 | Y25: =V25-X25 -> 3 | Z25: 09 | AA25: 2 | AD25: 1 | AG25: =AF25+AE25+AD25+AC25+AB25+AA25 -> 3 | AJ25: =AG25-AI25 -> 3 | AK25: 09 | AL25: 77 | AM25: 78 | AN25: 22 | AO25: 24 | AP25: 70 | AQ25: =AP25+AO25+AN25+AM25+AL25 -> 271 | AS25: 0 | AT25: =AQ25-AS25 -> 271
B26: 26/010 | H26: =SUM(C26:G26) -> 0 | I26: 10 | M26: =SUM(J26:L26) -> 0 | N26: =H26-M26 -> 0 | V26: =U26+T26+S26+R26+Q26 -> 0 | X26: 0 | Y26: =V26-X26 -> 0 | Z26: 10 | AG26: =AF26+AE26+AD26+AC26+AB26+AA26 -> 0 | AJ26: =AG26-AI26 -> 0 | AK26: 10 | AQ26: =AP26+AO26+AN26+AM26+AL26 -> 0 | AS26: 0 | AT26: =AQ26-AS26 -> 0
B27: 26/011 | C27: 107600 | D27: 76300 | E27: 38200 | F27: 56200 | G27: 70900 | H27: =SUM(C27:G27) -> 349200 | I27: 11 | J27: 194000 | K27: 155200 | M27: =SUM(J27:L27) -> 349200 | N27: =H27-M27 -> 0 | Q27: 1 | T27: 1 | V27: =U27+T27+S27+R27+Q27 -> 2 | X27: 0 | Y27: =V27-X27 -> 2 | Z27: 11 | AA27: 2 | AC27: 1 | AD27: 3 | AG27: =AF27+AE27+AD27+AC27+AB27+AA27 -> 6 | AJ27: =AG27-AI27 -> 6 | AK27: 11 | AL27: 56 | AM27: 55 | AN27: 24 | AO27: 40 | AP27: 48 | AQ27: =AP27+AO27+AN27+AM27+AL27 -> 223 | AS27: 0 | AT27: =AQ27-AS27 -> 223
B28: 26/012 | C28: 102700 | D28: 180200 | E28: 112400 | F28: 82400 | G28: 150450 | H28: =SUM(C28:G28) -> 628150 | I28: 12 | J28: 788500 | L28: -160350 | M28: =SUM(J28:L28) -> 628150 | N28: =H28-M28 -> 0 | Q28: 1 | R28: 1 | S28: 2 | U28: 1 | V28: =U28+T28+S28+R28+Q28 -> 5 | X28: 0 | Y28: =V28-X28 -> 5 | Z28: 12 | AA28: 3 | AB28: 3 | AC28: 1 | AD28: 4 | AG28: =AF28+AE28+AD28+AC28+AB28+AA28 -> 11 | AJ28: =AG28-AI28 -> 11 | AK28: 12 | AL28: 72 | AM28: 113 | AN28: 62 | AO28: 56 | AP28: 111 | AQ28: =AP28+AO28+AN28+AM28+AL28 -> 414 | AS28: 0 | AT28: =AQ28-AS28 -> 414
B29: 26/013 | C29: 160900 | D29: 202500 | E29: 190250 | F29: 97350 | G29: 262700 | H29: =SUM(C29:G29) -> 913700 | I29: 13 | J29: 1012200 | L29: -98500 | M29: =SUM(J29:L29) -> 913700 | N29: =H29-M29 -> 0 | Q29: 2 | R29: 2 | S29: 1 | V29: =U29+T29+S29+R29+Q29 -> 5 | X29: 0 | Y29: =V29-X29 -> 5 | Z29: 13 | AA29: 1 | AB29: 1 | AC29: 4 | AD29: 7 | AE29: 1 | AG29: =AF29+AE29+AD29+AC29+AB29+AA29 -> 14 | AJ29: =AG29-AI29 -> 14 | AK29: 13 | AL29: 70 | AM29: 87 | AN29: 78 | AO29: 45 | AP29: 114 | AQ29: =AP29+AO29+AN29+AM29+AL29 -> 394 | AS29: 0 | AT29: =AQ29-AS29 -> 394
B30: 26/014 | C30: 99500 | D30: 71700 | E30: 23800 | F30: 35000 | G30: 52200 | H30: =SUM(C30:G30) -> 282200 | I30: 14 | J30: 35000 | K30: 244300 | L30: 2900 | M30: =SUM(J30:L30) -> 282200 | N30: =H30-M30 -> 0 | V30: =U30+T30+S30+R30+Q30 -> 0 | X30: 0 | Y30: =V30-X30 -> 0 | Z30: 14 | AA30: 1 | AC30: 1 | AG30: =AF30+AE30+AD30+AC30+AB30+AA30 -> 2 | AJ30: =AG30-AI30 -> 2 | AK30: 14 | AL30: 84 | AM30: 45 | AN30: 27 | AO30: 24 | AP30: 41 | AQ30: =AP30+AO30+AN30+AM30+AL30 -> 221 | AS30: 0 | AT30: =AQ30-AS30 -> 221
B31: 26/015 | H31: =SUM(C31:G31) -> 0 | I31: 15 | M31: =SUM(J31:L31) -> 0 | N31: =H31-M31 -> 0 | V31: =U31+T31+S31+R31+Q31 -> 0 | X31: 0 | Y31: =V31-X31 -> 0 | Z31: 15 | AG31: =AF31+AE31+AD31+AC31+AB31+AA31 -> 0 | AJ31: =AG31-AI31 -> 0 | AK31: 15 | AQ31: =AP31+AO31+AN31+AM31+AL31 -> 0 | AS31: 0 | AT31: =AQ31-AS31 -> 0
B32: 26/016 | C32: 152600 | D32: 200200 | E32: 117100 | F32: 93600 | G32: 149300 | H32: =SUM(C32:G32) -> 712800 | I32: 16 | J32: 331800 | K32: 381000 | M32: =SUM(J32:L32) -> 712800 | N32: =H32-M32 -> 0 | S32: 1 | V32: =U32+T32+S32+R32+Q32 -> 1 | X32: 0 | Y32: =V32-X32 -> 1 | Z32: 16 | AA32: 2 | AB32: 2 | AC32: 1 | AD32: 4 | AG32: =AF32+AE32+AD32+AC32+AB32+AA32 -> 9 | AJ32: =AG32-AI32 -> 9 | AK32: 16 | AL32: 98 | AM32: 113 | AN32: 83 | AO32: 66 | AP32: 95 | AQ32: =AP32+AO32+AN32+AM32+AL32 -> 455 | AS32: 0 | AT32: =AQ32-AS32 -> 455
B33: 26/017 | C33: 33100 | D33: 39800 | E33: 13200 | F33: 21000 | G33: 29800 | H33: =SUM(C33:G33) -> 136900 | I33: 17 | J33: 104066.66 | K33: 42700 | L33: -9866.66 | M33: =SUM(J33:L33) -> 136900 | N33: =H33-M33 -> 0 | Q33: 1 | R33: 1 | V33: =U33+T33+S33+R33+Q33 -> 2 | X33: 0 | Y33: =V33-X33 -> 2 | Z33: 17 | AA33: 2 | AB33: 3 | AC33: 1 | AD33: 1 | AG33: =AF33+AE33+AD33+AC33+AB33+AA33 -> 7 | AJ33: =AG33-AI33 -> 7 | AK33: 17 | AL33: 39 | AM33: 47 | AN33: 16 | AO33: 25 | AP33: 32 | AQ33: =AP33+AO33+AN33+AM33+AL33 -> 159 | AS33: 0 | AT33: =AQ33-AS33 -> 159
B34: 26/018 | H34: =SUM(C34:G34) -> 0 | I34: 18 | M34: =SUM(J34:L34) -> 0 | N34: =H34-M34 -> 0 | V34: =U34+T34+S34+R34+Q34 -> 0 | X34: 0 | Y34: =V34-X34 -> 0 | Z34: 18 | AG34: =AF34+AE34+AD34+AC34+AB34+AA34 -> 0 | AJ34: =AG34-AI34 -> 0 | AK34: 18 | AQ34: =AP34+AO34+AN34+AM34+AL34 -> 0 | AS34: 0 | AT34: =AQ34-AS34 -> 0
B35: 26/019 | H35: =SUM(C35:G35) -> 0 | I35: 19 | M35: =SUM(J35:L35) -> 0 | N35: =H35-M35 -> 0 | V35: =U35+T35+S35+R35+Q35 -> 0 | X35: 0 | Y35: =V35-X35 -> 0 | Z35: 19 | AG35: =AF35+AE35+AD35+AC35+AB35+AA35 -> 0 | AJ35: =AG35-AI35 -> 0 | AK35: 19 | AQ35: =AP35+AO35+AN35+AM35+AL35 -> 0 | AS35: 0 | AT35: =AQ35-AS35 -> 0
C37: =SUM(C13:C35) -> 2695320 | D37: =SUM(D13:D35) -> 2346600 | E37: =SUM(E13:E35) -> 1049300 | F37: =SUM(F13:F35) -> 1152100 | G37: =SUM(G13:G35) -> 2088950 | H37: =SUM(H13:H35) -> 9332270 | J37: =SUM(J13:J35) -> 4908441.5 | K37: =SUM(K13:K36) -> 4855450 | L37: =SUM(L14:L35) -> -435821.47 | M37: =SUM(M13:M35) -> 9328070 | Q37: TOTAL ANULADAS | U37: =SUM(V13:V35) -> 36 | X37: =SUM(X13:X35) -> 0 | AA37: TOTAL PREMIADAS | AF37: =SUM(AG13:AG35) -> 132 | AI37: =SUM(AI13:AI35) -> 0 | AL37: TOTAL VENDIDAS | AP37: =SUM(AQ13:AQ35) -> 5722 | AS37: =SUM(AS13:AS35) -> 5
B39: DEBEN / SALIDA | J39: PAGAN / ENTRADA
B41: MARTIN GASTOS | D41: 0 | E41: DEPOSITOS | H41: =D42+C73 -> 0 | J41: DEUDA DE CAJA s/l/v | L41: 0 | M41: EXCEDENTE | N41: 0
B42: PREMIOS | D42: =J37 -> 4908441.5 | E42: PREST. PALP. | H42: 4000000 | J42: FALTANTE DE CAJA | L42: 0 | M42: MARTIN | N42: 0
B43: LIBRERIA | D43: 0 | E43: PREST. TELEKINO | H43: 0 | J43: PREST. PALP./ REVISTA | L43: 0 | M43: PREMIOS | N43: 0
B44: LIMPIEZA | D44: 0 | E44: PREST. JGOS. MENORES | H44: 0 | J44: PREST. TELEKINO | L44: 0 | N44: 0
B45: SODA/AGUA | D45: 0 | E45: IMPUESTOS | H45: 0 | J45: PREST. JGOS. MENORES | L45: 0 | N45: 0
B46: GASTOS VARIOS | D46: 0 | E46: OTROS | H46: =SUM(N13:N35) -> 4200 | L46: 0 | N46: 0
B48: SUB TOTAL | D48: =D41+D42+D43+D44+D45+D46+H42+H43+H44+H45+H46 -> 8912641.5 | G48: TOTAL | H48: =D48+H41 -> 8912641.5 | M48: SUB TOTAL | N48: =L41+L42+L43+L44+L45+L46+N41+N42+N43+N44+N45+N46 -> 0
C50: DETALLE RECAUDACION DE CAJA | H50: IMPORTE | J50: FECHA | L50: DETALLE CIERRE DE CAJA
C52: 20000 x | D52: 72 | E52: =20000*D52 -> 1440000 | I52: MAT | L52: 20000 x | M52: 72 | N52: =20000*M52 -> 1440000
C53: 10000 x | D53: 168 | E53: =10000*D53 -> 1680000 | I53: MAT | L53: 10000 x | M53: 281 | N53: =10000*M53 -> 2810000
C54: 2000 x | D54: 243 | E54: =2000*D54 -> 486000 | I54: MAT | L54: 2000 x | M54: 446 | N54: =2000*M54 -> 892000
C55: 1000 x | D55: 1144 | E55: =1000*D55 -> 1144000 | I55: MAT | L55: 1000 x | M55: 944 | N55: =1000*M55 -> 944000
C56: 500 x | D56: 178 | E56: =500*D56 -> 89000 | I56: MAT | K56: =SUM(H52:H56) -> 0 | L56: 500 x | M56: 110 | N56: =500*M56 -> 55000
C57: 200 x | D57: 50 | E57: =200*D57 -> 10000 | I57: VEP | L57: 200 x | M57: 247 | N57: =200*M57 -> 49400
C58: 100 x | D58: 94 | E58: =100*D58 -> 9400 | I58: VEP | L58: 100 x | M58: 88 | N58: =100*M58 -> 8800
C59: 50 x | D59: 2 | E59: =50*D59 -> 100 | I59: VEP | L59: 50 x | M59: 1796 | N59: =50*M59 -> 89800
C60: 20 x | D60: 0 | E60: =20*D60 -> 0 | I60: VEP | L60: 20 x | M60: 1510 | N60: =20*M60 -> 30200
C61: 10 x | D61: 0 | E61: =10*D61 -> 0 | I61: VEP | K61: =SUM(H57:H61) -> 0 | L61: 10 x | M61: 360 | N61: =10*M61 -> 3600
C62: 5 x | D62: 0 | E62: =5*D62 -> 0 | I62: TAR | L62: 5 x | M62: 0 | N62: =5*M62 -> 0
C63: 2 x | D63: 0 | E63: =2*D63 -> 0 | I63: TAR | L63: 2 x | M63: 0 | N63: =2*M63 -> 0
C64: 1 x | D64: 0 | E64: =1*D64 -> 0 | I64: TAR | L64: 1 x | M64: 0 | N64: =1*M64 -> 0
C65: SUB - TOTAL | E65: =SUM(E52:F64) -> 4858500 | I65: TAR | L65: SUB - TOTAL | N65: =SUM(N52:N64) -> 6322800
I66: TAR | K66: =SUM(H62:H66) -> 0
D67: TOTAL | F67: =D48+E65 -> 13771141 | I67: NOC | L67: PREMOS | N67: 0
I68: NOC | L68: TELEKINOS | N68: 0
D69: DIFERENCIA | F69: =F67-H37 -> 4438871.5 | I69: NOC | L69: BOL. S/PREMIOS | N69: 3115613.4
I70: NOC | L70: OTROS | N70: 0
C71: DEPOSITO | I71: NOC | M71: SUB- TOTAL | N71: =SUM(N67:N70) -> 3115613.4
I72: NOC | K72: =SUM(H67:H72) -> 0
C73: -4908441.5
H74: =SUM(H52:H72) -> 0 | M74: TOTAL | N74: =N65+N71 -> 9438413.4
L76: ARQUEO DE CAJA AL CIERRE (COMPOSICION DEL SALDO)
C77: TOTAL DE INGRESO | H77: =H9+H37+N48 -> 13442603 | L77: PREMIOS | N77: =N71 -> 3115613.4
L78: EFECTIVO | N78: =N65 -> 6322800
C79: TOTAL DE EGRESO | H79: =H74+H41+D41+D43+D44+D45+D46+H42+H43+H44+H45+H46 -> 4004200 | L79: TOTAL DE CAJA AL CIERRE | N79: =N71+N65 -> 9438413.4
C81: SALDO DEL DIA | H81: =H77-H79 -> 9438403.4 | L81: DIFERENCIA DE CAJA | N81: =N79-H81 -> 10
L82: (+) POSITIVO | M82: (-) NEGATIVO

Sheet 1001
D3: PLANILLA DE RECAUDACION DIARIA DE APUESTA Y PREMIOS | M3: ='0101'!M2 -> 2025
D5: FECHA : | E5: 45170 | G5: RECAUDACION DEL DIA: | I5: 45169
C7: 26 | D7: SALDO DEL DIA ANTERIOR | G7: PREMIOS | H7: ='0901'!N77 -> 3115613.4
G8: EFECTIVO | H8: ='0901'!N78 -> 6322800
G9: TOTAL | H9: =H7+H8 -> 9438413.4 | Q9: TICKET ANULADOS | AA9: TICKET PREMIADOS | AL9: TICKET VENDIDOS
B11: SUB | C11: MATUTINA | D11: VESPERT. | E11: SIESTA | F11: TARDE | G11: NOCT. | H11: TOTAL | J11: PREMIOS | K11: EFECTIVO | L11: MONEDAS | M11: TOTAL | N11: DIFER. | Q11: M | R11: V | S11: S | T11: T | U11: N | V11: TOTAL | X11: PRES. | Y11: DIFER. | AA11: ANT | AB11: M | AC11: V | AD11: S | AE11: T | AF11: N | AG11: TOTAL | AI11: PRES | AJ11: DIFER. | AL11: M | AM11: V | AN11: S | AO11: T | AP11: N | AQ11: TOTAL | AS11: PRES. | AT11: DIFER.
H12: =SUM(H13:H16) -> 1351950
B13: 001 | C13: 260100 | D13: 68900 | E13: 19300 | F13: 44900 | G13: 70200 | H13: =SUM(C13:G13) -> 463400 | I13: 001 | J13: 266000 | K13: 195000 | M13: =SUM(J13:L13) -> 461000 | N13: =H13-M13 -> 2400 | T13: 1 | U13: 2 | V13: =U13+T13+S13+R13+Q13 -> 3 | X13: 0 | Y13: =V13-X13 -> 3 | Z13: V | AA13: 5 | AD13: 1 | AG13: =AF13+AE13+AD13+AC13+AB13+AA13 -> 6 | AI13: 0 | AJ13: =AG13-AI13 -> 6 | AL13: 142 | AM13: 49 | AN13: 17 | AO13: 29 | AP13: 45 | AQ13: =AP13+AO13+AN13+AM13+AL13 -> 282 | AS13: 5 | AT13: =AQ13-AS13 -> 277
B14: 002 | H14: =SUM(C14:G14) -> 0 | I14: 002 | M14: =SUM(J14:L14) -> 0 | N14: =H14-M14 -> 0 | V14: =U14+T14+S14+R14+Q14 -> 0 | X14: 0 | Y14: =V14-X14 -> 0 | Z14: L | AG14: =AF14+AE14+AD14+AC14+AB14+AA14 -> 0 | AJ14: =AG14-AI14 -> 0 | AQ14: =AP14+AO14+AN14+AM14+AL14 -> 0 | AS14: 0 | AT14: =AQ14-AS14 -> 0
B15: 003 | C15: 339000 | D15: 162100 | E15: 96050 | F15: 156600 | G15: 134800 | H15: =SUM(C15:G15) -> 888550 | I15: 003 | J15: 658950 | K15: 229600 | M15: =SUM(J15:L15) -> 888550 | N15: =H15-M15 -> 0 | T15: 1 | V15: =U15+T15+S15+R15+Q15 -> 1 | X15: 0 | Y15: =V15-X15 -> 1 | Z15: M | AA15: 9 | AB15: 1 | AC15: 7 | AG15: =AF15+AE15+AD15+AC15+AB15+AA15 -> 17 | AJ15: =AG15-AI15 -> 17 | AL15: 142 | AM15: 70 | AN15: 29 | AO15: 50 | AP15: 49 | AQ15: =AP15+AO15+AN15+AM15+AL15 -> 340 | AS15: 0 | AT15: =AQ15-AS15 -> 340
B16: 004 | H16: =SUM(C16:G16) -> 0 | I16: 004 | M16: =SUM(J16:L16) -> 0 | N16: =H16-M16 -> 0 | V16: =U16+T16+S16+R16+Q16 -> 0 | X16: 0 | Y16: =V16-X16 -> 0 | AG16: =AF16+AE16+AD16+AC16+AB16+AA16 -> 0 | AJ16: =AG16-AI16 -> 0 | AQ16: =AP16+AO16+AN16+AM16+AL16 -> 0 | AS16: 0 | AT16: =AQ16-AS16 -> 0
B17: 26/001 | C17: 104100 | D17: 94400 | E17: 56100 | F17: 37200 | G17: 103800 | H17: =SUM(C17:G17) -> 395600 | I17: 01 | J17: 145000 | K17: 250600 | M17: =SUM(J17:L17) -> 395600 | N17: =H17-M17 -> 0 | Q17: 2 | R17: 2 | T17: 2 | U17: 1 | V17: =U17+T17+S17+R17+Q17 -> 7 | X17: 0 | Y17: =V17-X17 -> 7 | Z17: 01 | AC17: 4 | AG17: =AF17+AE17+AD17+AC17+AB17+AA17 -> 4 | AJ17: =AG17-AI17 -> 4 | AK17: 01 | AL17: 80 | AM17: 85 | AN17: 54 | AO17: 37 | AP17: 83 | AQ17: =AP17+AO17+AN17+AM17+AL17 -> 339 | AS17: 0 | AT17: =AQ17-AS17 -> 339
B18: 26/002 | C18: 308150 | D18: 213650 | E18: 85020 | F18: 129150 | G18: 279050 | H18: =SUM(C18:G18) -> 1015020 | I18: 02 | J18: 624050 | K18: 390950 | M18: =SUM(J18:L18) -> 1015000 | N18: =H18-M18 -> 20 | Q18: 1 | V18: =U18+T18+S18+R18+Q18 -> 1 | X18: 0 | Y18: =V18-X18 -> 1 | Z18: 02 | AA18: 10 | AC18: 1 | AD18: 3 | AE18: 2 | AG18: =AF18+AE18+AD18+AC18+AB18+AA18 -> 16 | AJ18: =AG18-AI18 -> 16 | AK18: 02 | AL18: 226 | AM18: 162 | AN18: 101 | AO18: 111 | AP18: 170 | AQ18: =AP18+AO18+AN18+AM18+AL18 -> 770 | AS18: 0 | AT18: =AQ18-AS18 -> 770
B19: 26/003 | C19: 129600 | D19: 104700 | E19: 114200 | F19: 125300 | G19: 249900 | H19: =SUM(C19:G19) -> 723700 | I19: 03 | J19: 45500 | K19: 678200 | M19: =SUM(J19:L19) -> 723700 | N19: =H19-M19 -> 0 | V19: =U19+T19+S19+R19+Q19 -> 0 | X19: 0 | Y19: =V19-X19 -> 0 | Z19: 03 | AC19: 2 | AD19: 1 | AE19: 1 | AG19: =AF19+AE19+AD19+AC19+AB19+AA19 -> 4 | AJ19: =AG19-AI19 -> 4 | AK19: 03 | AL19: 67 | AM19: 59 | AN19: 63 | AO19: 61 | AP19: 135 | AQ19: =AP19+AO19+AN19+AM19+AL19 -> 385 | AS19: 0 | AT19: =AQ19-AS19 -> 385
B20: 26/004 | C20: 90700 | D20: 116000 | E20: 84700 | F20: 87200 | G20: 183600 | H20: =SUM(C20:G20) -> 562200 | I20: 04 | J20: 115500 | K20: 442700 | M20: =SUM(J20:L20) -> 558200 | N20: =H20-M20 -> 4000 | V20: =U20+T20+S20+R20+Q20 -> 0 | X20: 0 | Y20: =V20-X20 -> 0 | Z20: 04 | AA20: 2 | AB20: 1 | AD20: 2 | AE20: 1 | AG20: =AF20+AE20+AD20+AC20+AB20+AA20 -> 6 | AJ20: =AG20-AI20 -> 6 | AK20: 04 | AL20: 66 | AM20: 72 | AN20: 58 | AO20: 56 | AP20: 104 | AQ20: =AP20+AO20+AN20+AM20+AL20 -> 356 | AS20: 0 | AT20: =AQ20-AS20 -> 356
B21: 26/005 | C21: 99600 | D21: 98600 | E21: 52500 | F21: 79400 | G21: 96600 | H21: =SUM(C21:G21) -> 426700 | I21: 05 | J21: 221900 | K21: 29600 | L21: 175200 | M21: =SUM(J21:L21) -> 426700 | N21: =H21-M21 -> 0 | V21: =U21+T21+S21+R21+Q21 -> 0 | X21: 0 | Y21: =V21-X21 -> 0 | Z21: 05 | AA21: 1 | AB21: 1 | AC21: 2 | AD21: 1 | AE21: 1 | AG21: =AF21+AE21+AD21+AC21+AB21+AA21 -> 6 | AJ21: =AG21-AI21 -> 6 | AK21: 05 | AL21: 55 | AM21: 54 | AN21: 27 | AO21: 30 | AP21: 48 | AQ21: =AP21+AO21+AN21+AM21+AL21 -> 214 | AS21: 0 | AT21: =AQ21-AS21 -> 214
B22: 26/006 | C22: 77700 | D22: 202100 | E22: 112500 | F22: 106000 | G22: 211200 | H22: =SUM(C22:G22) -> 709500 | I22: 06 | J22: 306600 | K22: 402900 | M22: =SUM(J22:L22) -> 709500 | N22: =H22-M22 -> 0 | Q22: 1 | R22: 1 | V22: =U22+T22+S22+R22+Q22 -> 2 | X22: 0 | Y22: =V22-X22 -> 2 | Z22: 06 | AA22: 6 | AB22: 1 | AC22: 8 | AD22: 2 | AE22: 4 | AG22: =AF22+AE22+AD22+AC22+AB22+AA22 -> 21 | AJ22: =AG22-AI22 -> 21 | AK22: 06 | AL22: 55 | AM22: 120 | AN22: 57 | AO22: 68 | AP22: 118 | AQ22: =AP22+AO22+AN22+AM22+AL22 -> 418 | AS22: 0 | AT22: =AQ22-AS22 -> 418
B23: 26/007 | C23: 211150 | D23: 139250 | E23: 84400 | F23: 135900 | G23: 141850 | H23: =SUM(C23:G23) -> 712550 | I23: 07 | J23: 262500 | K23: 450050 | M23: =SUM(J23:L23) -> 712550 | N23: =H23-M23 -> 0 | V23: =U23+T23+S23+R23+Q23 -> 0 | X23: 0 | Y23: =V23-X23 -> 0 | Z23: 07 | AA23: 2 | AB23: 2 | AC23: 5 | AD23: 3 | AE23: 2 | AG23: =AF23+AE23+AD23+AC23+AB23+AA23 -> 14 | AJ23: =AG23-AI23 -> 14 | AK23: 07 | AL23: 121 | AM23: 103 | AN23: 54 | AO23: 82 | AP23: 103 | AQ23: =AP23+AO23+AN23+AM23+AL23 -> 463 | AS23: 0 | AT23: =AQ23-AS23 -> 463
B24: 26/008 | C24: 33600 | D24: 63950 | E24: 8750 | F24: 25000 | G24: 60000 | H24: =SUM(C24:G24) -> 191300 | I24: 08 | J24: 35000 | K24: 156300 | M24: =SUM(J24:L24) -> 191300 | N24: =H24-M24 -> 0 | Q24: 1 | V24: =U24+T24+S24+R24+Q24 -> 1 | X24: 0 | Y24: =V24-X24 -> 1 | Z24: 08 | AC24: 1 | AG24: =AF24+AE24+AD24+AC24+AB24+AA24 -> 1 | AJ24: =AG24-AI24 -> 1 | AK24: 08 | AL24: 34 | AM24: 45 | AN24: 3 | AO24: 21 | AP24: 29 | AQ24: =AP24+AO24+AN24+AM24+AL24 -> 132 | AS24: 0 | AT24: =AQ24-AS24 -> 132
B25: 26/009 | C25: 90800 | D25: 129300 | E25: 71200 | F25: 43400 | G25: 148300 | H25: =SUM(C25:G25) -> 483000 | I25: 09 | J25: 171500 | K25: 311500 | M25: =SUM(J25:L25) -> 483000 | N25: =H25-M25 -> 0 | Q25: 1 | R25: 1 | S25: 3 | V25: =U25+T25+S25+R25+Q25 -> 5 | X25: 0 | Y25: =V25-X25 -> 5 | Z25: 09 | AB25: 1 | AC25: 4 | AD25: 1 | AG25: =AF25+AE25+AD25+AC25+AB25+AA25 -> 6 | AJ25: =AG25-AI25 -> 6 | AK25: 09 | AL25: 65 | AM25: 76 | AN25: 38 | AO25: 38 | AP25: 96 | AQ25: =AP25+AO25+AN25+AM25+AL25 -> 313 | AS25: 0 | AT25: =AQ25-AS25 -> 313
B26: 26/010 | H26: =SUM(C26:G26) -> 0 | I26: 10 | M26: =SUM(J26:L26) -> 0 | N26: =H26-M26 -> 0 | V26: =U26+T26+S26+R26+Q26 -> 0 | X26: 0 | Y26: =V26-X26 -> 0 | Z26: 10 | AG26: =AF26+AE26+AD26+AC26+AB26+AA26 -> 0 | AJ26: =AG26-AI26 -> 0 | AK26: 10 | AQ26: =AP26+AO26+AN26+AM26+AL26 -> 0 | AS26: 0 | AT26: =AQ26-AS26 -> 0
B27: 26/011 | C27: 72400 | D27: 65200 | E27: 24800 | F27: 39000 | G27: 43200 | H27: =SUM(C27:G27) -> 244600 | I27: 11 | J27: 427855 | L27: -183255 | M27: =SUM(J27:L27) -> 244600 | N27: =H27-M27 -> 0 | V27: =U27+T27+S27+R27+Q27 -> 0 | X27: 0 | Y27: =V27-X27 -> 0 | Z27: 11 | AA27: 3 | AC27: 3 | AD27: 1 | AG27: =AF27+AE27+AD27+AC27+AB27+AA27 -> 7 | AJ27: =AG27-AI27 -> 7 | AK27: 11 | AL27: 53 | AM27: 52 | AN27: 23 | AO27: 35 | AP27: 43 | AQ27: =AP27+AO27+AN27+AM27+AL27 -> 206 | AS27: 0 | AT27: =AQ27-AS27 -> 206
B28: 26/012 | C28: 93700 | D28: 134850 | E28: 91350 | F28: 56550 | G28: 75400 | H28: =SUM(C28:G28) -> 451850 | I28: 12 | J28: 127400 | K28: 324500 | L28: -50 | M28: =SUM(J28:L28) -> 451850 | N28: =H28-M28 -> 0 | Q28: 1 | R28: 2 | S28: 2 | V28: =U28+T28+S28+R28+Q28 -> 5 | X28: 0 | Y28: =V28-X28 -> 5 | Z28: 12 | AA28: 2 | AC28: 5 | AD28: 1 | AE28: 2 | AG28: =AF28+AE28+AD28+AC28+AB28+AA28 -> 10 | AJ28: =AG28-AI28 -> 10 | AK28: 12 | AL28: 75 | AM28: 98 | AN28: 68 | AO28: 55 | AP28: 74 | AQ28: =AP28+AO28+AN28+AM28+AL28 -> 370 | AS28: 0 | AT28: =AQ28-AS28 -> 370
B29: 26/013 | C29: 207500 | D29: 169900 | E29: 124600 | F29: 61700 | G29: 154600 | H29: =SUM(C29:G29) -> 718300 | I29: 13 | J29: 231000 | K29: 388800 | L29: 98500 | M29: =SUM(J29:L29) -> 718300 | N29: =H29-M29 -> 0 | V29: =U29+T29+S29+R29+Q29 -> 0 | X29: 0 | Y29: =V29-X29 -> 0 | Z29: 13 | AA29: 2 | AB29: 1 | AC29: 2 | AG29: =AF29+AE29+AD29+AC29+AB29+AA29 -> 5 | AJ29: =AG29-AI29 -> 5 | AK29: 13 | AL29: 81 | AM29: 85 | AN29: 58 | AO29: 33 | AP29: 71 | AQ29: =AP29+AO29+AN29+AM29+AL29 -> 328 | AS29: 0 | AT29: =AQ29-AS29 -> 328
B30: 26/014 | C30: 62700 | D30: 34800 | E30: 35600 | F30: 62800 | G30: 45100 | H30: =SUM(C30:G30) -> 241000 | I30: 14 | J30: 112000 | K30: 118400 | L30: 10600 | M30: =SUM(J30:L30) -> 241000 | N30: =H30-M30 -> 0 | V30: =U30+T30+S30+R30+Q30 -> 0 | X30: 0 | Y30: =V30-X30 -> 0 | Z30: 14 | AA30: 1 | AC30: 1 | AE30: 2 | AG30: =AF30+AE30+AD30+AC30+AB30+AA30 -> 4 | AJ30: =AG30-AI30 -> 4 | AK30: 14 | AL30: 48 | AM30: 28 | AN30: 20 | AO30: 44 | AP30: 30 | AQ30: =AP30+AO30+AN30+AM30+AL30 -> 170 | AS30: 0 | AT30: =AQ30-AS30 -> 170
B31: 26/015 | H31: =SUM(C31:G31) -> 0 | I31: 15 | M31: =SUM(J31:L31) -> 0 | N31: =H31-M31 -> 0 | V31: =U31+T31+S31+R31+Q31 -> 0 | X31: 0 | Y31: =V31-X31 -> 0 | Z31: 15 | AG31: =AF31+AE31+AD31+AC31+AB31+AA31 -> 0 | AJ31: =AG31-AI31 -> 0 | AK31: 15 | AQ31: =AP31+AO31+AN31+AM31+AL31 -> 0 | AS31: 0 | AT31: =AQ31-AS31 -> 0
B32: 26/016 | C32: 199800 | D32: 159900 | E32: 66800 | F32: 70800 | G32: 160700 | H32: =SUM(C32:G32) -> 658000 | I32: 16 | J32: 117600 | K32: 540400 | M32: =SUM(J32:L32) -> 658000 | N32: =H32-M32 -> 0 | T32: 1 | V32: =U32+T32+S32+R32+Q32 -> 1 | X32: 0 | Y32: =V32-X32 -> 1 | Z32: 16 | AA32: 1 | AB32: 1 | AC32: 2 | AD32: 1 | AG32: =AF32+AE32+AD32+AC32+AB32+AA32 -> 5 | AJ32: =AG32-AI32 -> 5 | AK32: 16 | AL32: 126 | AM32: 111 | AN32: 49 | AO32: 55 | AP32: 106 | AQ32: =AP32+AO32+AN32+AM32+AL32 -> 447 | AS32: 0 | AT32: =AQ32-AS32 -> 447
B33: 26/017 | C33: 27600 | D33: 32700 | E33: 15900 | F33: 14000 | G33: 27100 | H33: =SUM(C33:G33) -> 117300 | I33: 17 | J33: 35000 | K33: 72300 | L33: 9870 | M33: =SUM(J33:L33) -> 117170 | N33: =H33-M33 -> 130 | R33: 1 | V33: =U33+T33+S33+R33+Q33 -> 1 | X33: 0 | Y33: =V33-X33 -> 1 | Z33: 17 | AA33: 2 | AC33: 1 | AG33: =AF33+AE33+AD33+AC33+AB33+AA33 -> 3 | AJ33: =AG33-AI33 -> 3 | AK33: 17 | AL33: 26 | AM33: 23 | AN33: 14 | AO33: 12 | AP33: 30 | AQ33: =AP33+AO33+AN33+AM33+AL33 -> 105 | AS33: 0 | AT33: =AQ33-AS33 -> 105
B34: 26/018 | H34: =SUM(C34:G34) -> 0 | I34: 18 | M34: =SUM(J34:L34) -> 0 | N34: =H34-M34 -> 0 | V34: =U34+T34+S34+R34+Q34 -> 0 | X34: 0 | Y34: =V34-X34 -> 0 | Z34: 18 | AG34: =AF34+AE34+AD34+AC34+AB34+AA34 -> 0 | AJ34: =AG34-AI34 -> 0 | AK34: 18 | AQ34: =AP34+AO34+AN34+AM34+AL34 -> 0 | AS34: 0 | AT34: =AQ34-AS34 -> 0
B35: 26/019 | H35: =SUM(C35:G35) -> 0 | I35: 19 | M35: =SUM(J35:L35) -> 0 | N35: =H35-M35 -> 0 | V35: =U35+T35+S35+R35+Q35 -> 0 | X35: 0 | Y35: =V35-X35 -> 0 | Z35: 19 | AG35: =AF35+AE35+AD35+AC35+AB35+AA35 -> 0 | AJ35: =AG35-AI35 -> 0 | AK35: 19 | AQ35: =AP35+AO35+AN35+AM35+AL35 -> 0 | AS35: 0 | AT35: =AQ35-AS35 -> 0
C37: =SUM(C13:C35) -> 2408200 | D37: =SUM(D13:D35) -> 1990300 | E37: =SUM(E13:E35) -> 1143770 | F37: =SUM(F13:F35) -> 1274900 | G37: =SUM(G13:G35) -> 2185400 | H37: =SUM(H13:H35) -> 9002570 | J37: =SUM(J13:J35) -> 3903355 | K37: =SUM(K13:K36) -> 4981800 | L37: =SUM(L14:L35) -> 110865 | M37: =SUM(M13:M35) -> 8996020 | Q37: TOTAL ANULADAS | U37: =SUM(V13:V35) -> 27 | X37: =SUM(X13:X35) -> 0 | AA37: TOTAL PREMIADAS | AF37: =SUM(AG13:AG35) -> 135 | AI37: =SUM(AI13:AI35) -> 0 | AL37: TOTAL VENDIDAS | AP37: =SUM(AQ13:AQ35) -> 5638 | AS37: =SUM(AS13:AS35) -> 5
B39: DEBEN / SALIDA | J39: PAGAN / ENTRADA
B41: MARTIN GASTOS | D41: 0 | E41: DEPOSITOS | H41: =D42+C73 -> 9332269.4 | J41: DEUDA DE CAJA s/l/v | L41: 0 | M41: EXCEDENTE | N41: 0
B42: PREMIOS | D42: =J37 -> 3903355 | E42: PREST. PALP. | H42: 0 | J42: FALTANTE DE CAJA | L42: 0 | M42: MARTIN | N42: 0
B43: LIBRERIA | D43: 0 | E43: PREST. TELEKINO | H43: 0 | J43: PREST. PALP./ REVISTA | L43: 0 | M43: PREMIOS | N43: 0
B44: LIMPIEZA | D44: 0 | E44: PREST. JGOS. MENORES | H44: 0 | J44: PREST. TELEKINO | L44: 0 | N44: 0
B45: SODA/AGUA | D45: 0 | E45: IMPUESTOS | H45: 0 | J45: PREST. JGOS. MENORES | L45: 0 | N45: 0
B46: GASTOS VARIOS | D46: 0 | E46: OTROS | H46: =SUM(N13:N35) -> 6550 | L46: 0 | N46: 0
B48: SUB TOTAL | D48: =D41+D42+D43+D44+D45+D46+H42+H43+H44+H45+H46 -> 3909905 | G48: TOTAL | H48: =D48+H41 -> 13242174 | M48: SUB TOTAL | N48: =L41+L42+L43+L44+L45+L46+N41+N42+N43+N44+N45+N46 -> 0
C50: DETALLE RECAUDACION DE CAJA | H50: IMPORTE | J50: FECHA | L50: DETALLE CIERRE DE CAJA
C52: 20000 x | D52: 66 | E52: =20000*D52 -> 1320000 | I52: MAT | L52: 20000 x | M52: 38 | N52: =20000*M52 -> 760000
C53: 10000 x | D53: 195 | E53: =10000*D53 -> 1950000 | I53: MAT | L53: 10000 x | M53: 173 | N53: =10000*M53 -> 1730000
C54: 2000 x | D54: 321 | E54: =2000*D54 -> 642000 | I54: MAT | L54: 2000 x | M54: 567 | N54: =2000*M54 -> 1134000
C55: 1000 x | D55: 1131 | E55: =1000*D55 -> 1131000 | I55: MAT | L55: 1000 x | M55: 1230 | N55: =1000*M55 -> 1230000
C56: 500 x | D56: 55 | E56: =500*D56 -> 27500 | I56: MAT | K56: =SUM(H52:H56) -> 0 | L56: 500 x | M56: 164 | N56: =500*M56 -> 82000
C57: 200 x | D57: 69 | E57: =200*D57 -> 13800 | I57: VEP | L57: 200 x | M57: 315 | N57: =200*M57 -> 63000
C58: 100 x | D58: 153 | E58: =100*D58 -> 15300 | I58: VEP | L58: 100 x | M58: 238 | N58: =100*M58 -> 23800
C59: 50 x | D59: 2 | E59: =50*D59 -> 100 | I59: VEP | L59: 50 x | M59: 1798 | N59: =50*M59 -> 89900
C60: 20 x | D60: 1 | E60: =20*D60 -> 20 | I60: VEP | L60: 20 x | M60: 1512 | N60: =20*M60 -> 30240
C61: 10 x | D61: 0 | E61: =10*D61 -> 0 | I61: VEP | K61: =SUM(H57:H61) -> 0 | L61: 10 x | M61: 360 | N61: =10*M61 -> 3600
C62: 5 x | D62: 0 | E62: =5*D62 -> 0 | I62: TAR | L62: 5 x | M62: 0 | N62: =5*M62 -> 0
C63: 2 x | D63: 0 | E63: =2*D63 -> 0 | I63: TAR | L63: 2 x | M63: 0 | N63: =2*M63 -> 0
C64: 1 x | D64: 0 | E64: =1*D64 -> 0 | I64: TAR | L64: 1 x | M64: 0 | N64: =1*M64 -> 0
C65: SUB - TOTAL | E65: =SUM(E52:F64) -> 5099720 | I65: TAR | L65: SUB - TOTAL | N65: =SUM(N52:N64) -> 5146540
I66: TAR | K66: =SUM(H62:H66) -> 0
D67: TOTAL | F67: =D48+E65 -> 9009625 | I67: NOC | L67: PREMOS | N67: 840000
I68: NOC | L68: TELEKINOS | N68: 0
D69: DIFERENCIA | F69: =F67-H37 -> 7055 | I69: NOC | L69: BOL. S/PREMIOS | N69: 3115613.4
I70: NOC | L70: OTROS | N70: 0
C71: DEPOSITO | I71: NOC | M71: SUB- TOTAL | N71: =SUM(N67:N70) -> 3955613.4
I72: NOC | K72: =SUM(H67:H72) -> 0
C73: 5428914.4
H74: =SUM(H52:H72) -> 0 | M74: TOTAL | N74: =N65+N71 -> 9102153.4
L76: ARQUEO DE CAJA AL CIERRE (COMPOSICION DEL SALDO)
C77: TOTAL DE INGRESO | H77: =H9+H37+N48 -> 18440983 | L77: PREMIOS | N77: =N71 -> 3955613.4
L78: EFECTIVO | N78: =N65 -> 5146540
C79: TOTAL DE EGRESO | H79: =H74+H41+D41+D43+D44+D45+D46+H42+H43+H44+H45+H46 -> 9338819.4 | L79: TOTAL DE CAJA AL CIERRE | N79: =N71+N65 -> 9102153.4
C81: SALDO DEL DIA | H81: =H77-H79 -> 9102164 | L81: DIFERENCIA DE CAJA | N81: =N79-H81 -> -10.56
L82: (+) POSITIVO | M82: (-) NEGATIVO

Sheet 1101
D3: PLANILLA DE RECAUDACION DIARIA DE APUESTA Y PREMIOS | M3: ='0101'!M2 -> 2025
D5: FECHA : | E5: 45170 | G5: RECAUDACION DEL DIA: | I5: 45169
C7: 26 | D7: SALDO DEL DIA ANTERIOR | G7: PREMIOS | H7: ='1001'!N77 -> 3955613.4
G8: EFECTIVO | H8: ='1001'!N78 -> 5146540
G9: TOTAL | H9: =H7+H8 -> 9102153.4 | Q9: TICKET ANULADOS | AA9: TICKET PREMIADOS | AL9: TICKET VENDIDOS
B11: SUB | C11: MATUTINA | D11: VESPERT. | E11: SIESTA | F11: TARDE | G11: NOCT. | H11: TOTAL | J11: PREMIOS | K11: EFECTIVO | L11: MONEDAS | M11: TOTAL | N11: DIFER. | Q11: M | R11: V | S11: S | T11: T | U11: N | V11: TOTAL | X11: PRES. | Y11: DIFER. | AA11: ANT | AB11: M | AC11: V | AD11: S | AE11: T | AF11: N | AG11: TOTAL | AI11: PRES | AJ11: DIFER. | AL11: M | AM11: V | AN11: S | AO11: T | AP11: N | AQ11: TOTAL | AS11: PRES. | AT11: DIFER.
H12: =SUM(H13:H16) -> 1387050
B13: 001 | C13: 189150 | D13: 76600 | E13: 12700 | F13: 38350 | G13: 45900 | H13: =SUM(C13:G13) -> 362700 | I13: 001 | J13: 147000 | K13: 215700 | M13: =SUM(J13:L13) -> 362700 | N13: =H13-M13 -> 0 | Q13: 1 | R13: 1 | U13: 3 | V13: =U13+T13+S13+R13+Q13 -> 5 | X13: 0 | Y13: =V13-X13 -> 5 | Z13: V | AA13: 3 | AB13: 5 | AF13: 0 | AG13: =AF13+AE13+AD13+AC13+AB13+AA13 -> 8 | AI13: 0 | AJ13: =AG13-AI13 -> 8 | AL13: 92 | AM13: 47 | AN13: 12 | AO13: 23 | AP13: 28 | AQ13: =AP13+AO13+AN13+AM13+AL13 -> 202 | AS13: 0 | AT13: =AQ13-AS13 -> 202
B14: 002 | H14: =SUM(C14:G14) -> 0 | I14: 002 | M14: =SUM(J14:L14) -> 0 | N14: =H14-M14 -> 0 | V14: =U14+T14+S14+R14+Q14 -> 0 | X14: 0 | Y14: =V14-X14 -> 0 | Z14: L | AG14: =AF14+AE14+AD14+AC14+AB14+AA14 -> 0 | AJ14: =AG14-AI14 -> 0 | AQ14: =AP14+AO14+AN14+AM14+AL14 -> 0 | AS14: 0 | AT14: =AQ14-AS14 -> 0
B15: 003 | C15: 257500 | D15: 210500 | E15: 120350 | F15: 163300 | G15: 272700 | H15: =SUM(C15:G15) -> 1024350 | I15: 003 | J15: 648200 | K15: 376200 | L15: -50 | M15: =SUM(J15:L15) -> 1024350 | N15: =H15-M15 -> 0 | V15: =U15+T15+S15+R15+Q15 -> 0 | X15: 0 | Y15: =V15-X15 -> 0 | Z15: M | AA15: 5 | AB15: 5 | AC15: 1 | AE15: 6 | AG15: =AF15+AE15+AD15+AC15+AB15+AA15 -> 17 | AJ15: =AG15-AI15 -> 17 | AL15: 112 | AM15: 103 | AN15: 39 | AO15: 48 | AP15: 89 | AQ15: =AP15+AO15+AN15+AM15+AL15 -> 391 | AS15: 0 | AT15: =AQ15-AS15 -> 391
B16: 004 | H16: =SUM(C16:G16) -> 0 | I16: 004 | J16: 840000 | L16: -840000 | M16: =SUM(J16:L16) -> 0 | N16: =H16-M16 -> 0 | V16: =U16+T16+S16+R16+Q16 -> 0 | X16: 0 | Y16: =V16-X16 -> 0 | AG16: =AF16+AE16+AD16+AC16+AB16+AA16 -> 0 | AJ16: =AG16-AI16 -> 0 | AQ16: =AP16+AO16+AN16+AM16+AL16 -> 0 | AS16: 0 | AT16: =AQ16-AS16 -> 0
B17: 26/001 | C17: 114900 | D17: 109600 | E17: 38850 | F17: 65050 | G17: 108200 | H17: =SUM(C17:G17) -> 436600 | I17: 01 | J17: 192850 | K17: 243750 | M17: =SUM(J17:L17) -> 436600 | N17: =H17-M17 -> 0 | U17: 2 | V17: =U17+T17+S17+R17+Q17 -> 2 | X17: 0 | Y17: =V17-X17 -> 2 | Z17: 01 | AA17: 2 | AC17: 1 | AE17: 4 | AG17: =AF17+AE17+AD17+AC17+AB17+AA17 -> 7 | AJ17: =AG17-AI17 -> 7 | AK17: 01 | AL17: 88 | AM17: 85 | AN17: 51 | AO17: 61 | AP17: 91 | AQ17: =AP17+AO17+AN17+AM17+AL17 -> 376 | AS17: 0 | AT17: =AQ17-AS17 -> 376
B18: 26/002 | C18: 302800 | D18: 299650 | E18: 130750 | F18: 110750 | G18: 294910 | H18: =SUM(C18:G18) -> 1138860 | I18: 02 | J18: 391724.94 | K18: 747150 | L18: -14.94 | M18: =SUM(J18:L18) -> 1138860 | N18: =H18-M18 -> 0 | Q18: 1 | U18: 2 | V18: =U18+T18+S18+R18+Q18 -> 3 | X18: 0 | Y18: =V18-X18 -> 3 | Z18: 02 | AA18: 3 | AB18: 6 | AC18: 6 | AD18: 3 | AE18: 3 | AG18: =AF18+AE18+AD18+AC18+AB18+AA18 -> 21 | AJ18: =AG18-AI18 -> 21 | AK18: 02 | AL18: 178 | AM18: 206 | AN18: 134 | AO18: 110 | AP18: 192 | AQ18: =AP18+AO18+AN18+AM18+AL18 -> 820 | AS18: 0 | AT18: =AQ18-AS18 -> 820
B19: 26/003 | C19: 183500 | D19: 191300 | E19: 110800 | F19: 133300 | G19: 182500 | H19: =SUM(C19:G19) -> 801400 | I19: 03 | J19: 441000 | K19: 360400 | M19: =SUM(J19:L19) -> 801400 | N19: =H19-M19 -> 0 | V19: =U19+T19+S19+R19+Q19 -> 0 | X19: 0 | Y19: =V19-X19 -> 0 | Z19: 03 | AA19: 1 | AB19: 5 | AC19: 4 | AD19: 2 | AE19: 5 | AG19: =AF19+AE19+AD19+AC19+AB19+AA19 -> 17 | AJ19: =AG19-AI19 -> 17 | AK19: 03 | AL19: 95 | AM19: 97 | AN19: 63 | AO19: 64 | AP19: 92 | AQ19: =AP19+AO19+AN19+AM19+AL19 -> 411 | AS19: 0 | AT19: =AQ19-AS19 -> 411
B20: 26/004 | C20: 104500 | D20: 92200 | E20: 65400 | F20: 76300 | G20: 149000 | H20: =SUM(C20:G20) -> 487400 | I20: 04 | J20: 452900 | K20: 30500 | M20: =SUM(J20:L20) -> 483400 | N20: =H20-M20 -> 4000 | Q20: 1 | V20: =U20+T20+S20+R20+Q20 -> 1 | X20: 0 | Y20: =V20-X20 -> 1 | Z20: 04 | AA20: 3 | AB20: 2 | AC20: 3 | AD20: 1 | AE20: 3 | AG20: =AF20+AE20+AD20+AC20+AB20+AA20 -> 12 | AJ20: =AG20-AI20 -> 12 | AK20: 04 | AL20: 69 | AM20: 60 | AN20: 40 | AO20: 47 | AP20: 86 | AQ20: =AP20+AO20+AN20+AM20+AL20 -> 302 | AS20: 0 | AT20: =AQ20-AS20 -> 302
B21: 26/005 | C21: 83400 | D21: 95000 | E21: 56600 | F21: 63900 | G21: 81800 | H21: =SUM(C21:G21) -> 380700 | I21: 05 | J21: 263347.37 | K21: 117350 | M21: =SUM(J21:L21) -> 380697.37 | N21: =H21-M21 -> 2.63 | R21: 2 | U21: 1 | V21: =U21+T21+S21+R21+Q21 -> 3 | X21: 0 | Y21: =V21-X21 -> 3 | Z21: 05 | AB21: 1 | AC21: 1 | AE21: 4 | AG21: =AF21+AE21+AD21+AC21+AB21+AA21 -> 6 | AJ21: =AG21-AI21 -> 6 | AK21: 05 | AL21: 42 | AM21: 54 | AN21: 27 | AO21: 37 | AP21: 47 | AQ21: =AP21+AO21+AN21+AM21+AL21 -> 207 | AS21: 0 | AT21: =AQ21-AS21 -> 207
B22: 26/006 | C22: 176700 | D22: 167400 | E22: 53050 | F22: 79650 | G22: 163500 | H22: =SUM(C22:G22) -> 640300 | I22: 06 | J22: 432950 | K22: 207400 | L22: -50 | M22: =SUM(J22:L22) -> 640300 | N22: =H22-M22 -> 0 | Q22: 2 | R22: 1 | S22: 1 | T22: 1 | U22: 3 | V22: =U22+T22+S22+R22+Q22 -> 8 | X22: 0 | Y22: =V22-X22 -> 8 | Z22: 06 | AA22: 5 | AB22: 4 | AC22: 1 | AD22: 2 | AE22: 7 | AG22: =AF22+AE22+AD22+AC22+AB22+AA22 -> 19 | AJ22: =AG22-AI22 -> 19 | AK22: 06 | AL22: 99 | AM22: 112 | AN22: 39 | AO22: 61 | AP22: 99 | AQ22: =AP22+AO22+AN22+AM22+AL22 -> 410 | AS22: 0 | AT22: =AQ22-AS22 -> 410
B23: 26/007 | C23: 157450 | D23: 170550 | E23: 84000 | F23: 72900 | G23: 223500 | H23: =SUM(C23:G23) -> 708400 | I23: 07 | J23: 130900 | K23: 577500 | M23: =SUM(J23:L23) -> 708400 | N23: =H23-M23 -> 0 | V23: =U23+T23+S23+R23+Q23 -> 0 | X23: 0 | Y23: =V23-X23 -> 0 | Z23: 07 | AA23: 1 | AB23: 3 | AC23: 1 | AD23: 1 | AE23: 4 | AG23: =AF23+AE23+AD23+AC23+AB23+AA23 -> 10 | AJ23: =AG23-AI23 -> 10 | AK23: 07 | AL23: 95 | AM23: 106 | AN23: 59 | AO23: 59 | AP23: 137 | AQ23: =AP23+AO23+AN23+AM23+AL23 -> 456 | AS23: 0 | AT23: =AQ23-AS23 -> 456
B24: 26/008 | H24: =SUM(C24:G24) -> 0 | I24: 08 | M24: =SUM(J24:L24) -> 0 | N24: =H24-M24 -> 0 | V24: =U24+T24+S24+R24+Q24 -> 0 | X24: 0 | Y24: =V24-X24 -> 0 | Z24: 08 | AG24: =AF24+AE24+AD24+AC24+AB24+AA24 -> 0 | AJ24: =AG24-AI24 -> 0 | AK24: 08 | AQ24: =AP24+AO24+AN24+AM24+AL24 -> 0 | AS24: 0 | AT24: =AQ24-AS24 -> 0
B25: 26/009 | C25: 119400 | D25: 79100 | E25: 12450 | F25: 60100 | G25: 154200 | H25: =SUM(C25:G25) -> 425250 | I25: 09 | J25: 21000 | K25: 404300 | L25: -50 | M25: =SUM(J25:L25) -> 425250 | N25: =H25-M25 -> 0 | S25: 1 | V25: =U25+T25+S25+R25+Q25 -> 1 | X25: 0 | Y25: =V25-X25 -> 1 | Z25: 09 | AA25: 1 | AB25: 1 | AE25: 1 | AG25: =AF25+AE25+AD25+AC25+AB25+AA25 -> 3 | AJ25: =AG25-AI25 -> 3 | AK25: 09 | AL25: 62 | AM25: 56 | AN25: 12 | AO25: 35 | AP25: 95 | AQ25: =AP25+AO25+AN25+AM25+AL25 -> 260 | AS25: 0 | AT25: =AQ25-AS25 -> 260
B26: 26/010 | H26: =SUM(C26:G26) -> 0 | I26: 10 | M26: =SUM(J26:L26) -> 0 | N26: =H26-M26 -> 0 | V26: =U26+T26+S26+R26+Q26 -> 0 | X26: 0 | Y26: =V26-X26 -> 0 | Z26: 10 | AG26: =AF26+AE26+AD26+AC26+AB26+AA26 -> 0 | AJ26: =AG26-AI26 -> 0 | AK26: 10 | AQ26: =AP26+AO26+AN26+AM26+AL26 -> 0 | AS26: 0 | AT26: =AQ26-AS26 -> 0
B27: 26/011 | C27: 58500 | D27: 54400 | E27: 43300 | F27: 24300 | G27: 26800 | H27: =SUM(C27:G27) -> 207300 | I27: 11 | J27: 35000 | K27: 183250 | L27: -10950 | M27: =SUM(J27:L27) -> 207300 | N27: =H27-M27 -> 0 | R27: 1 | S27: 2 | T27: 1 | V27: =U27+T27+S27+R27+Q27 -> 4 | X27: 0 | Y27: =V27-X27 -> 4 | Z27: 11 | AB27: 1 | AG27: =AF27+AE27+AD27+AC27+AB27+AA27 -> 1 | AJ27: =AG27-AI27 -> 1 | AK27: 11 | AL27: 46 | AM27: 48 | AN27: 50 | AO27: 25 | AP27: 22 | AQ27: =AP27+AO27+AN27+AM27+AL27 -> 191 | AS27: 0 | AT27: =AQ27-AS27 -> 191
B28: 26/012 | C28: 76300 | D28: 116800 | E28: 77250 | F28: 101100 | G28: 151000 | H28: =SUM(C28:G28) -> 522450 | I28: 12 | J28: 212818.42 | K28: 309600 | M28: =SUM(J28:L28) -> 522418.42 | N28: =H28-M28 -> 31.58 | Q28: 1 | T28: 2 | V28: =U28+T28+S28+R28+Q28 -> 3 | X28: 0 | Y28: =V28-X28 -> 3 | Z28: 12 | AA28: 5 | AB28: 1 | AD28: 2 | AE28: 2 | AG28: =AF28+AE28+AD28+AC28+AB28+AA28 -> 10 | AJ28: =AG28-AI28 -> 10 | AK28: 12 | AL28: 67 | AM28: 94 | AN28: 56 | AO28: 54 | AP28: 87 | AQ28: =AP28+AO28+AN28+AM28+AL28 -> 358 | AS28: 0 | AT28: =AQ28-AS28 -> 358
B29: 26/013 | C29: 151500 | D29: 123200 | E29: 100000 | F29: 75600 | G29: 86400 | H29: =SUM(C29:G29) -> 536700 | I29: 13 | J29: 224700 | K29: 312000 | M29: =SUM(J29:L29) -> 536700 | N29: =H29-M29 -> 0 | R29: 1 | T29: 1 | V29: =U29+T29+S29+R29+Q29 -> 2 | X29: 0 | Y29: =V29-X29 -> 2 | Z29: 13 | AA29: 1 | AB29: 4 | AC29: 1 | AG29: =AF29+AE29+AD29+AC29+AB29+AA29 -> 6 | AJ29: =AG29-AI29 -> 6 | AK29: 13 | AL29: 72 | AM29: 62 | AN29: 54 | AO29: 31 | AP29: 37 | AQ29: =AP29+AO29+AN29+AM29+AL29 -> 256 | AS29: 0 | AT29: =AQ29-AS29 -> 256
B30: 26/014 | C30: 144050 | D30: 117550 | E30: 53000 | F30: 57500 | G30: 37900 | H30: =SUM(C30:G30) -> 410000 | I30: 14 | J30: 126000 | K30: 284000 | M30: =SUM(J30:L30) -> 410000 | N30: =H30-M30 -> 0 | Q30: 1 | S30: 1 | V30: =U30+T30+S30+R30+Q30 -> 2 | X30: 0 | Y30: =V30-X30 -> 2 | Z30: 14 | AA30: 1 | AC30: 2 | AE30: 1 | AG30: =AF30+AE30+AD30+AC30+AB30+AA30 -> 4 | AJ30: =AG30-AI30 -> 4 | AK30: 14 | AL30: 92 | AM30: 86 | AN30: 29 | AO30: 31 | AP30: 29 | AQ30: =AP30+AO30+AN30+AM30+AL30 -> 267 | AS30: 0 | AT30: =AQ30-AS30 -> 267
B31: 26/015 | H31: =SUM(C31:G31) -> 0 | I31: 15 | M31: =SUM(J31:L31) -> 0 | N31: =H31-M31 -> 0 | V31: =U31+T31+S31+R31+Q31 -> 0 | X31: 0 | Y31: =V31-X31 -> 0 | Z31: 15 | AG31: =AF31+AE31+AD31+AC31+AB31+AA31 -> 0 | AJ31: =AG31-AI31 -> 0 | AK31: 15 | AQ31: =AP31+AO31+AN31+AM31+AL31 -> 0 | AS31: 0 | AT31: =AQ31-AS31 -> 0
B32: 26/016 | C32: 121550 | D32: 165700 | E32: 130100 | F32: 78500 | G32: 155500 | H32: =SUM(C32:G32) -> 651350 | I32: 16 | J32: 521500 | K32: 129850 | M32: =SUM(J32:L32) -> 651350 | N32: =H32-M32 -> 0 | Q32: 1 | R32: 1 | S32: 1 | T32: 1 | V32: =U32+T32+S32+R32+Q32 -> 4 | X32: 0 | Y32: =V32-X32 -> 4 | Z32: 16 | AA32: 4 | AB32: 4 | AC32: 3 | AD32: 2 | AE32: 2 | AG32: =AF32+AE32+AD32+AC32+AB32+AA32 -> 15 | AJ32: =AG32-AI32 -> 15 | AK32: 16 | AL32: 77 | AM32: 115 | AN32: 66 | AO32: 40 | AP32: 91 | AQ32: =AP32+AO32+AN32+AM32+AL32 -> 389 | AS32: 0 | AT32: =AQ32-AS32 -> 389
B33: 26/017 | C33: 47800 | D33: 25800 | E33: 22400 | F33: 53600 | G33: 30700 | H33: =SUM(C33:G33) -> 180300 | I33: 17 | J33: 21000 | K33: 159400 | L33: -100 | M33: =SUM(J33:L33) -> 180300 | N33: =H33-M33 -> 0 | V33: =U33+T33+S33+R33+Q33 -> 0 | X33: 0 | Y33: =V33-X33 -> 0 | Z33: 17 | AC33: 2 | AD33: 1 | AG33: =AF33+AE33+AD33+AC33+AB33+AA33 -> 3 | AJ33: =AG33-AI33 -> 3 | AK33: 17 | AL33: 47 | AM33: 37 | AN33: 29 | AO33: 38 | AP33: 28 | AQ33: =AP33+AO33+AN33+AM33+AL33 -> 179 | AS33: 0 | AT33: =AQ33-AS33 -> 179
B34: 26/018 | H34: =SUM(C34:G34) -> 0 | I34: 18 | M34: =SUM(J34:L34) -> 0 | N34: =H34-M34 -> 0 | V34: =U34+T34+S34+R34+Q34 -> 0 | X34: 0 | Y34: =V34-X34 -> 0 | Z34: 18 | AG34: =AF34+AE34+AD34+AC34+AB34+AA34 -> 0 | AJ34: =AG34-AI34 -> 0 | AK34: 18 | AQ34: =AP34+AO34+AN34+AM34+AL34 -> 0 | AS34: 0 | AT34: =AQ34-AS34 -> 0
B35: 26/019 | H35: =SUM(C35:G35) -> 0 | I35: 19 | M35: =SUM(J35:L35) -> 0 | N35: =H35-M35 -> 0 | V35: =U35+T35+S35+R35+Q35 -> 0 | X35: 0 | Y35: =V35-X35 -> 0 | Z35: 19 | AG35: =AF35+AE35+AD35+AC35+AB35+AA35 -> 0 | AJ35: =AG35-AI35 -> 0 | AK35: 19 | AQ35: =AP35+AO35+AN35+AM35+AL35 -> 0 | AS35: 0 | AT35: =AQ35-AS35 -> 0
C37: =SUM(C13:C35) -> 2289000 | D37: =SUM(D13:D35) -> 2095350 | E37: =SUM(E13:E35) -> 1111000 | F37: =SUM(F13:F35) -> 1254200 | G37: =SUM(G13:G35) -> 2164510 | H37: =SUM(H13:H35) -> 8914060 | J37: =SUM(J13:J35) -> 5102890.7 | K37: =SUM(K13:K36) -> 4658350 | L37: =SUM(L14:L35) -> -851214.94 | M37: =SUM(M13:M35) -> 8910025.8 | Q37: TOTAL ANULADAS | U37: =SUM(V13:V35) -> 38 | X37: =SUM(X13:X35) -> 0 | AA37: TOTAL PREMIADAS | AF37: =SUM(AG13:AG35) -> 159 | AI37: =SUM(AI13:AI35) -> 0 | AL37: TOTAL VENDIDAS | AP37: =SUM(AQ13:AQ35) -> 5475 | AS37: =SUM(AS13:AS35) -> 0
B39: DEBEN / SALIDA | J39: PAGAN / ENTRADA
B41: MARTIN GASTOS | D41: 0 | E41: DEPOSITOS | H41: =D42+C73 -> 9002570 | J41: DEUDA DE CAJA s/l/v | L41: 0 | M41: EXCEDENTE | N41: 0
B42: PREMIOS | D42: =J37 -> 5102890.7 | E42: PREST. PALP. | H42: 0 | J42: FALTANTE DE CAJA | L42: 0 | M42: MARTIN | N42: 0
B43: LIBRERIA | D43: 0 | E43: PREST. TELEKINO | H43: 0 | J43: PREST. PALP./ REVISTA | L43: 0 | M43: PREMIOS | N43: 0
B44: LIMPIEZA | D44: 0 | E44: PREST. JGOS. MENORES | H44: 0 | J44: PREST. TELEKINO | L44: 0 | N44: 0
B45: SODA/AGUA | D45: 0 | E45: IMPUESTOS | H45: 0 | J45: PREST. JGOS. MENORES | L45: 0 | N45: 0
B46: GASTOS VARIOS | D46: 0 | E46: OTROS | H46: =SUM(N13:N35) -> 4034.21 | L46: 0 | N46: 0
B48: SUB TOTAL | D48: =D41+D42+D43+D44+D45+D46+H42+H43+H44+H45+H46 -> 5106924.9 | G48: TOTAL | H48: =D48+H41 -> 14109495 | M48: SUB TOTAL | N48: =L41+L42+L43+L44+L45+L46+N41+N42+N43+N44+N45+N46 -> 0
C50: DETALLE RECAUDACION DE CAJA | H50: IMPORTE | J50: FECHA | L50: DETALLE CIERRE DE CAJA
C52: 20000 x | D52: 48 | E52: =20000*D52 -> 960000 | I52: MAT | L52: 20000 x | M52: 93 | N52: =20000*M52 -> 1860000
C53: 10000 x | D53: 217 | E53: =10000*D53 -> 2170000 | I53: MAT | L53: 10000 x | M53: 249 | N53: =10000*M53 -> 2490000
C54: 2000 x | D54: 473 | E54: =2000*D54 -> 946000 | I54: MAT | L54: 2000 x | M54: 40 | N54: =2000*M54 -> 80000
C55: 1000 x | D55: 543 | E55: =1000*D55 -> 543000 | I55: MAT | L55: 1000 x | M55: 722 | N55: =1000*M55 -> 722000
C56: 500 x | D56: 34 | E56: =500*D56 -> 17000 | I56: MAT | K56: =SUM(H52:H56) -> 0 | L56: 500 x | M56: 198 | N56: =500*M56 -> 99000
C57: 200 x | D57: 27 | E57: =200*D57 -> 5400 | I57: VEP | L57: 200 x | M57: 239 | N57: =200*M57 -> 47800
C58: 100 x | D58: 57 | E58: =100*D58 -> 5700 | I58: VEP | L58: 100 x | M58: 92 | N58: =100*M58 -> 9200
C59: 50 x | D59: 5 | E59: =50*D59 -> 250 | I59: VEP | L59: 50 x | M59: 1804 | N59: =50*M59 -> 90200
C60: 20 x | D60: 0 | E60: =20*D60 -> 0 | I60: VEP | L60: 20 x | M60: 1520 | N60: =20*M60 -> 30400
C61: 10 x | D61: 0 | E61: =10*D61 -> 0 | I61: VEP | K61: =SUM(H57:H61) -> 0 | L61: 10 x | M61: 340 | N61: =10*M61 -> 3400
C62: 5 x | D62: 0 | E62: =5*D62 -> 0 | I62: TAR | L62: 5 x | M62: 0 | N62: =5*M62 -> 0
C63: 2 x | D63: 0 | E63: =2*D63 -> 0 | I63: TAR | L63: 2 x | M63: 0 | N63: =2*M63 -> 0
C64: 1 x | D64: 0 | E64: =1*D64 -> 0 | I64: TAR | L64: 1 x | M64: 0 | N64: =1*M64 -> 0
C65: SUB - TOTAL | E65: =SUM(E52:F64) -> 4647350 | I65: TAR | L65: SUB - TOTAL | N65: =SUM(N52:N64) -> 5432000
I66: TAR | K66: =SUM(H62:H66) -> 0
D67: TOTAL | F67: =D48+E65 -> 9754274.9 | I67: NOC | L67: PREMOS | N67: 462000
I68: NOC | L68: TELEKINOS | N68: 0
D69: DIFERENCIA | F69: =F67-H37 -> 840214.94 | I69: NOC | L69: BOL. S/PREMIOS | N69: 3115613.4
I70: NOC | L70: OTROS | N70: 0
C71: DEPOSITO | I71: NOC | M71: SUB- TOTAL | N71: =SUM(N67:N70) -> 3577613.4
I72: NOC | K72: =SUM(H67:H72) -> 0
C73: 3899679.3
H74: =SUM(H52:H72) -> 0 | M74: TOTAL | N74: =N65+N71 -> 9009613.4
L76: ARQUEO DE CAJA AL CIERRE (COMPOSICION DEL SALDO)
C77: TOTAL DE INGRESO | H77: =H9+H37+N48 -> 18016213 | L77: PREMIOS | N77: =N71 -> 3577613.4
L78: EFECTIVO | N78: =N65 -> 5432000
C79: TOTAL DE EGRESO | H79: =H74+H41+D41+D43+D44+D45+D46+H42+H43+H44+H45+H46 -> 9006604.2 | L79: TOTAL DE CAJA AL CIERRE | N79: =N71+N65 -> 9009613.4
C81: SALDO DEL DIA | H81: =H77-H79 -> 9009609.2 | L81: DIFERENCIA DE CAJA | N81: =N79-H81 -> 4.21
L82: (+) POSITIVO | M82: (-) NEGATIVO

Sheet 1201
D3: PLANILLA DE RECAUDACION DIARIA DE APUESTA Y PREMIOS | M3: ='0101'!M2 -> 2025
D5: FECHA : | E5: 45170 | G5: RECAUDACION DEL DIA: | I5: 45169
C7: 26 | D7: SALDO DEL DIA ANTERIOR | G7: PREMIOS | H7: ='1101'!N77 -> 3577613.4
G8: EFECTIVO | H8: ='1101'!N78 -> 5432000
G9: TOTAL | H9: =H7+H8 -> 9009613.4 | Q9: TICKET ANULADOS | AA9: TICKET PREMIADOS | AL9: TICKET VENDIDOS
B11: SUB | C11: MATUTINA | D11: VESPERT. | E11: SIESTA | F11: TARDE | G11: NOCT. | H11: TOTAL | J11: PREMIOS | K11: EFECTIVO | L11: MONEDAS | M11: TOTAL | N11: DIFER. | Q11: M | R11: V | S11: S | T11: T | U11: N | V11: TOTAL | X11: PRES. | Y11: DIFER. | AA11: ANT | AB11: M | AC11: V | AD11: S | AE11: T | AF11: N | AG11: TOTAL | AI11: PRES | AJ11: DIFER. | AL11: M | AM11: V | AN11: S | AO11: T | AP11: N | AQ11: TOTAL | AS11: PRES. | AT11: DIFER.
H12: =SUM(H13:H16) -> 1439100
B13: 001 | C13: 235450 | D13: 170150 | E13: 45400 | F13: 80100 | G13: 140800 | H13: =SUM(C13:G13) -> 671900 | I13: 001 | J13: 590100 | K13: 85200 | L13: -3400 | M13: =SUM(J13:L13) -> 671900 | N13: =H13-M13 -> 0 | V13: =U13+T13+S13+R13+Q13 -> 0 | X13: 0 | Y13: =V13-X13 -> 0 | Z13: V | AA13: 4 | AB13: 9 | AC13: 3 | AE13: 2 | AG13: =AF13+AE13+AD13+AC13+AB13+AA13 -> 18 | AI13: 0 | AJ13: =AG13-AI13 -> 18 | AL13: 133 | AM13: 102 | AN13: 25 | AO13: 43 | AP13: 69 | AQ13: =AP13+AO13+AN13+AM13+AL13 -> 372 | AS13: 0 | AT13: =AQ13-AS13 -> 372
B14: 002 | E14: 57900 | F14: 46250 | G14: 126450 | H14: =SUM(C14:G14) -> 230600 | I14: 002 | J14: 196000 | K14: 34600 | M14: =SUM(J14:L14) -> 230600 | N14: =H14-M14 -> 0 | S14: 1 | T14: 1 | U14: 2 | V14: =U14+T14+S14+R14+Q14 -> 4 | X14: 0 | Y14: =V14-X14 -> 4 | Z14: L | AA14: 2 | AB14: 1 | AC14: 4 | AG14: =AF14+AE14+AD14+AC14+AB14+AA14 -> 7 | AJ14: =AG14-AI14 -> 7 | AN14: 21 | AO14: 26 | AP14: 68 | AQ14: =AP14+AO14+AN14+AM14+AL14 -> 115 | AS14: 0 | AT14: =AQ14-AS14 -> 115
B15: 003 | C15: 297100 | D15: 174800 | E15: 27650 | F15: 13600 | G15: 23450 | H15: =SUM(C15:G15) -> 536600 | I15: 003 | J15: 459900 | K15: 76700 | L15: 0 | M15: =SUM(J15:L15) -> 536600 | N15: =H15-M15 -> 0 | V15: =U15+T15+S15+R15+Q15 -> 0 | X15: 0 | Y15: =V15-X15 -> 0 | Z15: M | AA15: 4 | AB15: 6 | AG15: =AF15+AE15+AD15+AC15+AB15+AA15 -> 10 | AJ15: =AG15-AI15 -> 10 | AL15: 133 | AM15: 100 | AN15: 22 | AO15: 9 | AP15: 15 | AQ15: =AP15+AO15+AN15+AM15+AL15 -> 279 | AS15: 0 | AT15: =AQ15-AS15 -> 279
B16: 004 | H16: =SUM(C16:G16) -> 0 | I16: 004 | J16: 462000 | L16: -462000 | M16: =SUM(J16:L16) -> 0 | N16: =H16-M16 -> 0 | V16: =U16+T16+S16+R16+Q16 -> 0 | X16: 0 | Y16: =V16-X16 -> 0 | AG16: =AF16+AE16+AD16+AC16+AB16+AA16 -> 0 | AJ16: =AG16-AI16 -> 0 | AQ16: =AP16+AO16+AN16+AM16+AL16 -> 0 | AS16: 0 | AT16: =AQ16-AS16 -> 0
B17: 26/001 | C17: 136400 | D17: 127700 | E17: 71700 | F17: 89150 | G17: 118250 | H17: =SUM(C17:G17) -> 543200 | I17: 01 | J17: 712500 | L17: -169300 | M17: =SUM(J17:L17) -> 543200 | N17: =H17-M17 -> 0 | V17: =U17+T17+S17+R17+Q17 -> 0 | X17: 0 | Y17: =V17-X17 -> 0 | Z17: 01 | AA17: 1 | AB17: 9 | AC17: 8 | AG17: =AF17+AE17+AD17+AC17+AB17+AA17 -> 18 | AJ17: =AG17-AI17 -> 18 | AK17: 01 | AL17: 85 | AM17: 92 | AN17: 56 | AO17: 63 | AP17: 93 | AQ17: =AP17+AO17+AN17+AM17+AL17 -> 389 | AS17: 0 | AT17: =AQ17-AS17 -> 389
B18: 26/002 | C18: 348600 | D18: 400600 | E18: 186350 | F18: 182150 | G18: 263405 | H18: =SUM(C18:G18) -> 1381105 | I18: 02 | J18: 807100 | K18: 574000 | M18: =SUM(J18:L18) -> 1381100 | N18: =H18-M18 -> 5 | Q18: 1 | R18: 1 | S18: 1 | V18: =U18+T18+S18+R18+Q18 -> 3 | X18: 0 | Y18: =V18-X18 -> 3 | Z18: 02 | AA18: 3 | AB18: 9 | AC18: 8 | AD18: 1 | AE18: 1 | AG18: =AF18+AE18+AD18+AC18+AB18+AA18 -> 22 | AJ18: =AG18-AI18 -> 22 | AK18: 02 | AL18: 216 | AM18: 214 | AN18: 123 | AO18: 138 | AP18: 212 | AQ18: =AP18+AO18+AN18+AM18+AL18 -> 903 | AS18: 0 | AT18: =AQ18-AS18 -> 903
B19: 26/003 | C19: 179400 | D19: 215650 | E19: 84400 | F19: 121900 | G19: 227900 | H19: =SUM(C19:G19) -> 829250 | I19: 03 | J19: 637758.33 | K19: 191500 | L19: -8.33 | M19: =SUM(J19:L19) -> 829250 | N19: =H19-M19 -> 0 | V19: =U19+T19+S19+R19+Q19 -> 0 | X19: 0 | Y19: =V19-X19 -> 0 | Z19: 03 | AA19: 1 | AB19: 10 | AC19: 7 | AE19: 4 | AG19: =AF19+AE19+AD19+AC19+AB19+AA19 -> 22 | AJ19: =AG19-AI19 -> 22 | AK19: 03 | AL19: 99 | AM19: 127 | AN19: 63 | AO19: 73 | AP19: 112 | AQ19: =AP19+AO19+AN19+AM19+AL19 -> 474 | AS19: 0 | AT19: =AQ19-AS19 -> 474
B20: 26/004 | C20: 108050 | D20: 205250 | E20: 111400 | F20: 164500 | G20: 267300 | H20: =SUM(C20:G20) -> 856500 | I20: 04 | J20: 972900 | L20: -120400 | M20: =SUM(J20:L20) -> 852500 | N20: =H20-M20 -> 4000 | R20: 2 | U20: 1 | V20: =U20+T20+S20+R20+Q20 -> 3 | X20: 0 | Y20: =V20-X20 -> 3 | Z20: 04 | AA20: 1 | AB20: 10 | AC20: 13 | AD20: 2 | AE20: 4 | AG20: =AF20+AE20+AD20+AC20+AB20+AA20 -> 30 | AJ20: =AG20-AI20 -> 30 | AK20: 04 | AL20: 73 | AM20: 112 | AN20: 68 | AO20: 104 | AP20: 138 | AQ20: =AP20+AO20+AN20+AM20+AL20 -> 495 | AS20: 0 | AT20: =AQ20-AS20 -> 495
B21: 26/005 | C21: 157500 | D21: 166500 | E21: 135000 | F21: 137600 | G21: 83900 | H21: =SUM(C21:G21) -> 680500 | I21: 05 | J21: 428400 | K21: 252100 | M21: =SUM(J21:L21) -> 680500 | N21: =H21-M21 -> 0 | Q21: 1 | T21: 1 | V21: =U21+T21+S21+R21+Q21 -> 2 | X21: 0 | Y21: =V21-X21 -> 2 | Z21: 05 | AA21: 3 | AB21: 2 | AC21: 3 | AD21: 2 | AG21: =AF21+AE21+AD21+AC21+AB21+AA21 -> 10 | AJ21: =AG21-AI21 -> 10 | AK21: 05 | AL21: 75 | AM21: 75 | AN21: 47 | AO21: 51 | AP21: 48 | AQ21: =AP21+AO21+AN21+AM21+AL21 -> 296 | AS21: 0 | AT21: =AQ21-AS21 -> 296
B22: 26/006 | C22: 184800 | D22: 172750 | E22: 66897 | F22: 164000 | G22: 225379 | H22: =SUM(C22:G22) -> 813826 | I22: 06 | J22: 467250 | K22: 346600 | L22: -24 | M22: =SUM(J22:L22) -> 813826 | N22: =H22-M22 -> 0 | R22: 1 | U22: 1 | V22: =U22+T22+S22+R22+Q22 -> 2 | X22: 0 | Y22: =V22-X22 -> 2 | Z22: 06 | AA22: 9 | AB22: 9 | AC22: 8 | AD22: 2 | AE22: 4 | AG22: =AF22+AE22+AD22+AC22+AB22+AA22 -> 32 | AJ22: =AG22-AI22 -> 32 | AK22: 06 | AL22: 110 | AM22: 126 | AN22: 41 | AO22: 91 | AP22: 147 | AQ22: =AP22+AO22+AN22+AM22+AL22 -> 515 | AS22: 0 | AT22: =AQ22-AS22 -> 515
B23: 26/007 | C23: 248050 | D23: 175550 | E23: 110700 | F23: 115700 | G23: 243750 | H23: =SUM(C23:G23) -> 893750 | I23: 07 | J23: 700000 | K23: 193800 | L23: -50 | M23: =SUM(J23:L23) -> 893750 | N23: =H23-M23 -> 0 | V23: =U23+T23+S23+R23+Q23 -> 0 | X23: 0 | Y23: =V23-X23 -> 0 | Z23: 07 | AA23: 2 | AB23: 2 | AC23: 3 | AD23: 1 | AE23: 2 | AG23: =AF23+AE23+AD23+AC23+AB23+AA23 -> 10 | AJ23: =AG23-AI23 -> 10 | AK23: 07 | AL23: 121 | AM23: 102 | AN23: 58 | AO23: 73 | AP23: 153 | AQ23: =AP23+AO23+AN23+AM23+AL23 -> 507 | AS23: 0 | AT23: =AQ23-AS23 -> 507
B24: 26/008 | H24: =SUM(C24:G24) -> 0 | I24: 08 | M24: =SUM(J24:L24) -> 0 | N24: =H24-M24 -> 0 | V24: =U24+T24+S24+R24+Q24 -> 0 | X24: 0 | Y24: =V24-X24 -> 0 | Z24: 08 | AG24: =AF24+AE24+AD24+AC24+AB24+AA24 -> 0 | AJ24: =AG24-AI24 -> 0 | AK24: 08 | AQ24: =AP24+AO24+AN24+AM24+AL24 -> 0 | AS24: 0 | AT24: =AQ24-AS24 -> 0
B25: 26/009 | C25: 133900 | D25: 138100 | E25: 63900 | F25: 77900 | G25: 193400 | H25: =SUM(C25:G25) -> 607200 | I25: 09 | J25: 584500 | K25: 22700 | M25: =SUM(J25:L25) -> 607200 | N25: =H25-M25 -> 0 | Q25: 1 | U25: 1 | V25: =U25+T25+S25+R25+Q25 -> 2 | X25: 0 | Y25: =V25-X25 -> 2 | Z25: 09 | AA25: 1 | AB25: 3 | AC25: 8 | AE25: 2 | AG25: =AF25+AE25+AD25+AC25+AB25+AA25 -> 14 | AJ25: =AG25-AI25 -> 14 | AK25: 09 | AL25: 61 | AM25: 93 | AN25: 46 | AO25: 63 | AP25: 102 | AQ25: =AP25+AO25+AN25+AM25+AL25 -> 365 | AS25: 0 | AT25: =AQ25-AS25 -> 365
B26: 26/010 | H26: =SUM(C26:G26) -> 0 | I26: 10 | M26: =SUM(J26:L26) -> 0 | N26: =H26-M26 -> 0 | V26: =U26+T26+S26+R26+Q26 -> 0 | X26: 0 | Y26: =V26-X26 -> 0 | Z26: 10 | AG26: =AF26+AE26+AD26+AC26+AB26+AA26 -> 0 | AJ26: =AG26-AI26 -> 0 | AK26: 10 | AQ26: =AP26+AO26+AN26+AM26+AL26 -> 0 | AS26: 0 | AT26: =AQ26-AS26 -> 0
B27: 26/011 | C27: 58900 | D27: 60700 | E27: 36300 | F27: 26400 | G27: 82200 | H27: =SUM(C27:G27) -> 264500 | I27: 11 | J27: 307300 | L27: -42800 | M27: =SUM(J27:L27) -> 264500 | N27: =H27-M27 -> 0 | Q27: 1 | T27: 1 | V27: =U27+T27+S27+R27+Q27 -> 2 | X27: 0 | Y27: =V27-X27 -> 2 | Z27: 11 | AA27: 4 | AB27: 6 | AC27: 1 | AD27: 2 | AE27: 1 | AG27: =AF27+AE27+AD27+AC27+AB27+AA27 -> 14 | AJ27: =AG27-AI27 -> 14 | AK27: 11 | AL27: 49 | AM27: 57 | AN27: 32 | AO27: 22 | AP27: 53 | AQ27: =AP27+AO27+AN27+AM27+AL27 -> 213 | AS27: 0 | AT27: =AQ27-AS27 -> 213
B28: 26/012 | C28: 122000 | D28: 172300 | E28: 84400 | F28: 120700 | G28: 215700 | H28: =SUM(C28:G28) -> 715100 | I28: 12 | J28: 756800 | L28: -41700 | M28: =SUM(J28:L28) -> 715100 | N28: =H28-M28 -> 0 | Q28: 2 | V28: =U28+T28+S28+R28+Q28 -> 2 | X28: 0 | Y28: =V28-X28 -> 2 | Z28: 12 | AA28: 4 | AB28: 11 | AC28: 12 | AD28: 1 | AE28: 2 | AG28: =AF28+AE28+AD28+AC28+AB28+AA28 -> 30 | AJ28: =AG28-AI28 -> 30 | AK28: 12 | AL28: 94 | AM28: 121 | AN28: 74 | AO28: 96 | AP28: 134 | AQ28: =AP28+AO28+AN28+AM28+AL28 -> 519 | AS28: 0 | AT28: =AQ28-AS28 -> 519
B29: 26/013 | C29: 162300 | D29: 225100 | E29: 135700 | F29: 91600 | G29: 173900 | H29: =SUM(C29:G29) -> 788600 | I29: 13 | J29: 360500 | K29: 428100 | M29: =SUM(J29:L29) -> 788600 | N29: =H29-M29 -> 0 | Q29: 1 | R29: 2 | T29: 4 | U29: 1 | V29: =U29+T29+S29+R29+Q29 -> 8 | X29: 0 | Y29: =V29-X29 -> 8 | Z29: 13 | AA29: 3 | AB29: 6 | AC29: 3 | AD29: 1 | AG29: =AF29+AE29+AD29+AC29+AB29+AA29 -> 13 | AJ29: =AG29-AI29 -> 13 | AK29: 13 | AL29: 85 | AM29: 94 | AN29: 68 | AO29: 45 | AP29: 89 | AQ29: =AP29+AO29+AN29+AM29+AL29 -> 381 | AS29: 0 | AT29: =AQ29-AS29 -> 381
B30: 26/014 | C30: 86700 | D30: 66600 | E30: 56000 | F30: 71000 | G30: 88600 | H30: =SUM(C30:G30) -> 368900 | I30: 14 | J30: 51800 | K30: 275400 | L30: 41700 | M30: =SUM(J30:L30) -> 368900 | N30: =H30-M30 -> 0 | R30: 1 | V30: =U30+T30+S30+R30+Q30 -> 1 | X30: 0 | Y30: =V30-X30 -> 1 | Z30: 14 | AD30: 2 | AE30: 1 | AG30: =AF30+AE30+AD30+AC30+AB30+AA30 -> 3 | AJ30: =AG30-AI30 -> 3 | AK30: 14 | AL30: 62 | AM30: 44 | AN30: 46 | AO30: 46 | AP30: 59 | AQ30: =AP30+AO30+AN30+AM30+AL30 -> 257 | AS30: 0 | AT30: =AQ30-AS30 -> 257
B31: 26/015 | H31: =SUM(C31:G31) -> 0 | I31: 15 | M31: =SUM(J31:L31) -> 0 | N31: =H31-M31 -> 0 | Q31: 1 | V31: =U31+T31+S31+R31+Q31 -> 1 | X31: 0 | Y31: =V31-X31 -> 1 | Z31: 15 | AG31: =AF31+AE31+AD31+AC31+AB31+AA31 -> 0 | AJ31: =AG31-AI31 -> 0 | AK31: 15 | AQ31: =AP31+AO31+AN31+AM31+AL31 -> 0 | AS31: 0 | AT31: =AQ31-AS31 -> 0
B32: 26/016 | C32: 154400 | D32: 168100 | E32: 91600 | F32: 106000 | G32: 158900 | H32: =SUM(C32:G32) -> 679000 | I32: 16 | J32: 273000 | K32: 406000 | M32: =SUM(J32:L32) -> 679000 | N32: =H32-M32 -> 0 | V32: =U32+T32+S32+R32+Q32 -> 0 | X32: 0 | Y32: =V32-X32 -> 0 | Z32: 16 | AA32: 2 | AB32: 3 | AC32: 3 | AG32: =AF32+AE32+AD32+AC32+AB32+AA32 -> 8 | AJ32: =AG32-AI32 -> 8 | AK32: 16 | AL32: 106 | AM32: 115 | AN32: 65 | AO32: 54 | AP32: 106 | AQ32: =AP32+AO32+AN32+AM32+AL32 -> 446 | AS32: 0 | AT32: =AQ32-AS32 -> 446
B33: 26/017 | C33: 54900 | D33: 55600 | E33: 12600 | F33: 33700 | G33: 38800 | H33: =SUM(C33:G33) -> 195600 | I33: 17 | J33: 305900 | L33: -110300 | M33: =SUM(J33:L33) -> 195600 | N33: =H33-M33 -> 0 | V33: =U33+T33+S33+R33+Q33 -> 0 | X33: 0 | Y33: =V33-X33 -> 0 | Z33: 17 | AA33: 2 | AB33: 5 | AE33: 1 | AG33: =AF33+AE33+AD33+AC33+AB33+AA33 -> 8 | AJ33: =AG33-AI33 -> 8 | AK33: 17 | AL33: 40 | AM33: 43 | AN33: 13 | AO33: 22 | AP33: 32 | AQ33: =AP33+AO33+AN33+AM33+AL33 -> 150 | AS33: 0 | AT33: =AQ33-AS33 -> 150
B34: 26/018 | H34: =SUM(C34:G34) -> 0 | I34: 18 | M34: =SUM(J34:L34) -> 0 | N34: =H34-M34 -> 0 | V34: =U34+T34+S34+R34+Q34 -> 0 | X34: 0 | Y34: =V34-X34 -> 0 | Z34: 18 | AG34: =AF34+AE34+AD34+AC34+AB34+AA34 -> 0 | AJ34: =AG34-AI34 -> 0 | AK34: 18 | AQ34: =AP34+AO34+AN34+AM34+AL34 -> 0 | AS34: 0 | AT34: =AQ34-AS34 -> 0
B35: 26/019 | H35: =SUM(C35:G35) -> 0 | I35: 19 | M35: =SUM(J35:L35) -> 0 | N35: =H35-M35 -> 0 | V35: =U35+T35+S35+R35+Q35 -> 0 | X35: 0 | Y35: =V35-X35 -> 0 | Z35: 19 | AG35: =AF35+AE35+AD35+AC35+AB35+AA35 -> 0 | AJ35: =AG35-AI35 -> 0 | AK35: 19 | AQ35: =AP35+AO35+AN35+AM35+AL35 -> 0 | AS35: 0 | AT35: =AQ35-AS35 -> 0
C37: =SUM(C13:C35) -> 2668450 | D37: =SUM(D13:D35) -> 2695450 | E37: =SUM(E13:E35) -> 1377897 | F37: =SUM(F13:F35) -> 1642250 | G37: =SUM(G13:G35) -> 2672084 | H37: =SUM(H13:H35) -> 11056131 | J37: =SUM(J13:J35) -> 9073708.3 | K37: =SUM(K13:K36) -> 2886700 | L37: =SUM(L14:L35) -> -904882.33 | M37: =SUM(M13:M35) -> 11052126 | Q37: TOTAL ANULADAS | U37: =SUM(V13:V35) -> 30 | X37: =SUM(X13:X35) -> 0 | AA37: TOTAL PREMIADAS | AF37: =SUM(AG13:AG35) -> 269 | AI37: =SUM(AI13:AI35) -> 0 | AL37: TOTAL VENDIDAS | AP37: =SUM(AQ13:AQ35) -> 6676 | AS37: =SUM(AS13:AS35) -> 0
B39: DEBEN / SALIDA | J39: PAGAN / ENTRADA
B41: MARTIN GASTOS | D41: 0 | E41: DEPOSITOS | H41: =D42+C73 -> 9073708.3 | J41: DEUDA DE CAJA s/l/v | L41: 0 | M41: EXCEDENTE | N41: 0
B42: PREMIOS | D42: =J37 -> 9073708.3 | E42: PREST. PALP. | H42: 0 | J42: FALTANTE DE CAJA | L42: 0 | M42: MARTIN | N42: 0
B43: LIBRERIA | D43: 0 | E43: PREST. TELEKINO | H43: 0 | J43: PREST. PALP./ REVISTA | L43: 0 | M43: PREMIOS | N43: 0
B44: LIMPIEZA | D44: 0 | E44: PREST. JGOS. MENORES | H44: 0 | J44: PREST. TELEKINO | L44: 0 | N44: 0
B45: SODA/AGUA | D45: 0 | E45: IMPUESTOS | H45: 0 | J45: PREST. JGOS. MENORES | L45: 0 | N45: 0
B46: GASTOS VARIOS | D46: 0 | E46: OTROS | H46: =SUM(N13:N35) -> 4005 | L46: 0 | N46: 0
B48: SUB TOTAL | D48: =D41+D42+D43+D44+D45+D46+H42+H43+H44+H45+H46 -> 9077713.3 | G48: TOTAL | H48: =D48+H41 -> 18151422 | M48: SUB TOTAL | N48: =L41+L42+L43+L44+L45+L46+N41+N42+N43+N44+N45+N46 -> 0
C50: DETALLE RECAUDACION DE CAJA | H50: IMPORTE | J50: FECHA | L50: DETALLE CIERRE DE CAJA
C52: 20000 x | D52: 40 | E52: =20000*D52 -> 800000 | I52: MAT | L52: 20000 x | M52: 133 | N52: =20000*M52 -> 2660000
C53: 10000 x | D53: 117 | E53: =10000*D53 -> 1170000 | I53: MAT | L53: 10000 x | M53: 345 | N53: =10000*M53 -> 3450000
C54: 2000 x | D54: 253 | E54: =2000*D54 -> 506000 | I54: MAT | L54: 2000 x | M54: 113 | N54: =2000*M54 -> 226000
C55: 1000 x | D55: 414 | E55: =1000*D55 -> 414000 | I55: MAT | L55: 1000 x | M55: 1265 | N55: =1000*M55 -> 1265000
C56: 500 x | D56: 65 | E56: =500*D56 -> 32500 | I56: MAT | K56: =SUM(H52:H56) -> 0 | L56: 500 x | M56: 141 | N56: =500*M56 -> 70500
C57: 200 x | D57: 13 | E57: =200*D57 -> 2600 | I57: VEP | L57: 200 x | M57: 35 | N57: =200*M57 -> 7000
C58: 100 x | D58: 33 | E58: =100*D58 -> 3300 | I58: VEP | L58: 100 x | M58: 1 | N58: =100*M58 -> 100
C59: 50 x | D59: 0 | E59: =50*D59 -> 0 | I59: VEP | L59: 50 x | M59: 1808 | N59: =50*M59 -> 90400
C60: 20 x | D60: 0 | E60: =20*D60 -> 0 | I60: VEP | L60: 20 x | M60: 1512 | N60: =20*M60 -> 30240
C61: 10 x | D61: 0 | E61: =10*D61 -> 0 | I61: VEP | K61: =SUM(H57:H61) -> 0 | L61: 10 x | M61: 360 | N61: =10*M61 -> 3600
C62: 5 x | D62: 0 | E62: =5*D62 -> 0 | I62: TAR | L62: 5 x | M62: 0 | N62: =5*M62 -> 0
C63: 2 x | D63: 0 | E63: =2*D63 -> 0 | I63: TAR | L63: 2 x | M63: 0 | N63: =2*M63 -> 0
C64: 1 x | D64: 0 | E64: =1*D64 -> 0 | I64: TAR | L64: 1 x | M64: 0 | N64: =1*M64 -> 0
C65: SUB - TOTAL | E65: =SUM(E52:F64) -> 2928400 | I65: TAR | L65: SUB - TOTAL | N65: =SUM(N52:N64) -> 7802840
I66: TAR | K66: =SUM(H62:H66) -> 0
D67: TOTAL | F67: =D48+F65 -> 9077713.3 | I67: NOC | L67: PREMOS | N67: 70000
I68: NOC | L68: TELEKINOS | N68: 0
D69: DIFERENCIA | F69: =F67-H37 -> -1978417.7 | I69: NOC | L69: BOL. S/PREMIOS | N69: 3115613.4
I70: NOC | L70: OTROS | N70: 0
C71: DEPOSITO | I71: NOC | M71: SUB- TOTAL | N71: =SUM(N67:N70) -> 3185613.4
I72: NOC | K72: =SUM(H67:H72) -> 0
C73: 0
H74: =SUM(H52:H72) -> 0 | M74: TOTAL | N74: =N65+N71 -> 10988453
L76: ARQUEO DE CAJA AL CIERRE (COMPOSICION DEL SALDO)
C77: TOTAL DE INGRESO | H77: =H9+H37+N48 -> 20065744 | L77: PREMIOS | N77: =N71 -> 3185613.4
L78: EFECTIVO | N78: =N65 -> 7802840
C79: TOTAL DE EGRESO | H79: =H74+H41+D41+D43+D44+D45+D46+H42+H43+H44+H45+H46 -> 9077713.3 | L79: TOTAL DE CAJA AL CIERRE | N79: =N71+N65 -> 10988453
C81: SALDO DEL DIA | H81: =H77-H79 -> 10988031 | L81: DIFERENCIA DE CAJA | N81: =N79-H81 -> 422.33
L82: (+) POSITIVO | M82: (-) NEGATIVO

Sheet 1301
D3: PLANILLA DE RECAUDACION DIARIA DE APUESTA Y PREMIOS | M3: ='0101'!M2 -> 2025
D5: FECHA : | E5: 45170 | G5: RECAUDACION DEL DIA: | I5: 45169
C7: 26 | D7: SALDO DEL DIA ANTERIOR | G7: PREMIOS | H7: ='1201'!N77 -> 3185613.4
G8: EFECTIVO | H8: ='1201'!N78 -> 7802840
G9: TOTAL | H9: =H7+H8 -> 10988453 | Q9: TICKET ANULADOS | AA9: TICKET PREMIADOS | AL9: TICKET VENDIDOS
B11: SUB | C11: MATUTINA | D11: VESPERT. | E11: SIESTA | F11: TARDE | G11: NOCT. | H11: TOTAL | J11: PREMIOS | K11: EFECTIVO | L11: MONEDAS | M11: TOTAL | N11: DIFER. | Q11: M | R11: V | S11: S | T11: T | U11: N | V11: TOTAL | X11: PRES. | Y11: DIFER. | AA11: ANT | AB11: M | AC11: V | AD11: S | AE11: T | AF11: N | AG11: TOTAL | AI11: PRES | AJ11: DIFER. | AL11: M | AM11: V | AN11: S | AO11: T | AP11: N | AQ11: TOTAL | AS11: PRES. | AT11: DIFER.
H12: =SUM(H13:H16) -> 1166200
B13: 001 | C13: 227500 | D13: 105850 | E13: 12250 | F13: 9200 | G13: 8000 | H13: =SUM(C13:G13) -> 362800 | I13: 001 | J13: 140000 | K13: 222800 | M13: =SUM(J13:L13) -> 362800 | N13: =H13-M13 -> 0 | Q13: 1 | V13: =U13+T13+S13+R13+Q13 -> 1 | X13: 0 | Y13: =V13-X13 -> 1 | Z13: V | AA13: 8 | AG13: =AF13+AE13+AD13+AC13+AB13+AA13 -> 8 | AI13: 0 | AJ13: =AG13-AI13 -> 8 | AL13: 130 | AM13: 58 | AN13: 11 | AO13: 5 | AP13: 3 | AQ13: =AP13+AO13+AN13+AM13+AL13 -> 207 | AS13: 0 | AT13: =AQ13-AS13 -> 207
B14: 002 | E14: 16200 | F14: 41200 | G14: 99600 | H14: =SUM(C14:G14) -> 157000 | I14: 002 | J14: 40000 | K14: 117000 | M14: =SUM(J14:L14) -> 157000 | N14: =H14-M14 -> 0 | V14: =U14+T14+S14+R14+Q14 -> 0 | X14: 0 | Y14: =V14-X14 -> 0 | Z14: L | AG14: =AF14+AE14+AD14+AC14+AB14+AA14 -> 0 | AJ14: =AG14-AI14 -> 0 | AN14: 6 | AO14: 11 | AP14: 42 | AQ14: =AP14+AO14+AN14+AM14+AL14 -> 59 | AS14: 0 | AT14: =AQ14-AS14 -> 59
B15: 003 | C15: 260500 | D15: 138300 | E15: 32900 | F15: 66000 | G15: 148700 | H15: =SUM(C15:G15) -> 646400 | I15: 003 | J15: 552200 | K15: 94200 | M15: =SUM(J15:L15) -> 646400 | N15: =H15-M15 -> 0 | Q15: 2 | U15: 1 | V15: =U15+T15+S15+R15+Q15 -> 3 | X15: 0 | Y15: =V15-X15 -> 3 | Z15: M | AA15: 5 | AB15: 2 | AC15: 3 | AG15: =AF15+AE15+AD15+AC15+AB15+AA15 -> 10 | AJ15: =AG15-AI15 -> 10 | AL15: 119 | AM15: 81 | AN15: 25 | AO15: 40 | AP15: 71 | AQ15: =AP15+AO15+AN15+AM15+AL15 -> 336 | AS15: 0 | AT15: =AQ15-AS15 -> 336
B16: 004 | H16: =SUM(C16:G16) -> 0 | I16: 004 | J16: 70000 | L16: -70000 | M16: =SUM(J16:L16) -> 0 | N16: =H16-M16 -> 0 | V16: =U16+T16+S16+R16+Q16 -> 0 | X16: 0 | Y16: =V16-X16 -> 0 | AG16: =AF16+AE16+AD16+AC16+AB16+AA16 -> 0 | AJ16: =AG16-AI16 -> 0 | AQ16: =AP16+AO16+AN16+AM16+AL16 -> 0 | AS16: 0 | AT16: =AQ16-AS16 -> 0
B17: 26/001 | C17: 208100 | D17: 101900 | E17: 33800 | F17: 57100 | G17: 93400 | H17: =SUM(C17:G17) -> 494300 | I17: 01 | J17: 806400 | L17: -312100 | M17: =SUM(J17:L17) -> 494300 | N17: =H17-M17 -> 0 | Q17: 2 | V17: =U17+T17+S17+R17+Q17 -> 2 | X17: 0 | Y17: =V17-X17 -> 2 | Z17: 01 | AA17: 5 | AB17: 2 | AC17: 3 | AG17: =AF17+AE17+AD17+AC17+AB17+AA17 -> 10 | AJ17: =AG17-AI17 -> 10 | AK17: 01 | AL17: 97 | AM17: 66 | AN17: 31 | AO17: 46 | AP17: 69 | AQ17: =AP17+AO17+AN17+AM17+AL17 -> 309 | AS17: 0 | AT17: =AQ17-AS17 -> 309
B18: 26/002 | C18: 418550 | D18: 379350 | E18: 240250 | F18: 271750 | G18: 369210 | H18: =SUM(C18:G18) -> 1679110 | I18: 02 | J18: 2603300 | L18: -924190 | M18: =SUM(J18:L18) -> 1679110 | N18: =H18-M18 -> 0 | U18: 1 | V18: =U18+T18+S18+R18+Q18 -> 1 | X18: 0 | Y18: =V18-X18 -> 1 | Z18: 02 | AA18: 5 | AB18: 15 | AC18: 6 | AE18: 2 | AG18: =AF18+AE18+AD18+AC18+AB18+AA18 -> 28 | AJ18: =AG18-AI18 -> 28 | AK18: 02 | AL18: 245 | AM18: 247 | AN18: 193 | AO18: 204 | AP18: 266 | AQ18: =AP18+AO18+AN18+AM18+AL18 -> 1155 | AS18: 0 | AT18: =AQ18-AS18 -> 1155
B19: 26/003 | C19: 265400 | D19: 183700 | E19: 101000 | F19: 99400 | G19: 190500 | H19: =SUM(C19:G19) -> 840000 | I19: 03 | J19: 240450 | K19: 599550 | M19: =SUM(J19:L19) -> 840000 | N19: =H19-M19 -> 0 | V19: =U19+T19+S19+R19+Q19 -> 0 | X19: 0 | Y19: =V19-X19 -> 0 | Z19: 03 | AA19: 2 | AC19: 3 | AD19: 2 | AE19: 3 | AG19: =AF19+AE19+AD19+AC19+AB19+AA19 -> 10 | AJ19: =AG19-AI19 -> 10 | AK19: 03 | AL19: 127 | AM19: 102 | AN19: 60 | AO19: 56 | AP19: 107 | AQ19: =AP19+AO19+AN19+AM19+AL19 -> 452 | AS19: 0 | AT19: =AQ19-AS19 -> 452
B20: 26/004 | C20: 190150 | D20: 150050 | E20: 146350 | F20: 148250 | G20: 360550 | H20: =SUM(C20:G20) -> 995350 | I20: 04 | J20: 582000 | K20: 403350 | M20: =SUM(J20:L20) -> 985350 | N20: =H20-M20 -> 10000 | T20: 2 | U20: 2 | V20: =U20+T20+S20+R20+Q20 -> 4 | X20: 0 | Y20: =V20-X20 -> 4 | Z20: 04 | AA20: 6 | AB20: 2 | AC20: 10 | AE20: 1 | AG20: =AF20+AE20+AD20+AC20+AB20+AA20 -> 19 | AJ20: =AG20-AI20 -> 19 | AK20: 04 | AL20: 107 | AM20: 93 | AN20: 82 | AO20: 93 | AP20: 182 | AQ20: =AP20+AO20+AN20+AM20+AL20 -> 557 | AS20: 0 | AT20: =AQ20-AS20 -> 557
B21: 26/005 | C21: 109000 | D21: 201100 | E21: 151000 | F21: 58000 | G21: 101700 | H21: =SUM(C21:G21) -> 620800 | I21: 05 | J21: 359300 | K21: 261500 | M21: =SUM(J21:L21) -> 620800 | N21: =H21-M21 -> 0 | T21: 1 | V21: =U21+T21+S21+R21+Q21 -> 1 | X21: 0 | Y21: =V21-X21 -> 1 | Z21: 05 | AA21: 4 | AB21: 1 | AC21: 4 | AE21: 1 | AG21: =AF21+AE21+AD21+AC21+AB21+AA21 -> 10 | AJ21: =AG21-AI21 -> 10 | AK21: 05 | AL21: 55 | AM21: 82 | AN21: 66 | AO21: 44 | AP21: 64 | AQ21: =AP21+AO21+AN21+AM21+AL21 -> 311 | AS21: 0 | AT21: =AQ21-AS21 -> 311
B22: 26/006 | C22: 219250 | D22: 249900 | E22: 104200 | F22: 141550 | G22: 263500 | H22: =SUM(C22:G22) -> 978400 | I22: 06 | J22: 638400 | K22: 340000 | M22: =SUM(J22:L22) -> 978400 | N22: =H22-M22 -> 0 | Q22: 4 | R22: 4 | V22: =U22+T22+S22+R22+Q22 -> 8 | X22: 0 | Y22: =V22-X22 -> 8 | Z22: 06 | AA22: 12 | AB22: 6 | AC22: 10 | AD22: 3 | AE22: 3 | AG22: =AF22+AE22+AD22+AC22+AB22+AA22 -> 34 | AJ22: =AG22-AI22 -> 34 | AK22: 06 | AL22: 135 | AM22: 148 | AN22: 75 | AO22: 95 | AP22: 154 | AQ22: =AP22+AO22+AN22+AM22+AL22 -> 607 | AS22: 0 | AT22: =AQ22-AS22 -> 607
B23: 26/007 | C23: 276450 | D23: 283600 | E23: 89550 | F23: 81200 | G23: 245200 | H23: =SUM(C23:G23) -> 976000 | I23: 07 | J23: 330400 | K23: 646600 | L23: -1000 | M23: =SUM(J23:L23) -> 976000 | N23: =H23-M23 -> 0 | V23: =U23+T23+S23+R23+Q23 -> 0 | X23: 0 | Y23: =V23-X23 -> 0 | Z23: 07 | AA23: 1 | AB23: 3 | AC23: 4 | AE23: 1 | AG23: =AF23+AE23+AD23+AC23+AB23+AA23 -> 9 | AJ23: =AG23-AI23 -> 9 | AK23: 07 | AL23: 163 | AM23: 158 | AN23: 58 | AO23: 52 | AP23: 135 | AQ23: =AP23+AO23+AN23+AM23+AL23 -> 566 | AS23: 0 | AT23: =AQ23-AS23 -> 566
B24: 26/008 | H24: =SUM(C24:G24) -> 0 | I24: 08 | M24: =SUM(J24:L24) -> 0 | N24: =H24-M24 -> 0 | V24: =U24+T24+S24+R24+Q24 -> 0 | X24: 0 | Y24: =V24-X24 -> 0 | Z24: 08 | AG24: =AF24+AE24+AD24+AC24+AB24+AA24 -> 0 | AJ24: =AG24-AI24 -> 0 | AK24: 08 | AQ24: =AP24+AO24+AN24+AM24+AL24 -> 0 | AS24: 0 | AT24: =AQ24-AS24 -> 0
B25: 26/009 | C25: 149000 | D25: 182200 | E25: 68700 | F25: 54100 | G25: 131100 | H25: =SUM(C25:G25) -> 585100 | I25: 09 | J25: 497700 | K25: 87400 | M25: =SUM(J25:L25) -> 585100 | N25: =H25-M25 -> 0 | T25: 1 | V25: =U25+T25+S25+R25+Q25 -> 1 | X25: 0 | Y25: =V25-X25 -> 1 | Z25: 09 | AA25: 6 | AB25: 1 | AC25: 3 | AG25: =AF25+AE25+AD25+AC25+AB25+AA25 -> 10 | AJ25: =AG25-AI25 -> 10 | AK25: 09 | AL25: 72 | AM25: 100 | AN25: 36 | AO25: 37 | AP25: 81 | AQ25: =AP25+AO25+AN25+AM25+AL25 -> 326 | AS25: 0 | AT25: =AQ25-AS25 -> 326
B26: 26/010 | H26: =SUM(C26:G26) -> 0 | I26: 10 | M26: =SUM(J26:L26) -> 0 | N26: =H26-M26 -> 0 | V26: =U26+T26+S26+R26+Q26 -> 0 | X26: 0 | Y26: =V26-X26 -> 0 | Z26: 10 | AG26: =AF26+AE26+AD26+AC26+AB26+AA26 -> 0 | AJ26: =AG26-AI26 -> 0 | AK26: 10 | AQ26: =AP26+AO26+AN26+AM26+AL26 -> 0 | AS26: 0 | AT26: =AQ26-AS26 -> 0
B27: 26/011 | C27: 89100 | D27: 60600 | E27: 51500 | F27: 34700 | G27: 142600 | H27: =SUM(C27:G27) -> 378500 | I27: 11 | J27: 441700 | L27: -63200 | M27: =SUM(J27:L27) -> 378500 | N27: =H27-M27 -> 0 | U27: 1 | V27: =U27+T27+S27+R27+Q27 -> 1 | X27: 0 | Y27: =V27-X27 -> 1 | Z27: 11 | AA27: 1 | AB27: 3 | AC27: 3 | AD27: 1 | AG27: =AF27+AE27+AD27+AC27+AB27+AA27 -> 8 | AJ27: =AG27-AI27 -> 8 | AK27: 11 | AL27: 65 | AM27: 44 | AN27: 34 | AO27: 37 | AP27: 74 | AQ27: =AP27+AO27+AN27+AM27+AL27 -> 254 | AS27: 0 | AT27: =AQ27-AS27 -> 254
B28: 26/012 | C28: 166430 | D28: 178730 | E28: 72850 | F28: 85450 | G28: 188950 | H28: =SUM(C28:G28) -> 692410 | I28: 12 | J28: 110600 | K28: 581800 | L28: 10 | M28: =SUM(J28:L28) -> 692410 | N28: =H28-M28 -> 0 | V28: =U28+T28+S28+R28+Q28 -> 0 | X28: 0 | Y28: =V28-X28 -> 0 | Z28: 12 | AA28: 3 | AB28: 1 | AC28: 2 | AE28: 2 | AG28: =AF28+AE28+AD28+AC28+AB28+AA28 -> 8 | AJ28: =AG28-AI28 -> 8 | AK28: 12 | AL28: 135 | AM28: 145 | AN28: 58 | AO28: 63 | AP28: 166 | AQ28: =AP28+AO28+AN28+AM28+AL28 -> 567 | AS28: 0 | AT28: =AQ28-AS28 -> 567
B29: 26/013 | C29: 225000 | D29: 208250 | E29: 148850 | F29: 100400 | G29: 275200 | H29: =SUM(C29:G29) -> 957700 | I29: 13 | J29: 85050 | K29: 872700 | L29: -50 | M29: =SUM(J29:L29) -> 957700 | N29: =H29-M29 -> 0 | R29: 1 | U29: 1 | V29: =U29+T29+S29+R29+Q29 -> 2 | X29: 0 | Y29: =V29-X29 -> 2 | Z29: 13 | AA29: 1 | AB29: 2 | AC29: 1 | AG29: =AF29+AE29+AD29+AC29+AB29+AA29 -> 4 | AJ29: =AG29-AI29 -> 4 | AK29: 13 | AL29: 111 | AM29: 94 | AN29: 63 | AO29: 44 | AP29: 103 | AQ29: =AP29+AO29+AN29+AM29+AL29 -> 415 | AS29: 0 | AT29: =AQ29-AS29 -> 415
B30: 26/014 | C30: 80200 | D30: 77700 | E30: 15900 | F30: 23700 | G30: 96400 | H30: =SUM(C30:G30) -> 293900 | I30: 14 | J30: 193789.47 | K30: 100100 | L30: 10.53 | M30: =SUM(J30:L30) -> 293900 | N30: =H30-M30 -> 0 | U30: 1 | V30: =U30+T30+S30+R30+Q30 -> 1 | X30: 0 | Y30: =V30-X30 -> 1 | Z30: 14 | AA30: 2 | AB30: 2 | AC30: 1 | AG30: =AF30+AE30+AD30+AC30+AB30+AA30 -> 5 | AJ30: =AG30-AI30 -> 5 | AK30: 14 | AL30: 61 | AM30: 53 | AN30: 13 | AO30: 15 | AP30: 62 | AQ30: =AP30+AO30+AN30+AM30+AL30 -> 204 | AS30: 0 | AT30: =AQ30-AS30 -> 204
B31: 26/015 | H31: =SUM(C31:G31) -> 0 | I31: 15 | M31: =SUM(J31:L31) -> 0 | N31: =H31-M31 -> 0 | V31: =U31+T31+S31+R31+Q31 -> 0 | X31: 0 | Y31: =V31-X31 -> 0 | Z31: 15 | AG31: =AF31+AE31+AD31+AC31+AB31+AA31 -> 0 | AJ31: =AG31-AI31 -> 0 | AK31: 15 | AQ31: =AP31+AO31+AN31+AM31+AL31 -> 0 | AS31: 0 | AT31: =AQ31-AS31 -> 0
B32: 26/016 | C32: 120900 | D32: 180500 | E32: 61400 | F32: 42450 | G32: 118950 | H32: =SUM(C32:G32) -> 524200 | I32: 16 | J32: 499333.33 | K32: 24900 | L32: -33.33 | M32: =SUM(J32:L32) -> 524200 | N32: =H32-M32 -> 0 | Q32: 1 | S32: 2 | U32: 1 | V32: =U32+T32+S32+R32+Q32 -> 4 | X32: 0 | Y32: =V32-X32 -> 4 | Z32: 16 | AA32: 3 | AB32: 2 | AC32: 1 | AE32: 2 | AG32: =AF32+AE32+AD32+AC32+AB32+AA32 -> 8 | AJ32: =AG32-AI32 -> 8 | AK32: 16 | AL32: 67 | AM32: 105 | AN32: 43 | AO32: 36 | AP32: 74 | AQ32: =AP32+AO32+AN32+AM32+AL32 -> 325 | AS32: 0 | AT32: =AQ32-AS32 -> 325
B33: 26/017 | C33: 75000 | D33: 66900 | E33: 20500 | F33: 21700 | G33: 57300 | H33: =SUM(C33:G33) -> 241400 | I33: 17 | J33: 79333.33 | K33: 51800 | L33: 110266.67 | M33: =SUM(J33:L33) -> 241400 | N33: =H33-M33 -> 0 | V33: =U33+T33+S33+R33+Q33 -> 0 | X33: 0 | Y33: =V33-X33 -> 0 | Z33: 17 | AA33: 2 | AB33: 3 | AC33: 3 | AE33: 2 | AG33: =AF33+AE33+AD33+AC33+AB33+AA33 -> 10 | AJ33: =AG33-AI33 -> 10 | AK33: 17 | AL33: 57 | AM33: 46 | AN33: 28 | AO33: 32 | AP33: 64 | AQ33: =AP33+AO33+AN33+AM33+AL33 -> 227 | AS33: 0 | AT33: =AQ33-AS33 -> 227
B34: 26/018 | H34: =SUM(C34:G34) -> 0 | I34: 18 | M34: =SUM(J34:L34) -> 0 | N34: =H34-M34 -> 0 | V34: =U34+T34+S34+R34+Q34 -> 0 | X34: 0 | Y34: =V34-X34 -> 0 | Z34: 18 | AG34: =AF34+AE34+AD34+AC34+AB34+AA34 -> 0 | AJ34: =AG34-AI34 -> 0 | AK34: 18 | AQ34: =AP34+AO34+AN34+AM34+AL34 -> 0 | AS34: 0 | AT34: =AQ34-AS34 -> 0
B35: 26/019 | H35: =SUM(C35:G35) -> 0 | I35: 19 | M35: =SUM(J35:L35) -> 0 | N35: =H35-M35 -> 0 | V35: =U35+T35+S35+R35+Q35 -> 0 | X35: 0 | Y35: =V35-X35 -> 0 | Z35: 19 | AG35: =AF35+AE35+AD35+AC35+AB35+AA35 -> 0 | AJ35: =AG35-AI35 -> 0 | AK35: 19 | AQ35: =AP35+AO35+AN35+AM35+AL35 -> 0 | AS35: 0 | AT35: =AQ35-AS35 -> 0
C37: =SUM(C13:C35) -> 3080530 | D37: =SUM(D13:D35) -> 2748630 | E37: =SUM(E13:E35) -> 1367200 | F37: =SUM(F13:F35) -> 1336150 | G37: =SUM(G13:G35) -> 2890860 | H37: =SUM(H13:H35) -> 11423370 | J37: =SUM(J13:J35) -> 8269956.1 | K37: =SUM(K13:K36) -> 4403700 | L37: =SUM(L14:L35) -> -1260286.1 | M37: =SUM(M13:M35) -> 11413370 | Q37: TOTAL ANULADAS | U37: =SUM(V13:V35) -> 29 | X37: =SUM(X13:X35) -> 0 | AA37: TOTAL PREMIADAS | AF37: =SUM(AG13:AG35) -> 191 | AI37: =SUM(AI13:AI35) -> 0 | AL37: TOTAL VENDIDAS | AP37: =SUM(AQ13:AQ35) -> 6877 | AS37: =SUM(AS13:AS35) -> 0
B39: DEBEN / SALIDA | J39: PAGAN / ENTRADA
B41: MARTIN GASTOS | D41: 0 | E41: DEPOSITOS | H41: =D42+C73 -> 10896483 | J41: DEUDA DE CAJA s/l/v | L41: 0 | M41: EXCEDENTE | N41: 0
B42: PREMIOS | D42: =J37 -> 8269956.1 | E42: PREST. PALP. | H42: 0 | J42: FALTANTE DE CAJA | L42: 0 | M42: MARTIN | N42: 0
B43: LIBRERIA | D43: 0 | E43: PREST. TELEKINO | H43: 0 | J43: PREST. PALP./ REVISTA | L43: 0 | M43: PREMIOS | N43: 0
B44: LIMPIEZA | D44: 0 | E44: PREST. JGOS. MENORES | H44: 0 | J44: PREST. TELEKINO | L44: 0 | N44: 0
B45: SODA/AGUA | D45: 0 | E45: IMPUESTOS | H45: 0 | J45: PREST. JGOS. MENORES | L45: 0 | N45: 0
B46: GASTOS VARIOS | D46: 0 | E46: OTROS | H46: =SUM(N13:N35) -> 10000 | L46: 0 | N46: 0
B48: SUB TOTAL | D48: =D41+D42+D43+D44+D45+D46+H42+H43+H44+H45+H46 -> 8279956.1 | G48: TOTAL | H48: =D48+H41 -> 19176439 | M48: SUB TOTAL | N48: =L41+L42+L43+L44+L45+L46+N41+N42+N43+N44+N45+N46 -> 0
C50: DETALLE RECAUDACION DE CAJA | H50: IMPORTE | J50: FECHA | L50: DETALLE CIERRE DE CAJA
C52: 20000 x | D52: 76 | E52: =20000*D52 -> 1520000 | I52: MAT | L52: 20000 x | M52: 74 | N52: =20000*M52 -> 1480000
C53: 10000 x | D53: 44 | E53: =10000*D53 -> 440000 | I53: MAT | L53: 10000 x | M53: 387 | N53: =10000*M53 -> 3870000
C54: 2000 x | D54: 287 | E54: =2000*D54 -> 574000 | I54: MAT | L54: 2000 x | M54: 87 | N54: =2000*M54 -> 174000
C55: 1000 x | D55: 567 | E55: =1000*D55 -> 567000 | I55: MAT | L55: 1000 x | M55: 81 | N55: =1000*M55 -> 81000
C56: 500 x | D56: 182 | E56: =500*D56 -> 91000 | I56: MAT | K56: =SUM(H52:H56) -> 0 | L56: 500 x | M56: 217 | N56: =500*M56 -> 108500
C57: 200 x | D57: 67 | E57: =200*D57 -> 13400 | I57: VEP | L57: 200 x | M57: 93 | N57: =200*M57 -> 18600
C58: 100 x | D58: 89 | E58: =100*D58 -> 8900 | I58: VEP | L58: 100 x | M58: 76 | N58: =100*M58 -> 7600
C59: 50 x | D59: 2 | E59: =50*D59 -> 100 | I59: VEP | L59: 50 x | M59: 1409 | N59: =50*M59 -> 70450
C60: 20 x | D60: 0 | E60: =20*D60 -> 0 | I60: VEP | L60: 20 x | M60: 1512 | N60: =20*M60 -> 30240
C61: 10 x | D61: 0 | E61: =10*D61 -> 0 | I61: VEP | K61: =SUM(H57:H61) -> 0 | L61: 10 x | M61: 362 | N61: =10*M61 -> 3620
C62: 5 x | D62: 0 | E62: =5*D62 -> 0 | I62: TAR | L62: 5 x | M62: 0 | N62: =5*M62 -> 0
C63: 2 x | D63: 0 | E63: =2*D63 -> 0 | I63: TAR | L63: 2 x | M63: 0 | N63: =2*M63 -> 0
C64: 1 x | D64: 0 | E64: =1*D64 -> 0 | I64: TAR | L64: 1 x | M64: 0 | N64: =1*M64 -> 0
C65: SUB - TOTAL | E65: =SUM(E52:F64) -> 3214400 | I65: TAR | L65: SUB - TOTAL | N65: =SUM(N52:N64) -> 5844010
I66: TAR | K66: =SUM(H62:H66) -> 0
D67: TOTAL | F67: =D48+E65 -> 11494356 | I67: NOC | L67: PREMOS | N67: 2527000
I68: NOC | L68: TELEKINOS | N68: 0
D69: DIFERENCIA | F69: =F67-H37 -> 70986.13 | I69: NOC | L69: BOL. S/PREMIOS | N69: 3115613.4
I70: NOC | L70: OTROS | N70: 0
C71: DEPOSITO | I71: NOC | M71: SUB- TOTAL | N71: =SUM(N67:N70) -> 5642613.4
I72: NOC | K72: =SUM(H67:H72) -> 0
C73: 2626526.5
H74: =SUM(H52:H72) -> 0 | M74: TOTAL | N74: =N65+N71 -> 11486623
L76: ARQUEO DE CAJA AL CIERRE (COMPOSICION DEL SALDO)
C77: TOTAL DE INGRESO | H77: =H9+H37+N48 -> 22411823 | L77: PREMIOS | N77: =N71 -> 5642613.4
L78: EFECTIVO | N78: =N65 -> 5844010
C79: TOTAL DE EGRESO | H79: =H74+H41+D41+D43+D44+D45+D46+H42+H43+H44+H45+H46 -> 10906483 | L79: TOTAL DE CAJA AL CIERRE | N79: =N71+N65 -> 11486623
C81: SALDO DEL DIA | H81: =H77-H79 -> 11505341 | L81: DIFERENCIA DE CAJA | N81: =N79-H81 -> -18717.33
L82: (+) POSITIVO | M82: (-) NEGATIVO

Sheet 1401
D3: PLANILLA DE RECAUDACION DIARIA DE APUESTA Y PREMIOS | M3: ='0101'!M2 -> 2025
D5: FECHA : | E5: 45170 | G5: RECAUDACION DEL DIA: | I5: 45169
C7: 26 | D7: SALDO DEL DIA ANTERIOR | G7: PREMIOS | H7: 0
G8: EFECTIVO | H8: 0
G9: TOTAL | H9: =H7+H8 -> 0 | Q9: TICKET ANULADOS | AA9: TICKET PREMIADOS | AL9: TICKET VENDIDOS
B11: SUB | C11: MATUTINA | D11: VESPERT. | E11: SIESTA | F11: TARDE | G11: NOCT. | H11: TOTAL | J11: PREMIOS | K11: EFECTIVO | L11: MONEDAS | M11: TOTAL | N11: DIFER. | Q11: M | R11: V | S11: S | T11: T | U11: N | V11: TOTAL | X11: PRES. | Y11: DIFER. | AA11: ANT | AB11: M | AC11: V | AD11: S | AE11: T | AF11: N | AG11: TOTAL | AI11: PRES | AJ11: DIFER. | AL11: M | AM11: V | AN11: S | AO11: T | AP11: N | AQ11: TOTAL | AS11: PRES. | AT11: DIFER.
H12: =SUM(H13:H16) -> 0
B13: 001 | H13: =SUM(C13:G13) -> 0 | I13: 001 | M13: =SUM(J13:L13) -> 0 | N13: =H13-M13 -> 0 | V13: =U13+T13+S13+R13+Q13 -> 0 | X13: 0 | Y13: =V13-X13 -> 0 | Z13: V | AG13: =AF13+AE13+AD13+AC13+AB13+AA13 -> 0 | AI13: 0 | AJ13: =AG13-AI13 -> 0 | AQ13: =AP13+AO13+AN13+AM13+AL13 -> 0 | AS13: 0 | AT13: =AQ13-AS13 -> 0
B14: 002 | H14: =SUM(C14:G14) -> 0 | I14: 002 | M14: =SUM(J14:L14) -> 0 | N14: =H14-M14 -> 0 | V14: =U14+T14+S14+R14+Q14 -> 0 | X14: 0 | Y14: =V14-X14 -> 0 | Z14: L | AG14: =AF14+AE14+AD14+AC14+AB14+AA14 -> 0 | AJ14: =AG14-AI14 -> 0 | AQ14: =AP14+AO14+AN14+AM14+AL14 -> 0 | AS14: 0 | AT14: =AQ14-AS14 -> 0
B15: 003 | H15: =SUM(C15:G15) -> 0 | I15: 003 | M15: =SUM(J15:L15) -> 0 | N15: =H15-M15 -> 0 | V15: =U15+T15+S15+R15+Q15 -> 0 | X15: 0 | Y15: =V15-X15 -> 0 | Z15: M | AG15: =AF15+AE15+AD15+AC15+AB15+AA15 -> 0 | AJ15: =AG15-AI15 -> 0 | AQ15: =AP15+AO15+AN15+AM15+AL15 -> 0 | AS15: 0 | AT15: =AQ15-AS15 -> 0
B16: 004 | H16: =SUM(C16:G16) -> 0 | I16: 004 | M16: =SUM(J16:L16) -> 0 | N16: =H16-M16 -> 0 | V16: =U16+T16+S16+R16+Q16 -> 0 | X16: 0 | Y16: =V16-X16 -> 0 | AG16: =AF16+AE16+AD16+AC16+AB16+AA16 -> 0 | AJ16: =AG16-AI16 -> 0 | AQ16: =AP16+AO16+AN16+AM16+AL16 -> 0 | AS16: 0 | AT16: =AQ16-AS16 -> 0
B17: 26/001 | H17: =SUM(C17:G17) -> 0 | I17: 01 | M17: =SUM(J17:L17) -> 0 | N17: =H17-M17 -> 0 | V17: =U17+T17+S17+R17+Q17 -> 0 | X17: 0 | Y17: =V17-X17 -> 0 | Z17: 01 | AG17: =AF17+AE17+AD17+AC17+AB17+AA17 -> 0 | AJ17: =AG17-AI17 -> 0 | AK17: 01 | AQ17: =AP17+AO17+AN17+AM17+AL17 -> 0 | AS17: 0 | AT17: =AQ17-AS17 -> 0
B18: 26/002 | H18: =SUM(C18:G18) -> 0 | I18: 02 | M18: =SUM(J18:L18) -> 0 | N18: =H18-M18 -> 0 | V18: =U18+T18+S18+R18+Q18 -> 0 | X18: 0 | Y18: =V18-X18 -> 0 | Z18: 02 | AG18: =AF18+AE18+AD18+AC18+AB18+AA18 -> 0 | AJ18: =AG18-AI18 -> 0 | AK18: 02 | AQ18: =AP18+AO18+AN18+AM18+AL18 -> 0 | AS18: 0 | AT18: =AQ18-AS18 -> 0
B19: 26/003 | H19: =SUM(C19:G19) -> 0 | I19: 03 | M19: =SUM(J19:L19) -> 0 | N19: =H19-M19 -> 0 | V19: =U19+T19+S19+R19+Q19 -> 0 | X19: 0 | Y19: =V19-X19 -> 0 | Z19: 03 | AG19: =AF19+AE19+AD19+AC19+AB19+AA19 -> 0 | AJ19: =AG19-AI19 -> 0 | AK19: 03 | AQ19: =AP19+AO19+AN19+AM19+AL19 -> 0 | AS19: 0 | AT19: =AQ19-AS19 -> 0
B20: 26/004 | H20: =SUM(C20:G20) -> 0 | I20: 04 | M20: =SUM(J20:L20) -> 0 | N20: =H20-M20 -> 0 | V20: =U20+T20+S20+R20+Q20 -> 0 | X20: 0 | Y20: =V20-X20 -> 0 | Z20: 04 | AG20: =AF20+AE20+AD20+AC20+AB20+AA20 -> 0 | AJ20: =AG20-AI20 -> 0 | AK20: 04 | AQ20: =AP20+AO20+AN20+AM20+AL20 -> 0 | AS20: 0 | AT20: =AQ20-AS20 -> 0
B21: 26/005 | H21: =SUM(C21:G21) -> 0 | I21: 05 | M21: =SUM(J21:L21) -> 0 | N21: =H21-M21 -> 0 | V21: =U21+T21+S21+R21+Q21 -> 0 | X21: 0 | Y21: =V21-X21 -> 0 | Z21: 05 | AG21: =AF21+AE21+AD21+AC21+AB21+AA21 -> 0 | AJ21: =AG21-AI21 -> 0 | AK21: 05 | AQ21: =AP21+AO21+AN21+AM21+AL21 -> 0 | AS21: 0 | AT21: =AQ21-AS21 -> 0
B22: 26/006 | H22: =SUM(C22:G22) -> 0 | I22: 06 | M22: =SUM(J22:L22) -> 0 | N22: =H22-M22 -> 0 | V22: =U22+T22+S22+R22+Q22 -> 0 | X22: 0 | Y22: =V22-X22 -> 0 | Z22: 06 | AG22: =AF22+AE22+AD22+AC22+AB22+AA22 -> 0 | AJ22: =AG22-AI22 -> 0 | AK22: 06 | AQ22: =AP22+AO22+AN22+AM22+AL22 -> 0 | AS22: 0 | AT22: =AQ22-AS22 -> 0
B23: 26/007 | H23: =SUM(C23:G23) -> 0 | I23: 07 | M23: =SUM(J23:L23) -> 0 | N23: =H23-M23 -> 0 | V23: =U23+T23+S23+R23+Q23 -> 0 | X23: 0 | Y23: =V23-X23 -> 0 | Z23: 07 | AG23: =AF23+AE23+AD23+AC23+AB23+AA23 -> 0 | AJ23: =AG23-AI23 -> 0 | AK23: 07 | AQ23: =AP23+AO23+AN23+AM23+AL23 -> 0 | AS23: 0 | AT23: =AQ23-AS23 -> 0
B24: 26/008 | H24: =SUM(C24:G24) -> 0 | I24: 08 | M24: =SUM(J24:L24) -> 0 | N24: =H24-M24 -> 0 | V24: =U24+T24+S24+R24+Q24 -> 0 | X24: 0 | Y24: =V24-X24 -> 0 | Z24: 08 | AG24: =AF24+AE24+AD24+AC24+AB24+AA24 -> 0 | AJ24: =AG24-AI24 -> 0 | AK24: 08 | AQ24: =AP24+AO24+AN24+AM24+AL24 -> 0 | AS24: 0 | AT24: =AQ24-AS24 -> 0
B25: 26/009 | H25: =SUM(C25:G25) -> 0 | I25: 09 | M25: =SUM(J25:L25) -> 0 | N25: =H25-M25 -> 0 | V25: =U25+T25+S25+R25+Q25 -> 0 | X25: 0 | Y25: =V25-X25 -> 0 | Z25: 09 | AG25: =AF25+AE25+AD25+AC25+AB25+AA25 -> 0 | AJ25: =AG25-AI25 -> 0 | AK25: 09 | AQ25: =AP25+AO25+AN25+AM25+AL25 -> 0 | AS25: 0 | AT25: =AQ25-AS25 -> 0
B26: 26/010 | H26: =SUM(C26:G26) -> 0 | I26: 10 | M26: =SUM(J26:L26) -> 0 | N26: =H26-M26 -> 0 | V26: =U26+T26+S26+R26+Q26 -> 0 | X26: 0 | Y26: =V26-X26 -> 0 | Z26: 10 | AG26: =AF26+AE26+AD26+AC26+AB26+AA26 -> 0 | AJ26: =AG26-AI26 -> 0 | AK26: 10 | AQ26: =AP26+AO26+AN26+AM26+AL26 -> 0 | AS26: 0 | AT26: =AQ26-AS26 -> 0
B27: 26/011 | H27: =SUM(C27:G27) -> 0 | I27: 11 | M27: =SUM(J27:L27) -> 0 | N27: =H27-M27 -> 0 | V27: =U27+T27+S27+R27+Q27 -> 0 | X27: 0 | Y27: =V27-X27 -> 0 | Z27: 11 | AG27: =AF27+AE27+AD27+AC27+AB27+AA27 -> 0 | AJ27: =AG27-AI27 -> 0 | AK27: 11 | AQ27: =AP27+AO27+AN27+AM27+AL27 -> 0 | AS27: 0 | AT27: =AQ27-AS27 -> 0
B28: 26/012 | H28: =SUM(C28:G28) -> 0 | I28: 12 | M28: =SUM(J28:L28) -> 0 | N28: =H28-M28 -> 0 | V28: =U28+T28+S28+R28+Q28 -> 0 | X28: 0 | Y28: =V28-X28 -> 0 | Z28: 12 | AG28: =AF28+AE28+AD28+AC28+AB28+AA28 -> 0 | AJ28: =AG28-AI28 -> 0 | AK28: 12 | AQ28: =AP28+AO28+AN28+AM28+AL28 -> 0 | AS28: 0 | AT28: =AQ28-AS28 -> 0
